lab1/vending_machine/vending_machine_def.v
// Title         : vending_machine_def.v
// Author      : Jae-Eon Jo (Jojaeeon@postech.ac.kr) 
//					Dongup Kwon (nankdu7@postech.ac.kr)

// Macro constants (prefix k & CamelCase)
`define kTotalBits 32
  
`define kItemBits 8
`define kNumItems 4

`define kCoinBits 8
`define kNumCoins 3

`define kWaitTime 10

`define S0_init 32'h00
`define S1_wait 32'h01
`define S2_select 32'h02
`define S3_return 32'h03

lab1/vending_machine/change_state.v
`include "vending_machine_def.v"


module change_state(clk,reset_n,current_total_nxt,current_total);

	input clk;
	input reset_n;
	input [`kTotalBits-1:0] current_total_nxt;
	output reg [`kTotalBits-1:0] current_total;
	
	// Sequential circuit to reset or update the states
	always @(posedge clk ) begin
		if (!reset_n) begin
			// TODO: reset all states.

			//reset current_total(0)
			current_total <= `kTotalBits'b0;
		end
		else begin
			// TODO: update all states.
			
			// update current_total to current_total_nxt
			current_total <= current_total_nxt;
		end
	end
endmodule

lab1/vending_machine/calculate_current_state.v

`include "vending_machine_def.v"
	

module calculate_current_state(i_input_coin,i_select_item,i_trigger_return,item_price,coin_value,current_total,
relative_money,current_total_nxt,wait_time,o_return_coin,o_available_item,o_output_item);

	input i_trigger_return;
	
	input [`kNumCoins-1:0] i_input_coin,o_return_coin;
	input [`kNumItems-1:0]	i_select_item;			
	input [31:0] item_price [`kNumItems-1:0];
	input [31:0] coin_value [`kNumCoins-1:0];	
	input [`kTotalBits-1:0] current_total;
	input [31:0] wait_time;
	output reg [`kNumItems-1:0] o_available_item,o_output_item;
	output [`kTotalBits-1:0] relative_money;
	output reg  [`kTotalBits-1:0] current_total_nxt;
	integer i;	

	reg  [`kTotalBits-1:0] input_total, output_total, return_total;

	initial begin
		input_total = 0;
		output_total = 0;
		return_total = 0;
	end

	assign relative_money = input_total - output_total - return_total;

	// Combinational logic for the next states
	always @(*) begin
		
		// if (current_total == `S4_return && relative_money == 0)
		// 	current_total_nxt = `S0_init;
		// else if (i_input_coin > 0)
		// 	current_total_nxt = `S2_coin;
		// else if (wait_time == 0 || i_trigger_return)
		// 	current_total_nxt = `S4_return;
		// else if (i_select_item > 0)
		// 	current_total_nxt = `S3_select;
		// else 
		// 	current_total_nxt = `S1_wait;

		//maybe we can use this logic also.

		case (current_total)
			`S0_init:
				if (i_input_coin > 0) 
					current_total_nxt = `S2_coin;
				else 
					current_total_nxt = `S1_wait;
			`S1_wait:
				if (i_input_coin > 0) 
					current_total_nxt = `S2_coin;
				else if (i_select_item > 0) 
					current_total_nxt = `S3_select;
				else if (wait_time == 0 || i_trigger_return)
					current_total_nxt = `S4_return;
			`S2_coin:
				current_total_nxt = `S1_wait;
			`S3_select:
				current_total_nxt = `S1_wait;
			`S4_return:
				if (relative_money == 0)
					current_total_nxt = `S0_init;
		endcase
		
	end

	
	
	// Combinational logic for the outputs
	always @(*) begin
		case (current_total)
			`S0_init: begin
				input_total = 0;
				output_total = 0;
				return_total = 0;
			end
			`S1_wait: begin
				for (i = 0; i < `kNumItems; i = i + 1) begin
					if (input_total - output_total >= item_price[i])
						o_available_item[i] = 1;
					else
						o_available_item[i] = 0;
				end
			end
			`S2_coin: begin
				for (i = 0; i < `kNumCoins; i = i + 1) begin
					if (i_input_coin[i]) begin
						input_total = input_total + coin_value[i] / 2; //for result..
					end
				end
			end
			`S3_select: begin
				for (i = 0; i < `kNumItems; i = i+1) begin
					if (i_select_item[i] && o_available_item[i]) begin
						o_output_item[i] = 1;
						output_total = output_total + item_price[i] / 2; //for result..
					end
					else begin
						o_output_item[i] = 0;
					end
				end
			end
			`S4_return: begin
				for (i = 0; i < `kNumCoins; i = i + 1) begin
					if (o_return_coin[i]) begin
						return_total = return_total + coin_value[i];
					end
				end
			end
		endcase

	end
 
	


endmodule

lab1/vending_machine/check_time_and_coin.v
`include "vending_machine_def.v"

	

module check_time_and_coin(i_input_coin,i_select_item,coin_value,o_available_item,relative_money,i_trigger_return,clk,reset_n,wait_time,o_return_coin);
	input clk;
	input reset_n;
	input i_trigger_return;
	input [31:0] coin_value [`kNumCoins-1:0];
	input [`kNumCoins-1:0] i_input_coin;
	input [`kNumItems-1:0]	i_select_item;
	input [`kNumItems-1:0] o_available_item;
	input [`kTotalBits-1:0] relative_money;
	output reg  [`kNumCoins-1:0] o_return_coin;
	output reg [31:0] wait_time;

	reg flag;

	// initiate values
	initial begin
		// TODO: initiate values

		o_return_coin = `kNumCoins'b000;
		wait_time = `kWaitTime;
		flag = 0;
	end


	// update coin return time
	always @(i_input_coin, i_select_item) begin
		// TODO: update coin return time
		
	end

	always @(*) begin
		// TODO: o_return_coin
	
	end

	always @(posedge clk ) begin

		if (wait_time == 0) begin
			if (relative_money >= coin_value[2])
				o_return_coin <= `kNumCoins'b100;
			else if (relative_money >= coin_value[1])
				o_return_coin <= `kNumCoins'b010;
			else if (relative_money >= coin_value[0])
				o_return_coin <= `kNumCoins'b001;
			else
				o_return_coin <= `kNumCoins'b000;
		end
		else	
			o_return_coin <= `kNumCoins'b000;

		if (!reset_n) begin
			wait_time <= `kWaitTime;
		end
		else if (i_trigger_return && !flag) begin
			wait_time <= 2;
			flag <= 1;
		end
		else if (i_input_coin > 0)
			wait_time <= `kWaitTime;
		else if ((i_select_item & o_available_item) > 0)
			wait_time <= `kWaitTime;
		else begin
			if (wait_time > 0)
				wait_time <= wait_time - 1;
			else
				wait_time <= 0;
		end
	end
endmodule

lab1/vending_machine/vending_machine.v
// Title         : vending_machine.v
// Author      : Jae-Eon Jo (Jojaeeon@postech.ac.kr) 
//			     Dongup Kwon (nankdu7@postech.ac.kr) (2015.03.30)
//			     Jaehun Ryu (jaehunryu@postech.ac.kr) (2021.03.07)

`include "vending_machine_def.v"


module vending_machine (
	clk,							// Clock signal
	reset_n,						// Reset signal (active-low)

	i_input_coin,				// coin is inserted.
	i_select_item,				// item is selected.
	i_trigger_return,			// change-return is triggered 

	o_available_item,			// Sign of the item availability
	o_output_item,			// Sign of the item withdrawal
	o_return_coin				// Sign of the coin return
);

	// Ports Declaration
	// Do not modify the module interface
	input clk;
	input reset_n;
	
	input [`kNumCoins-1:0] i_input_coin;
	input [`kNumItems-1:0] i_select_item;
	input i_trigger_return;
		
	output [`kNumItems-1:0] o_available_item;
	output [`kNumItems-1:0] o_output_item;
	output [`kNumCoins-1:0] o_return_coin;


	

	// Do not modify the values.
	wire [31:0] item_price [`kNumItems-1:0];	// Price of each item
	wire [31:0] coin_value [`kNumCoins-1:0];	// Value of each coin
	assign item_price[0] = 400;
	assign item_price[1] = 500;
	assign item_price[2] = 1000;
	assign item_price[3] = 2000;
	assign coin_value[0] = 100;
	assign coin_value[1] = 500;
	assign coin_value[2] = 1000;

	// Internal states. You may add your own net variables.
	wire [`kTotalBits-1:0] current_total;
	
	// Next internal states. You may add your own net variables.
	wire [`kTotalBits-1:0] current_total_nxt;

	
	// Variables. You may add more your own net variables.
	wire [`kTotalBits-1:0] relative_money;
	wire [31:0] wait_time;


	// This module interface, structure, and given a number of modules are not mandatory but recommended.
	// However, Implementations that use modules are mandatory.
	
  	check_time_and_coin check_time_and_coin_module(.i_input_coin(i_input_coin),
  									.i_select_item(i_select_item),
									.coin_value(coin_value),
									.relative_money(relative_money),
									.i_trigger_return(i_trigger_return),
									.clk(clk),
									.reset_n(reset_n),
									.wait_time(wait_time),
									.o_return_coin(o_return_coin));

	calculate_current_state calculate_current_state_module(.i_input_coin(i_input_coin),
										.i_select_item(i_select_item),
										.i_trigger_return(i_trigger_return),
										.item_price(item_price),
										.coin_value(coin_value),
										.current_total(current_total),
										.relative_money(relative_money),
										.current_total_nxt(current_total_nxt),
										.wait_time(wait_time),
										.o_return_coin(o_return_coin),
										.o_available_item(o_available_item),
										.o_output_item(o_output_item));
	
  	change_state change_state_module(
						.clk(clk),
						.reset_n(reset_n),
						.current_total_nxt(current_total_nxt),
						.current_total(current_total));


endmodule

lab1/vending_machine/waveform.vcd
$version Generated by VerilatedVcd $end
$timescale 1ps $end
 $scope module TOP $end
  $var wire 1 / clk $end
  $var wire 1 0 reset_n $end
  $var wire 3 1 i_input_coin [2:0] $end
  $var wire 4 2 i_select_item [3:0] $end
  $var wire 1 3 i_trigger_return $end
  $var wire 4 4 o_available_item [3:0] $end
  $var wire 4 5 o_output_item [3:0] $end
  $var wire 3 6 o_return_coin [2:0] $end
  $scope module vending_machine $end
   $var wire 1 / clk $end
   $var wire 1 0 reset_n $end
   $var wire 3 1 i_input_coin [2:0] $end
   $var wire 4 2 i_select_item [3:0] $end
   $var wire 1 3 i_trigger_return $end
   $var wire 4 4 o_available_item [3:0] $end
   $var wire 4 5 o_output_item [3:0] $end
   $var wire 3 6 o_return_coin [2:0] $end
   $var wire 32 # item_price[0] [31:0] $end
   $var wire 32 $ item_price[1] [31:0] $end
   $var wire 32 % item_price[2] [31:0] $end
   $var wire 32 & item_price[3] [31:0] $end
   $var wire 32 ' coin_value[0] [31:0] $end
   $var wire 32 ( coin_value[1] [31:0] $end
   $var wire 32 ) coin_value[2] [31:0] $end
   $var wire 32 * current_total [31:0] $end
   $var wire 32 7 current_total_nxt [31:0] $end
   $var wire 32 8 relative_money [31:0] $end
   $var wire 32 + wait_time [31:0] $end
   $scope module calculate_current_state_module $end
    $var wire 1 3 i_trigger_return $end
    $var wire 3 1 i_input_coin [2:0] $end
    $var wire 3 6 o_return_coin [2:0] $end
    $var wire 4 2 i_select_item [3:0] $end
    $var wire 32 # item_price[0] [31:0] $end
    $var wire 32 $ item_price[1] [31:0] $end
    $var wire 32 % item_price[2] [31:0] $end
    $var wire 32 & item_price[3] [31:0] $end
    $var wire 32 ' coin_value[0] [31:0] $end
    $var wire 32 ( coin_value[1] [31:0] $end
    $var wire 32 ) coin_value[2] [31:0] $end
    $var wire 32 * current_total [31:0] $end
    $var wire 32 + wait_time [31:0] $end
    $var wire 4 4 o_available_item [3:0] $end
    $var wire 4 5 o_output_item [3:0] $end
    $var wire 32 8 relative_money [31:0] $end
    $var wire 32 7 current_total_nxt [31:0] $end
    $var wire 32 , i [31:0] $end
    $var wire 32 9 input_total [31:0] $end
    $var wire 32 : output_total [31:0] $end
    $var wire 32 - return_total [31:0] $end
   $upscope $end
   $scope module change_state_module $end
    $var wire 1 / clk $end
    $var wire 1 0 reset_n $end
    $var wire 32 7 current_total_nxt [31:0] $end
    $var wire 32 * current_total [31:0] $end
   $upscope $end
   $scope module check_time_and_coin_module $end
    $var wire 1 / clk $end
    $var wire 1 0 reset_n $end
    $var wire 1 3 i_trigger_return $end
    $var wire 32 ' coin_value[0] [31:0] $end
    $var wire 32 ( coin_value[1] [31:0] $end
    $var wire 32 ) coin_value[2] [31:0] $end
    $var wire 3 1 i_input_coin [2:0] $end
    $var wire 4 2 i_select_item [3:0] $end
    $var wire 4 4 o_available_item [3:0] $end
    $var wire 32 8 relative_money [31:0] $end
    $var wire 3 6 o_return_coin [2:0] $end
    $var wire 32 + wait_time [31:0] $end
    $var wire 1 . flag $end
   $upscope $end
  $upscope $end
 $upscope $end
$enddefinitions $end


#0
b00000000000000000000000110010000 #
b00000000000000000000000111110100 $
b00000000000000000000001111101000 %
b00000000000000000000011111010000 &
b00000000000000000000000001100100 '
b00000000000000000000000111110100 (
b00000000000000000000001111101000 )
b01110011010110000001011000110101 *
b00000000000000000000000000001010 +
b00000110101011011111010100111011 ,
b00000000000000000000000000000000 -
0.
1/
10
b000 1
b0000 2
03
b1100 4
b0110 5
b000 6
b10101101111110111100100100010010 7
b00000000000000000000000000000000 8
b00000000000000000000000000000000 9
b00000000000000000000000000000000 :
#1
0/
#2
b00000000000000000000000000000000 *
1/
00
b00000000000000000000000000000001 7
#3
0/
#4
1/
#5
0/
#6
b00000000000000000000000000000001 *
b00000000000000000000000000001001 +
b00000000000000000000000000000100 ,
1/
10
b0000 4
#7
0/
#8
b00000000000000000000000000000010 *
b00000000000000000000000000001010 +
b00000000000000000000000000000011 ,
1/
b001 1
b00000000000000000000000000110010 8
b00000000000000000000000000110010 9
#9
0/
b00000000000000000000000001100100 8
b00000000000000000000000001100100 9
#10
b00000000000000000000000000000001 *
b00000000000000000000000000001001 +
b00000000000000000000000000000100 ,
1/
b000 1
#11
0/
#12
b00000000000000000000000000000010 *
b00000000000000000000000000001010 +
b00000000000000000000000000000011 ,
1/
b001 1
b00000000000000000000000010010110 8
b00000000000000000000000010010110 9
#13
0/
b00000000000000000000000011001000 8
b00000000000000000000000011001000 9
#14
b00000000000000000000000000000001 *
b00000000000000000000000000001001 +
b00000000000000000000000000000100 ,
1/
b000 1
#15
0/
#16
b00000000000000000000000000000010 *
b00000000000000000000000000001010 +
b00000000000000000000000000000011 ,
1/
b001 1
b00000000000000000000000011111010 8
b00000000000000000000000011111010 9
#17
0/
b00000000000000000000000100101100 8
b00000000000000000000000100101100 9
#18
b00000000000000000000000000000001 *
b00000000000000000000000000001001 +
b00000000000000000000000000000100 ,
1/
b000 1
#19
0/
#20
b00000000000000000000000000000010 *
b00000000000000000000000000001010 +
b00000000000000000000000000000011 ,
1/
b001 1
b00000000000000000000000101011110 8
b00000000000000000000000101011110 9
#21
0/
b00000000000000000000000110010000 8
b00000000000000000000000110010000 9
#22
b00000000000000000000000000000001 *
b00000000000000000000000000001001 +
b00000000000000000000000000000100 ,
1/
b000 1
b0001 4
#23
0/
#24
b00000000000000000000000000000010 *
b00000000000000000000000000001010 +
b00000000000000000000000000000011 ,
1/
b001 1
b00000000000000000000000111000010 8
b00000000000000000000000111000010 9
#25
0/
b00000000000000000000000111110100 8
b00000000000000000000000111110100 9
#26
b00000000000000000000000000000001 *
b00000000000000000000000000001001 +
b00000000000000000000000000000100 ,
1/
b000 1
b0011 4
#27
0/
#28
b00000000000000000000000000001000 +
1/
#29
0/
#30
b00000000000000000000000000000000 *
b00000000000000000000000000001010 +
1/
00
b00000000000000000000000000000000 8
b00000000000000000000000000000000 9
#31
0/
#32
1/
#33
0/
#34
b00000000000000000000000000000001 *
b00000000000000000000000000001001 +
1/
10
b0000 4
#35
0/
#36
b00000000000000000000000000000010 *
b00000000000000000000000000001010 +
b00000000000000000000000000000011 ,
1/
b010 1
b00000000000000000000000011111010 8
b00000000000000000000000011111010 9
#37
0/
b00000000000000000000000111110100 8
b00000000000000000000000111110100 9
#38
b00000000000000000000000000000001 *
b00000000000000000000000000001001 +
b00000000000000000000000000000100 ,
1/
b000 1
b0011 4
#39
0/
#40
b00000000000000000000000000000010 *
b00000000000000000000000000001010 +
b00000000000000000000000000000011 ,
1/
b010 1
b00000000000000000000001011101110 8
b00000000000000000000001011101110 9
#41
0/
b00000000000000000000001111101000 8
b00000000000000000000001111101000 9
#42
b00000000000000000000000000000001 *
b00000000000000000000000000001001 +
b00000000000000000000000000000100 ,
1/
b000 1
b0111 4
#43
0/
#44
b00000000000000000000000000000010 *
b00000000000000000000000000001010 +
b00000000000000000000000000000011 ,
1/
b010 1
b00000000000000000000010011100010 8
b00000000000000000000010011100010 9
#45
0/
b00000000000000000000010111011100 8
b00000000000000000000010111011100 9
#46
b00000000000000000000000000000001 *
b00000000000000000000000000001001 +
b00000000000000000000000000000100 ,
1/
b000 1
#47
0/
#48
b00000000000000000000000000000010 *
b00000000000000000000000000001010 +
b00000000000000000000000000000011 ,
1/
b010 1
b00000000000000000000011011010110 8
b00000000000000000000011011010110 9
#49
0/
b00000000000000000000011111010000 8
b00000000000000000000011111010000 9
#50
b00000000000000000000000000000001 *
b00000000000000000000000000001001 +
b00000000000000000000000000000100 ,
1/
b000 1
b1111 4
#51
0/
#52
b00000000000000000000000000001000 +
1/
#53
0/
#54
b00000000000000000000000000000000 *
b00000000000000000000000000001010 +
1/
00
b00000000000000000000000000000000 8
b00000000000000000000000000000000 9
#55
0/
#56
1/
#57
0/
#58
b00000000000000000000000000000001 *
b00000000000000000000000000001001 +
1/
10
b0000 4
#59
0/
#60
b00000000000000000000000000000010 *
b00000000000000000000000000001010 +
b00000000000000000000000000000011 ,
1/
b100 1
b00000000000000000000000111110100 8
b00000000000000000000000111110100 9
#61
0/
b00000000000000000000001111101000 8
b00000000000000000000001111101000 9
#62
b00000000000000000000000000000001 *
b00000000000000000000000000001001 +
b00000000000000000000000000000100 ,
1/
b000 1
b0111 4
#63
0/
#64
b00000000000000000000000000000010 *
b00000000000000000000000000001010 +
b00000000000000000000000000000011 ,
1/
b100 1
b00000000000000000000010111011100 8
b00000000000000000000010111011100 9
#65
0/
b00000000000000000000011111010000 8
b00000000000000000000011111010000 9
#66
b00000000000000000000000000000001 *
b00000000000000000000000000001001 +
b00000000000000000000000000000100 ,
1/
b000 1
b1111 4
#67
0/
#68
b00000000000000000000000000001000 +
1/
#69
0/
#70
b00000000000000000000000000000000 *
b00000000000000000000000000001010 +
1/
00
b00000000000000000000000000000000 8
b00000000000000000000000000000000 9
#71
0/
#72
1/
#73
0/
#74
b00000000000000000000000000000001 *
b00000000000000000000000000001001 +
1/
10
b0000 4
#75
0/
#76
b00000000000000000000000000000010 *
b00000000000000000000000000001010 +
b00000000000000000000000000000011 ,
1/
b100 1
b00000000000000000000000111110100 8
b00000000000000000000000111110100 9
#77
0/
b00000000000000000000001111101000 8
b00000000000000000000001111101000 9
#78
b00000000000000000000000000000001 *
b00000000000000000000000000001001 +
b00000000000000000000000000000100 ,
1/
b000 1
b0111 4
#79
0/
#80
b00000000000000000000000000000010 *
b00000000000000000000000000001010 +
b00000000000000000000000000000011 ,
1/
b100 1
b00000000000000000000010111011100 8
b00000000000000000000010111011100 9
#81
0/
b00000000000000000000011111010000 8
b00000000000000000000011111010000 9
#82
b00000000000000000000000000000001 *
b00000000000000000000000000001001 +
b00000000000000000000000000000100 ,
1/
b000 1
b1111 4
#83
0/
#84
b00000000000000000000000000000010 *
b00000000000000000000000000001010 +
b00000000000000000000000000000011 ,
1/
b100 1
b00000000000000000000100111000100 8
b00000000000000000000100111000100 9
#85
0/
b00000000000000000000101110111000 8
b00000000000000000000101110111000 9
#86
b00000000000000000000000000000001 *
b00000000000000000000000000001001 +
b00000000000000000000000000000100 ,
1/
b000 1
#87
0/
#88
b00000000000000000000000000000011 *
b00000000000000000000000000001010 +
1/
b0001 2
b0001 5
b00000000000000000000101011110000 8
b00000000000000000000000011001000 :
#89
0/
b00000000000000000000101000101000 8
b00000000000000000000000110010000 :
#90
b00000000000000000000000000000001 *
b00000000000000000000000000001001 +
1/
b0000 2
b0000 5
#91
0/
#92
b00000000000000000000000000001000 +
1/
#93
0/
#94
b00000000000000000000000000000111 +
1/
#95
0/
#96
b00000000000000000000000000000011 *
b00000000000000000000000000001010 +
1/
b0001 2
b0001 5
b00000000000000000000100101100000 8
b00000000000000000000001001011000 :
#97
0/
b00000000000000000000100010011000 8
b00000000000000000000001100100000 :
#98
b00000000000000000000000000000001 *
b00000000000000000000000000001001 +
1/
b0000 2
b0000 5
#99
0/
#100
b00000000000000000000000000001000 +
1/
#101
0/
#102
b00000000000000000000000000000111 +
1/
#103
0/
#104
b00000000000000000000000000000011 *
b00000000000000000000000000001010 +
1/
b0001 2
b0001 5
b00000000000000000000011111010000 8
b00000000000000000000001111101000 :
#105
0/
b00000000000000000000011100001000 8
b00000000000000000000010010110000 :
#106
b00000000000000000000000000000001 *
b00000000000000000000000000001001 +
1/
b0000 2
b0111 4
b0000 5
#107
0/
#108
b00000000000000000000000000001000 +
1/
#109
0/
#110
b00000000000000000000000000000111 +
1/
#111
0/
#112
b00000000000000000000000000000011 *
b00000000000000000000000000001010 +
1/
b0001 2
b0001 5
b00000000000000000000011001000000 8
b00000000000000000000010101111000 :
#113
0/
b00000000000000000000010101111000 8
b00000000000000000000011001000000 :
#114
b00000000000000000000000000000001 *
b00000000000000000000000000001001 +
1/
b0000 2
b0000 5
#115
0/
#116
b00000000000000000000000000001000 +
1/
#117
0/
#118
b00000000000000000000000000000111 +
1/
#119
0/
#120
b00000000000000000000000000000011 *
b00000000000000000000000000001010 +
1/
b0001 2
b0001 5
b00000000000000000000010010110000 8
b00000000000000000000011100001000 :
#121
0/
b00000000000000000000001111101000 8
b00000000000000000000011111010000 :
#122
b00000000000000000000000000000001 *
b00000000000000000000000000001001 +
1/
b0000 2
b0000 5
#123
0/
#124
b00000000000000000000000000001000 +
1/
#125
0/
#126
b00000000000000000000000000000111 +
1/
#127
0/
#128
b00000000000000000000000000000011 *
b00000000000000000000000000001010 +
1/
b0001 2
b0001 5
b00000000000000000000001100100000 8
b00000000000000000000100010011000 :
#129
0/
b00000000000000000000001001011000 8
b00000000000000000000100101100000 :
#130
b00000000000000000000000000000001 *
b00000000000000000000000000001001 +
1/
b0000 2
b0011 4
b0000 5
#131
0/
#132
b00000000000000000000000000001000 +
1/
#133
0/
#134
b00000000000000000000000000000111 +
1/
#135
0/
#136
b00000000000000000000000000000011 *
b00000000000000000000000000001010 +
1/
b0001 2
b0001 5
b00000000000000000000000110010000 8
b00000000000000000000101000101000 :
#137
0/
b00000000000000000000000011001000 8
b00000000000000000000101011110000 :
#138
b00000000000000000000000000000001 *
b00000000000000000000000000001001 +
1/
b0000 2
b0000 4
b0000 5
#139
0/
#140
b00000000000000000000000000001000 +
1/
#141
0/
#142
b00000000000000000000000000000111 +
1/
#143
0/
#144
b00000000000000000000000000000110 +
1/
#145
0/
#146
b00000000000000000000000000000101 +
1/
#147
0/
#148
b00000000000000000000000000000010 *
b00000000000000000000000000001010 +
b00000000000000000000000000000011 ,
1/
b100 1
b00000000000000000000001010111100 8
b00000000000000000000110110101100 9
#149
0/
b00000000000000000000010010110000 8
b00000000000000000000111110100000 9
#150
b00000000000000000000000000000001 *
b00000000000000000000000000001001 +
b00000000000000000000000000000100 ,
1/
b000 1
b0111 4
#151
0/
#152
b00000000000000000000000000000010 *
b00000000000000000000000000001010 +
b00000000000000000000000000000011 ,
1/
b100 1
b00000000000000000000011010100100 8
b00000000000000000001000110010100 9
#153
0/
b00000000000000000000100010011000 8
b00000000000000000001001110001000 9
#154
b00000000000000000000000000000001 *
b00000000000000000000000000001001 +
b00000000000000000000000000000100 ,
1/
b000 1
b1111 4
#155
0/
#156
b00000000000000000000000000000010 *
b00000000000000000000000000001010 +
b00000000000000000000000000000011 ,
1/
b100 1
b00000000000000000000101010001100 8
b00000000000000000001010101111100 9
#157
0/
b00000000000000000000110010000000 8
b00000000000000000001011101110000 9
#158
b00000000000000000000000000000001 *
b00000000000000000000000000001001 +
b00000000000000000000000000000100 ,
1/
b000 1
#159
0/
#160
b00000000000000000000000000000011 *
b00000000000000000000000000001010 +
1/
b0010 2
b0010 5
b00000000000000000000101110000110 8
b00000000000000000000101111101010 :
#161
0/
b00000000000000000000101010001100 8
b00000000000000000000110011100100 :
#162
b00000000000000000000000000000001 *
b00000000000000000000000000001001 +
1/
b0000 2
b0000 5
#163
0/
#164
b00000000000000000000000000001000 +
1/
#165
0/
#166
b00000000000000000000000000000111 +
1/
#167
0/
#168
b00000000000000000000000000000011 *
b00000000000000000000000000001010 +
1/
b0010 2
b0010 5
b00000000000000000000100110010010 8
b00000000000000000000110111011110 :
#169
0/
b00000000000000000000100010011000 8
b00000000000000000000111011011000 :
#170
b00000000000000000000000000000001 *
b00000000000000000000000000001001 +
1/
b0000 2
b0000 5
#171
0/
#172
b00000000000000000000000000001000 +
1/
#173
0/
#174
b00000000000000000000000000000111 +
1/
#175
0/
#176
b00000000000000000000000000000011 *
b00000000000000000000000000001010 +
1/
b0010 2
b0010 5
b00000000000000000000011110011110 8
b00000000000000000000111111010010 :
#177
0/
b00000000000000000000011010100100 8
b00000000000000000001000011001100 :
#178
b00000000000000000000000000000001 *
b00000000000000000000000000001001 +
1/
b0000 2
b0111 4
b0000 5
#179
0/
#180
b00000000000000000000000000001000 +
1/
#181
0/
#182
b00000000000000000000000000000111 +
1/
#183
0/
#184
b00000000000000000000000000000011 *
b00000000000000000000000000001010 +
1/
b0010 2
b0010 5
b00000000000000000000010110101010 8
b00000000000000000001000111000110 :
#185
0/
b00000000000000000000010010110000 8
b00000000000000000001001011000000 :
#186
b00000000000000000000000000000001 *
b00000000000000000000000000001001 +
1/
b0000 2
b0000 5
#187
0/
#188
b00000000000000000000000000001000 +
1/
#189
0/
#190
b00000000000000000000000000000111 +
1/
#191
0/
#192
b00000000000000000000000000000011 *
b00000000000000000000000000001010 +
1/
b0010 2
b0010 5
b00000000000000000000001110110110 8
b00000000000000000001001110111010 :
#193
0/
b00000000000000000000001010111100 8
b00000000000000000001010010110100 :
#194
b00000000000000000000000000000001 *
b00000000000000000000000000001001 +
1/
b0000 2
b0011 4
b0000 5
#195
0/
#196
b00000000000000000000000000001000 +
1/
#197
0/
#198
b00000000000000000000000000000111 +
1/
#199
0/
#200
b00000000000000000000000000000011 *
b00000000000000000000000000001010 +
1/
b0010 2
b0010 5
b00000000000000000000000111000010 8
b00000000000000000001010110101110 :
#201
0/
b00000000000000000000000011001000 8
b00000000000000000001011010101000 :
#202
b00000000000000000000000000000001 *
b00000000000000000000000000001001 +
1/
b0000 2
b0000 4
b0000 5
#203
0/
#204
b00000000000000000000000000001000 +
1/
#205
0/
#206
b00000000000000000000000000000111 +
1/
#207
0/
#208
b00000000000000000000000000000010 *
b00000000000000000000000000001010 +
b00000000000000000000000000000011 ,
1/
b001 1
b00000000000000000000000011111010 8
b00000000000000000001011110100010 9
#209
0/
b00000000000000000000000100101100 8
b00000000000000000001011111010100 9
#210
b00000000000000000000000000000001 *
b00000000000000000000000000001001 +
b00000000000000000000000000000100 ,
1/
b000 1
#211
0/
#212
b00000000000000000000000000000010 *
b00000000000000000000000000001010 +
b00000000000000000000000000000011 ,
1/
b001 1
b00000000000000000000000101011110 8
b00000000000000000001100000000110 9
#213
0/
b00000000000000000000000110010000 8
b00000000000000000001100000111000 9
#214
b00000000000000000000000000000001 *
b00000000000000000000000000001001 +
b00000000000000000000000000000100 ,
1/
b000 1
b0001 4
#215
0/
#216
b00000000000000000000000000000010 *
b00000000000000000000000000001010 +
b00000000000000000000000000000011 ,
1/
b100 1
b00000000000000000000001110000100 8
b00000000000000000001101000101100 9
#217
0/
b00000000000000000000010101111000 8
b00000000000000000001110000100000 9
#218
b00000000000000000000000000000001 *
b00000000000000000000000000001001 +
b00000000000000000000000000000100 ,
1/
b000 1
b0111 4
#219
0/
#220
b00000000000000000000000000000010 *
b00000000000000000000000000001010 +
b00000000000000000000000000000011 ,
1/
b100 1
b00000000000000000000011101101100 8
b00000000000000000001111000010100 9
#221
0/
b00000000000000000000100101100000 8
b00000000000000000010000000001000 9
#222
b00000000000000000000000000000001 *
b00000000000000000000000000001001 +
b00000000000000000000000000000100 ,
1/
b000 1
b1111 4
#223
0/
#224
b00000000000000000000000000000010 *
b00000000000000000000000000001010 +
b00000000000000000000000000000011 ,
1/
b100 1
b00000000000000000000101101010100 8
b00000000000000000010000111111100 9
#225
0/
b00000000000000000000110101001000 8
b00000000000000000010001111110000 9
#226
b00000000000000000000000000000001 *
b00000000000000000000000000001001 +
b00000000000000000000000000000100 ,
1/
b000 1
#227
0/
#228
b00000000000000000000000000000011 *
b00000000000000000000000000001010 +
1/
b0100 2
b0100 5
b00000000000000000000101101010100 8
b00000000000000000001100010011100 :
#229
0/
b00000000000000000000100101100000 8
b00000000000000000001101010010000 :
#230
b00000000000000000000000000000001 *
b00000000000000000000000000001001 +
1/
b0000 2
b0000 5
#231
0/
#232
b00000000000000000000000000001000 +
1/
#233
0/
#234
b00000000000000000000000000000111 +
1/
#235
0/
#236
b00000000000000000000000000000011 *
b00000000000000000000000000001010 +
1/
b0100 2
b0100 5
b00000000000000000000011101101100 8
b00000000000000000001110010000100 :
#237
0/
b00000000000000000000010101111000 8
b00000000000000000001111001111000 :
#238
b00000000000000000000000000000001 *
b00000000000000000000000000001001 +
1/
b0000 2
b0111 4
b0000 5
#239
0/
#240
b00000000000000000000000000001000 +
1/
#241
0/
#242
b00000000000000000000000000000111 +
1/
#243
0/
#244
b00000000000000000000000000000011 *
b00000000000000000000000000001010 +
1/
b0100 2
b0100 5
b00000000000000000000001110000100 8
b00000000000000000010000001101100 :
#245
0/
b00000000000000000000000110010000 8
b00000000000000000010001001100000 :
#246
b00000000000000000000000000000001 *
b00000000000000000000000000001001 +
1/
b0000 2
b0001 4
b0000 5
#247
0/
#248
b00000000000000000000000000001000 +
1/
#249
0/
#250
b00000000000000000000000000000111 +
1/
#251
0/
#252
b00000000000000000000000000000010 *
b00000000000000000000000000001010 +
b00000000000000000000000000000011 ,
1/
b100 1
b00000000000000000000001110000100 8
b00000000000000000010010111100100 9
#253
0/
b00000000000000000000010101111000 8
b00000000000000000010011111011000 9
#254
b00000000000000000000000000000001 *
b00000000000000000000000000001001 +
b00000000000000000000000000000100 ,
1/
b000 1
b0111 4
#255
0/
#256
b00000000000000000000000000000010 *
b00000000000000000000000000001010 +
b00000000000000000000000000000011 ,
1/
b100 1
b00000000000000000000011101101100 8
b00000000000000000010100111001100 9
#257
0/
b00000000000000000000100101100000 8
b00000000000000000010101111000000 9
#258
b00000000000000000000000000000001 *
b00000000000000000000000000001001 +
b00000000000000000000000000000100 ,
1/
b000 1
b1111 4
#259
0/
#260
b00000000000000000000000000000010 *
b00000000000000000000000000001010 +
b00000000000000000000000000000011 ,
1/
b100 1
b00000000000000000000101101010100 8
b00000000000000000010110110110100 9
#261
0/
b00000000000000000000110101001000 8
b00000000000000000010111110101000 9
#262
b00000000000000000000000000000001 *
b00000000000000000000000000001001 +
b00000000000000000000000000000100 ,
1/
b000 1
#263
0/
#264
b00000000000000000000000000000011 *
b00000000000000000000000000001010 +
1/
b1000 2
b1000 5
b00000000000000000000100101100000 8
b00000000000000000010011001001000 :
#265
0/
b00000000000000000000010101111000 8
b00000000000000000010101000110000 :
