lab1/vending_machine/vending_machine_def.v
// Title         : vending_machine_def.v
// Author      : Jae-Eon Jo (Jojaeeon@postech.ac.kr) 
//					Dongup Kwon (nankdu7@postech.ac.kr)

// Macro constants (prefix k & CamelCase)
`define kTotalBits 32
  
`define kItemBits 8
`define kNumItems 4

`define kCoinBits 8
`define kNumCoins 3

`define kWaitTime 10

`define S0_init 32'h00
`define S1_wait 32'h01
`define S2_coin 32'h02
`define S3_select 32'h03

lab1/vending_machine/change_state.v
`include "vending_machine_def.v"


module change_state(clk,reset_n,current_total_nxt,current_total);

	input clk;
	input reset_n;
	input [`kTotalBits-1:0] current_total_nxt;
	output reg [`kTotalBits-1:0] current_total;
	
	// Sequential circuit to reset or update the states
	always @(posedge clk ) begin
		if (!reset_n) begin
			// TODO: reset all states.

			//reset current_total(0)
			current_total <= `kTotalBits'b0;
		end
		else begin
			// TODO: update all states.
			
			// update current_total to current_total_nxt
			current_total <= current_total_nxt;
		end
	end
endmodule

lab1/vending_machine/calculate_current_state.v

`include "vending_machine_def.v"
	

module calculate_current_state(i_input_coin,i_select_item,item_price,coin_value,current_total,
input_total, output_total, return_total,current_total_nxt,wait_time,o_return_coin,o_available_item,o_output_item);


	
	input [`kNumCoins-1:0] i_input_coin,o_return_coin;
	input [`kNumItems-1:0]	i_select_item;			
	input [31:0] item_price [`kNumItems-1:0];
	input [31:0] coin_value [`kNumCoins-1:0];	
	input [`kTotalBits-1:0] current_total;
	input [31:0] wait_time;
	output reg [`kNumItems-1:0] o_available_item,o_output_item;
	output reg  [`kTotalBits-1:0] input_total, output_total, return_total;
	output reg  [`kTotalBits-1:0] current_total_nxt;
	integer i;	

	initial begin
		input_total = 0;
		output_total = 0;
		return_total = input_total - output_total;
		//need to revise
		if (wait_time == 0 && o_return_coin > 0)
			return_total = 0;
	end

	// Combinational logic for the next states
	always @(*) begin
		// TODO: current_total_nxt
		// You don't have to worry about concurrent activations in each input vector (or array).
		// Calculate the next current_total state.
		
		case (current_total)
			`S0_init:
				current_total_nxt = `S1_wait;
			`S1_wait:
				if(i_input_coin > 0) 
					current_total_nxt = `S2_coin;
				else if(i_select_item > 0) 
					current_total_nxt = `S3_select;
			`S2_coin:
				current_total_nxt = `S1_wait;
			`S3_select:
				if (o_available_item > 0) 
					current_total_nxt = `S2_coin;
				else if (input_total > output_total)
					current_total_nxt = `S2_coin;
				else
					current_total_nxt = `S0_init;
			default: begin current_total_nxt = `S0_init; end
		endcase
		
	end

	
	
	// Combinational logic for the outputs
	always @(*) begin
		// TODO: o_available_item
		// TODO: o_output_item
		//$monitor("state: %h, coin: %h", current_total, input_total);
		case (current_total)
			`S0_init: begin
				input_total = 0;
				output_total = 0;
				return_total = 0;
				o_available_item = 0;
			end
			`S1_wait: begin
				for (i = 0; i < `kNumItems; i = i+1) begin
					if (input_total - output_total >= item_price[i])
						o_available_item[i] = 1;
					else
						o_available_item[i] = 0;
				end
			end
			`S2_coin: begin
				for (i = 0; i < `kNumCoins; i = i+1) begin
					if (i_input_coin[i])
						input_total = input_total + coin_value[i] / 2;
				end
			end
			`S3_select: begin
				for (i = 0; i < `kNumItems; i = i+1) begin
					if (i_select_item[i] && o_available_item[i]) begin
						o_output_item[i] = 1;
						output_total = output_total + item_price[i] / 2;
					end
					else begin
						o_output_item[i] = 0;
					end
				end
			end
			default: return_total = input_total - output_total;
		endcase

	end
 
	


endmodule

lab1/vending_machine/check_time_and_coin.v
`include "vending_machine_def.v"

	

module check_time_and_coin(i_input_coin,i_select_item,clk,reset_n,wait_time,o_return_coin);
	input clk;
	input reset_n;
	input [`kNumCoins-1:0] i_input_coin;
	input [`kNumItems-1:0]	i_select_item;
	output reg  [`kNumCoins-1:0] o_return_coin;
	output reg [31:0] wait_time;

	// initiate values
	initial begin
		// TODO: initiate values

		o_return_coin = `kNumCoins'b0;
		wait_time = `kWaitTime;
	end


	// update coin return time
	always @(i_input_coin, i_select_item) begin
		// TODO: update coin return time

		// wait_time will be initialized to original
	end

	always @(*) begin
		// TODO: o_return_coin

	end

	always @(posedge clk ) begin
		if (!reset_n) begin
		// TODO: reset all states.

		// reset all output value //
		o_return_coin <= `kNumCoins'b001; //revise later
		wait_time <= `kWaitTime;
		end
		if (i_input_coin > 0 || i_select_item > 0)
			wait_time <= `kWaitTime;
		else begin
		// TODO: update all states.

		// update output value - wait_time decresing //
		wait_time <= wait_time - 1;
		end
	end
endmodule

lab1/vending_machine/vending_machine.v
// Title         : vending_machine.v
// Author      : Jae-Eon Jo (Jojaeeon@postech.ac.kr) 
//			     Dongup Kwon (nankdu7@postech.ac.kr) (2015.03.30)
//			     Jaehun Ryu (jaehunryu@postech.ac.kr) (2021.03.07)

`include "vending_machine_def.v"


module vending_machine (
	clk,							// Clock signal
	reset_n,						// Reset signal (active-low)

	i_input_coin,				// coin is inserted.
	i_select_item,				// item is selected.
	i_trigger_return,			// change-return is triggered 

	o_available_item,			// Sign of the item availability
	o_output_item,			// Sign of the item withdrawal
	o_return_coin				// Sign of the coin return
);

	// Ports Declaration
	// Do not modify the module interface
	input clk;
	input reset_n;
	
	input [`kNumCoins-1:0] i_input_coin;
	input [`kNumItems-1:0] i_select_item;
	input i_trigger_return;
		
	output [`kNumItems-1:0] o_available_item;
	output [`kNumItems-1:0] o_output_item;
	output [`kNumCoins-1:0] o_return_coin;


	

	// Do not modify the values.
	wire [31:0] item_price [`kNumItems-1:0];	// Price of each item
	wire [31:0] coin_value [`kNumCoins-1:0];	// Value of each coin
	assign item_price[0] = 400;
	assign item_price[1] = 500;
	assign item_price[2] = 1000;
	assign item_price[3] = 2000;
	assign coin_value[0] = 100;
	assign coin_value[1] = 500;
	assign coin_value[2] = 1000;

	// Internal states. You may add your own net variables.
	wire [`kTotalBits-1:0] current_total;
	
	// Next internal states. You may add your own net variables.
	wire [`kTotalBits-1:0] current_total_nxt;

	
	// Variables. You may add more your own net variables.
	wire [`kTotalBits-1:0] input_total, output_total, return_total;
	wire [31:0] wait_time;


	// This module interface, structure, and given a number of modules are not mandatory but recommended.
	// However, Implementations that use modules are mandatory.
	wire ret;
	wire [31:0] rett;
	assign ret = i_trigger_return;
	assign rett = input_total;
	assign rett = output_total;
	assign rett = return_total;
	assign rett = rett;
	assign ret = ret;
	
  	check_time_and_coin check_time_and_coin_module(.i_input_coin(i_input_coin),
  									.i_select_item(i_select_item),
									.clk(clk),
									.reset_n(reset_n),
									.wait_time(wait_time),
									.o_return_coin(o_return_coin));

	calculate_current_state calculate_current_state_module(.i_input_coin(i_input_coin),
										.i_select_item(i_select_item),
										.item_price(item_price),
										.coin_value(coin_value),
										.current_total(current_total),
										.input_total(input_total),
										.output_total(output_total),
										.return_total(return_total),
										.current_total_nxt(current_total_nxt),
										.wait_time(wait_time),
										.o_return_coin(o_return_coin),
										.o_available_item(o_available_item),
										.o_output_item(o_output_item));
	
  	change_state change_state_module(
						.clk(clk),
						.reset_n(reset_n),
						.current_total_nxt(current_total_nxt),
						.current_total(current_total));


endmodule

lab1/vending_machine/waveform.vcd
$version Generated by VerilatedVcd $end
$timescale 1ps $end
 $scope module TOP $end
  $var wire 1 - clk $end
  $var wire 1 . reset_n $end
  $var wire 3 / i_input_coin [2:0] $end
  $var wire 4 0 i_select_item [3:0] $end
  $var wire 1 1 i_trigger_return $end
  $var wire 4 2 o_available_item [3:0] $end
  $var wire 4 3 o_output_item [3:0] $end
  $var wire 3 4 o_return_coin [2:0] $end
  $scope module vending_machine $end
   $var wire 1 - clk $end
   $var wire 1 . reset_n $end
   $var wire 3 / i_input_coin [2:0] $end
   $var wire 4 0 i_select_item [3:0] $end
   $var wire 1 1 i_trigger_return $end
   $var wire 4 2 o_available_item [3:0] $end
   $var wire 4 3 o_output_item [3:0] $end
   $var wire 3 4 o_return_coin [2:0] $end
   $var wire 32 # item_price[0] [31:0] $end
   $var wire 32 $ item_price[1] [31:0] $end
   $var wire 32 % item_price[2] [31:0] $end
   $var wire 32 & item_price[3] [31:0] $end
   $var wire 32 ' coin_value[0] [31:0] $end
   $var wire 32 ( coin_value[1] [31:0] $end
   $var wire 32 ) coin_value[2] [31:0] $end
   $var wire 32 * current_total [31:0] $end
   $var wire 32 5 current_total_nxt [31:0] $end
   $var wire 32 6 input_total [31:0] $end
   $var wire 32 7 output_total [31:0] $end
   $var wire 32 8 return_total [31:0] $end
   $var wire 32 + wait_time [31:0] $end
   $var wire 1 1 ret $end
   $var wire 32 6 rett [31:0] $end
   $scope module calculate_current_state_module $end
    $var wire 3 / i_input_coin [2:0] $end
    $var wire 3 4 o_return_coin [2:0] $end
    $var wire 4 0 i_select_item [3:0] $end
    $var wire 32 # item_price[0] [31:0] $end
    $var wire 32 $ item_price[1] [31:0] $end
    $var wire 32 % item_price[2] [31:0] $end
    $var wire 32 & item_price[3] [31:0] $end
    $var wire 32 ' coin_value[0] [31:0] $end
    $var wire 32 ( coin_value[1] [31:0] $end
    $var wire 32 ) coin_value[2] [31:0] $end
    $var wire 32 * current_total [31:0] $end
    $var wire 32 + wait_time [31:0] $end
    $var wire 4 2 o_available_item [3:0] $end
    $var wire 4 3 o_output_item [3:0] $end
    $var wire 32 6 input_total [31:0] $end
    $var wire 32 7 output_total [31:0] $end
    $var wire 32 8 return_total [31:0] $end
    $var wire 32 5 current_total_nxt [31:0] $end
    $var wire 32 , i [31:0] $end
   $upscope $end
   $scope module change_state_module $end
    $var wire 1 - clk $end
    $var wire 1 . reset_n $end
    $var wire 32 5 current_total_nxt [31:0] $end
    $var wire 32 * current_total [31:0] $end
   $upscope $end
   $scope module check_time_and_coin_module $end
    $var wire 1 - clk $end
    $var wire 1 . reset_n $end
    $var wire 3 / i_input_coin [2:0] $end
    $var wire 4 0 i_select_item [3:0] $end
    $var wire 3 4 o_return_coin [2:0] $end
    $var wire 32 + wait_time [31:0] $end
   $upscope $end
  $upscope $end
 $upscope $end
$enddefinitions $end


#0
b00000000000000000000000110010000 #
b00000000000000000000000111110100 $
b00000000000000000000001111101000 %
b00000000000000000000011111010000 &
b00000000000000000000000001100100 '
b00000000000000000000000111110100 (
b00000000000000000000001111101000 )
b01110011010110000001011000110101 *
b00000000000000000000000000001010 +
b11000110011011010100110101011000 ,
1-
1.
b000 /
b0000 0
01
b1100 2
b0110 3
b000 4
b00000000000000000000000000000000 5
b00000000000000000000000000000000 6
b00000000000000000000000000000000 7
b00000000000000000000000000000000 8
#1
0-
#2
b00000000000000000000000000000000 *
b00000000000000000000000000001001 +
1-
0.
b0000 2
b001 4
b00000000000000000000000000000001 5
#3
0-
#4
b00000000000000000000000000001000 +
1-
#5
0-
#6
b00000000000000000000000000000001 *
b00000000000000000000000000000111 +
b00000000000000000000000000000100 ,
1-
1.
#7
0-
#8
b00000000000000000000000000000010 *
b00000000000000000000000000001010 +
b00000000000000000000000000000011 ,
1-
b001 /
b00000000000000000000000000110010 6
#9
0-
b00000000000000000000000001100100 6
#10
b00000000000000000000000000000001 *
b00000000000000000000000000001001 +
b00000000000000000000000000000100 ,
1-
b000 /
#11
0-
#12
b00000000000000000000000000000010 *
b00000000000000000000000000001010 +
b00000000000000000000000000000011 ,
1-
b001 /
b00000000000000000000000010010110 6
#13
0-
b00000000000000000000000011001000 6
#14
b00000000000000000000000000000001 *
b00000000000000000000000000001001 +
b00000000000000000000000000000100 ,
1-
b000 /
#15
0-
#16
b00000000000000000000000000000010 *
b00000000000000000000000000001010 +
b00000000000000000000000000000011 ,
1-
b001 /
b00000000000000000000000011111010 6
#17
0-
b00000000000000000000000100101100 6
#18
b00000000000000000000000000000001 *
b00000000000000000000000000001001 +
b00000000000000000000000000000100 ,
1-
b000 /
#19
0-
#20
b00000000000000000000000000000010 *
b00000000000000000000000000001010 +
b00000000000000000000000000000011 ,
1-
b001 /
b00000000000000000000000101011110 6
#21
0-
b00000000000000000000000110010000 6
#22
b00000000000000000000000000000001 *
b00000000000000000000000000001001 +
b00000000000000000000000000000100 ,
1-
b000 /
b0001 2
#23
0-
#24
b00000000000000000000000000000010 *
b00000000000000000000000000001010 +
b00000000000000000000000000000011 ,
1-
b001 /
b00000000000000000000000111000010 6
#25
0-
b00000000000000000000000111110100 6
#26
b00000000000000000000000000000001 *
b00000000000000000000000000001001 +
b00000000000000000000000000000100 ,
1-
b000 /
b0011 2
#27
0-
#28
b00000000000000000000000000001000 +
1-
#29
0-
#30
b00000000000000000000000000000000 *
b00000000000000000000000000000111 +
1-
0.
b0000 2
b00000000000000000000000000000000 6
#31
0-
#32
b00000000000000000000000000000110 +
1-
#33
0-
#34
b00000000000000000000000000000001 *
b00000000000000000000000000000101 +
1-
1.
#35
0-
#36
b00000000000000000000000000000010 *
b00000000000000000000000000001010 +
b00000000000000000000000000000011 ,
1-
b010 /
b00000000000000000000000011111010 6
#37
0-
b00000000000000000000000111110100 6
#38
b00000000000000000000000000000001 *
b00000000000000000000000000001001 +
b00000000000000000000000000000100 ,
1-
b000 /
b0011 2
#39
0-
#40
b00000000000000000000000000000010 *
b00000000000000000000000000001010 +
b00000000000000000000000000000011 ,
1-
b010 /
b00000000000000000000001011101110 6
#41
0-
b00000000000000000000001111101000 6
#42
b00000000000000000000000000000001 *
b00000000000000000000000000001001 +
b00000000000000000000000000000100 ,
1-
b000 /
b0111 2
#43
0-
#44
b00000000000000000000000000000010 *
b00000000000000000000000000001010 +
b00000000000000000000000000000011 ,
1-
b010 /
b00000000000000000000010011100010 6
#45
0-
b00000000000000000000010111011100 6
#46
b00000000000000000000000000000001 *
b00000000000000000000000000001001 +
b00000000000000000000000000000100 ,
1-
b000 /
#47
0-
#48
b00000000000000000000000000000010 *
b00000000000000000000000000001010 +
b00000000000000000000000000000011 ,
1-
b010 /
b00000000000000000000011011010110 6
#49
0-
b00000000000000000000011111010000 6
#50
b00000000000000000000000000000001 *
b00000000000000000000000000001001 +
b00000000000000000000000000000100 ,
1-
b000 /
b1111 2
#51
0-
#52
b00000000000000000000000000001000 +
1-
#53
0-
#54
b00000000000000000000000000000000 *
b00000000000000000000000000000111 +
1-
0.
b0000 2
b00000000000000000000000000000000 6
#55
0-
#56
b00000000000000000000000000000110 +
1-
#57
0-
#58
b00000000000000000000000000000001 *
b00000000000000000000000000000101 +
1-
1.
#59
0-
#60
b00000000000000000000000000000010 *
b00000000000000000000000000001010 +
b00000000000000000000000000000011 ,
1-
b100 /
b00000000000000000000000111110100 6
#61
0-
b00000000000000000000001111101000 6
#62
b00000000000000000000000000000001 *
b00000000000000000000000000001001 +
b00000000000000000000000000000100 ,
1-
b000 /
b0111 2
#63
0-
#64
b00000000000000000000000000000010 *
b00000000000000000000000000001010 +
b00000000000000000000000000000011 ,
1-
b100 /
b00000000000000000000010111011100 6
#65
0-
b00000000000000000000011111010000 6
#66
b00000000000000000000000000000001 *
b00000000000000000000000000001001 +
b00000000000000000000000000000100 ,
1-
b000 /
b1111 2
#67
0-
#68
b00000000000000000000000000001000 +
1-
#69
0-
#70
b00000000000000000000000000000000 *
b00000000000000000000000000000111 +
1-
0.
b0000 2
b00000000000000000000000000000000 6
#71
0-
#72
b00000000000000000000000000000110 +
1-
#73
0-
#74
b00000000000000000000000000000001 *
b00000000000000000000000000000101 +
1-
1.
#75
0-
#76
b00000000000000000000000000000010 *
b00000000000000000000000000001010 +
b00000000000000000000000000000011 ,
1-
b100 /
b00000000000000000000000111110100 6
#77
0-
b00000000000000000000001111101000 6
#78
b00000000000000000000000000000001 *
b00000000000000000000000000001001 +
b00000000000000000000000000000100 ,
1-
b000 /
b0111 2
#79
0-
#80
b00000000000000000000000000000010 *
b00000000000000000000000000001010 +
b00000000000000000000000000000011 ,
1-
b100 /
b00000000000000000000010111011100 6
#81
0-
b00000000000000000000011111010000 6
#82
b00000000000000000000000000000001 *
b00000000000000000000000000001001 +
b00000000000000000000000000000100 ,
1-
b000 /
b1111 2
#83
0-
#84
b00000000000000000000000000000010 *
b00000000000000000000000000001010 +
b00000000000000000000000000000011 ,
1-
b100 /
b00000000000000000000100111000100 6
#85
0-
b00000000000000000000101110111000 6
#86
b00000000000000000000000000000001 *
b00000000000000000000000000001001 +
b00000000000000000000000000000100 ,
1-
b000 /
#87
0-
#88
b00000000000000000000000000000011 *
b00000000000000000000000000001010 +
1-
b0001 0
b0001 3
b00000000000000000000000000000010 5
b00000000000000000000000011001000 7
#89
0-
b00000000000000000000000110010000 7
#90
b00000000000000000000000000000010 *
b00000000000000000000000000001001 +
b00000000000000000000000000000011 ,
1-
b0000 0
b0000 3
b00000000000000000000000000000001 5
#91
0-
#92
b00000000000000000000000000000001 *
b00000000000000000000000000001000 +
b00000000000000000000000000000100 ,
1-
#93
0-
#94
b00000000000000000000000000000111 +
1-
#95
0-
#96
b00000000000000000000000000000011 *
b00000000000000000000000000001010 +
1-
b0001 0
b0001 3
b00000000000000000000000000000010 5
b00000000000000000000001001011000 7
#97
0-
b00000000000000000000001100100000 7
#98
b00000000000000000000000000000010 *
b00000000000000000000000000001001 +
b00000000000000000000000000000011 ,
1-
b0000 0
b0000 3
b00000000000000000000000000000001 5
#99
0-
#100
b00000000000000000000000000000001 *
b00000000000000000000000000001000 +
b00000000000000000000000000000100 ,
1-
#101
0-
#102
b00000000000000000000000000000111 +
1-
#103
0-
#104
b00000000000000000000000000000011 *
b00000000000000000000000000001010 +
1-
b0001 0
b0001 3
b00000000000000000000000000000010 5
b00000000000000000000001111101000 7
#105
0-
b00000000000000000000010010110000 7
#106
b00000000000000000000000000000010 *
b00000000000000000000000000001001 +
b00000000000000000000000000000011 ,
1-
b0000 0
b0000 3
b00000000000000000000000000000001 5
#107
0-
#108
b00000000000000000000000000000001 *
b00000000000000000000000000001000 +
b00000000000000000000000000000100 ,
1-
b0111 2
#109
0-
#110
b00000000000000000000000000000111 +
1-
#111
0-
#112
b00000000000000000000000000000011 *
b00000000000000000000000000001010 +
1-
b0001 0
b0001 3
b00000000000000000000000000000010 5
b00000000000000000000010101111000 7
#113
0-
b00000000000000000000011001000000 7
#114
b00000000000000000000000000000010 *
b00000000000000000000000000001001 +
b00000000000000000000000000000011 ,
1-
b0000 0
b0000 3
b00000000000000000000000000000001 5
#115
0-
#116
b00000000000000000000000000000001 *
b00000000000000000000000000001000 +
b00000000000000000000000000000100 ,
1-
#117
0-
#118
b00000000000000000000000000000111 +
1-
#119
0-
#120
b00000000000000000000000000000011 *
b00000000000000000000000000001010 +
1-
b0001 0
b0001 3
b00000000000000000000000000000010 5
b00000000000000000000011100001000 7
#121
0-
b00000000000000000000011111010000 7
#122
b00000000000000000000000000000010 *
b00000000000000000000000000001001 +
b00000000000000000000000000000011 ,
1-
b0000 0
b0000 3
b00000000000000000000000000000001 5
#123
0-
#124
b00000000000000000000000000000001 *
b00000000000000000000000000001000 +
b00000000000000000000000000000100 ,
1-
#125
0-
#126
b00000000000000000000000000000111 +
1-
#127
0-
#128
b00000000000000000000000000000011 *
b00000000000000000000000000001010 +
1-
b0001 0
b0001 3
b00000000000000000000000000000010 5
b00000000000000000000100010011000 7
#129
0-
b00000000000000000000100101100000 7
#130
b00000000000000000000000000000010 *
b00000000000000000000000000001001 +
b00000000000000000000000000000011 ,
1-
b0000 0
b0000 3
b00000000000000000000000000000001 5
#131
0-
#132
b00000000000000000000000000000001 *
b00000000000000000000000000001000 +
b00000000000000000000000000000100 ,
1-
b0011 2
#133
0-
#134
b00000000000000000000000000000111 +
1-
#135
0-
#136
b00000000000000000000000000000011 *
b00000000000000000000000000001010 +
1-
b0001 0
b0001 3
b00000000000000000000000000000010 5
b00000000000000000000101000101000 7
#137
0-
b00000000000000000000101011110000 7
#138
b00000000000000000000000000000010 *
b00000000000000000000000000001001 +
b00000000000000000000000000000011 ,
1-
b0000 0
b0000 3
b00000000000000000000000000000001 5
#139
0-
#140
b00000000000000000000000000000001 *
b00000000000000000000000000001000 +
b00000000000000000000000000000100 ,
1-
b0000 2
#141
0-
#142
b00000000000000000000000000000111 +
1-
#143
0-
#144
b00000000000000000000000000000110 +
1-
#145
0-
#146
b00000000000000000000000000000101 +
1-
#147
0-
#148
b00000000000000000000000000000010 *
b00000000000000000000000000001010 +
b00000000000000000000000000000011 ,
1-
b100 /
b00000000000000000000110110101100 6
#149
0-
b00000000000000000000111110100000 6
#150
b00000000000000000000000000000001 *
b00000000000000000000000000001001 +
b00000000000000000000000000000100 ,
1-
b000 /
b0111 2
#151
0-
#152
b00000000000000000000000000000010 *
b00000000000000000000000000001010 +
b00000000000000000000000000000011 ,
1-
b100 /
b00000000000000000001000110010100 6
#153
0-
b00000000000000000001001110001000 6
#154
b00000000000000000000000000000001 *
b00000000000000000000000000001001 +
b00000000000000000000000000000100 ,
1-
b000 /
b1111 2
#155
0-
#156
b00000000000000000000000000000010 *
b00000000000000000000000000001010 +
b00000000000000000000000000000011 ,
1-
b100 /
b00000000000000000001010101111100 6
#157
0-
b00000000000000000001011101110000 6
#158
b00000000000000000000000000000001 *
b00000000000000000000000000001001 +
b00000000000000000000000000000100 ,
1-
b000 /
#159
0-
#160
b00000000000000000000000000000011 *
b00000000000000000000000000001010 +
1-
b0010 0
b0010 3
b00000000000000000000000000000010 5
b00000000000000000000101111101010 7
#161
0-
b00000000000000000000110011100100 7
#162
b00000000000000000000000000000010 *
b00000000000000000000000000001001 +
b00000000000000000000000000000011 ,
1-
b0000 0
b0000 3
b00000000000000000000000000000001 5
#163
0-
#164
b00000000000000000000000000000001 *
b00000000000000000000000000001000 +
b00000000000000000000000000000100 ,
1-
#165
0-
#166
b00000000000000000000000000000111 +
1-
#167
0-
#168
b00000000000000000000000000000011 *
b00000000000000000000000000001010 +
1-
b0010 0
b0010 3
b00000000000000000000000000000010 5
b00000000000000000000110111011110 7
#169
0-
b00000000000000000000111011011000 7
#170
b00000000000000000000000000000010 *
b00000000000000000000000000001001 +
b00000000000000000000000000000011 ,
1-
b0000 0
b0000 3
b00000000000000000000000000000001 5
#171
0-
#172
b00000000000000000000000000000001 *
b00000000000000000000000000001000 +
b00000000000000000000000000000100 ,
1-
#173
0-
#174
b00000000000000000000000000000111 +
1-
#175
0-
#176
b00000000000000000000000000000011 *
b00000000000000000000000000001010 +
1-
b0010 0
b0010 3
b00000000000000000000000000000010 5
b00000000000000000000111111010010 7
#177
0-
b00000000000000000001000011001100 7
#178
b00000000000000000000000000000010 *
b00000000000000000000000000001001 +
b00000000000000000000000000000011 ,
1-
b0000 0
b0000 3
b00000000000000000000000000000001 5
#179
0-
#180
b00000000000000000000000000000001 *
b00000000000000000000000000001000 +
b00000000000000000000000000000100 ,
1-
b0111 2
#181
0-
#182
b00000000000000000000000000000111 +
1-
#183
0-
#184
b00000000000000000000000000000011 *
b00000000000000000000000000001010 +
1-
b0010 0
b0010 3
b00000000000000000000000000000010 5
b00000000000000000001000111000110 7
#185
0-
b00000000000000000001001011000000 7
#186
b00000000000000000000000000000010 *
b00000000000000000000000000001001 +
b00000000000000000000000000000011 ,
1-
b0000 0
b0000 3
b00000000000000000000000000000001 5
#187
0-
#188
b00000000000000000000000000000001 *
b00000000000000000000000000001000 +
b00000000000000000000000000000100 ,
1-
#189
0-
#190
b00000000000000000000000000000111 +
1-
#191
0-
#192
b00000000000000000000000000000011 *
b00000000000000000000000000001010 +
1-
b0010 0
b0010 3
b00000000000000000000000000000010 5
b00000000000000000001001110111010 7
#193
0-
b00000000000000000001010010110100 7
#194
b00000000000000000000000000000010 *
b00000000000000000000000000001001 +
b00000000000000000000000000000011 ,
1-
b0000 0
b0000 3
b00000000000000000000000000000001 5
#195
0-
#196
b00000000000000000000000000000001 *
b00000000000000000000000000001000 +
b00000000000000000000000000000100 ,
1-
b0011 2
#197
0-
#198
b00000000000000000000000000000111 +
1-
#199
0-
#200
b00000000000000000000000000000011 *
b00000000000000000000000000001010 +
1-
b0010 0
b0010 3
b00000000000000000000000000000010 5
b00000000000000000001010110101110 7
#201
0-
b00000000000000000001011010101000 7
#202
b00000000000000000000000000000010 *
b00000000000000000000000000001001 +
b00000000000000000000000000000011 ,
1-
b0000 0
b0000 3
b00000000000000000000000000000001 5
#203
0-
#204
b00000000000000000000000000000001 *
b00000000000000000000000000001000 +
b00000000000000000000000000000100 ,
1-
b0000 2
#205
0-
#206
b00000000000000000000000000000111 +
1-
#207
0-
#208
b00000000000000000000000000000010 *
b00000000000000000000000000001010 +
b00000000000000000000000000000011 ,
1-
b001 /
b00000000000000000001011110100010 6
#209
0-
b00000000000000000001011111010100 6
#210
b00000000000000000000000000000001 *
b00000000000000000000000000001001 +
b00000000000000000000000000000100 ,
1-
b000 /
#211
0-
#212
b00000000000000000000000000000010 *
b00000000000000000000000000001010 +
b00000000000000000000000000000011 ,
1-
b001 /
b00000000000000000001100000000110 6
#213
0-
b00000000000000000001100000111000 6
#214
b00000000000000000000000000000001 *
b00000000000000000000000000001001 +
b00000000000000000000000000000100 ,
1-
b000 /
b0001 2
#215
0-
#216
b00000000000000000000000000000010 *
b00000000000000000000000000001010 +
b00000000000000000000000000000011 ,
1-
b100 /
b00000000000000000001101000101100 6
#217
0-
b00000000000000000001110000100000 6
#218
b00000000000000000000000000000001 *
b00000000000000000000000000001001 +
b00000000000000000000000000000100 ,
1-
b000 /
b0111 2
#219
0-
#220
b00000000000000000000000000000010 *
b00000000000000000000000000001010 +
b00000000000000000000000000000011 ,
1-
b100 /
b00000000000000000001111000010100 6
#221
0-
b00000000000000000010000000001000 6
#222
b00000000000000000000000000000001 *
b00000000000000000000000000001001 +
b00000000000000000000000000000100 ,
1-
b000 /
b1111 2
#223
0-
#224
b00000000000000000000000000000010 *
b00000000000000000000000000001010 +
b00000000000000000000000000000011 ,
1-
b100 /
b00000000000000000010000111111100 6
#225
0-
b00000000000000000010001111110000 6
#226
b00000000000000000000000000000001 *
b00000000000000000000000000001001 +
b00000000000000000000000000000100 ,
1-
b000 /
#227
0-
#228
b00000000000000000000000000000011 *
b00000000000000000000000000001010 +
1-
b0100 0
b0100 3
b00000000000000000000000000000010 5
b00000000000000000001100010011100 7
#229
0-
b00000000000000000001101010010000 7
#230
b00000000000000000000000000000010 *
b00000000000000000000000000001001 +
b00000000000000000000000000000011 ,
1-
b0000 0
b0000 3
b00000000000000000000000000000001 5
#231
0-
#232
b00000000000000000000000000000001 *
b00000000000000000000000000001000 +
b00000000000000000000000000000100 ,
1-
#233
0-
#234
b00000000000000000000000000000111 +
1-
#235
0-
#236
b00000000000000000000000000000011 *
b00000000000000000000000000001010 +
1-
b0100 0
b0100 3
b00000000000000000000000000000010 5
b00000000000000000001110010000100 7
#237
0-
b00000000000000000001111001111000 7
#238
b00000000000000000000000000000010 *
b00000000000000000000000000001001 +
b00000000000000000000000000000011 ,
1-
b0000 0
b0000 3
b00000000000000000000000000000001 5
#239
0-
#240
b00000000000000000000000000000001 *
b00000000000000000000000000001000 +
b00000000000000000000000000000100 ,
1-
b0111 2
#241
0-
#242
b00000000000000000000000000000111 +
1-
#243
0-
#244
b00000000000000000000000000000011 *
b00000000000000000000000000001010 +
1-
b0100 0
b0100 3
b00000000000000000000000000000010 5
b00000000000000000010000001101100 7
#245
0-
b00000000000000000010001001100000 7
#246
b00000000000000000000000000000010 *
b00000000000000000000000000001001 +
b00000000000000000000000000000011 ,
1-
b0000 0
b0000 3
b00000000000000000000000000000001 5
#247
0-
#248
b00000000000000000000000000000001 *
b00000000000000000000000000001000 +
b00000000000000000000000000000100 ,
1-
b0001 2
#249
0-
#250
b00000000000000000000000000000111 +
1-
#251
0-
#252
b00000000000000000000000000000010 *
b00000000000000000000000000001010 +
b00000000000000000000000000000011 ,
1-
b100 /
b00000000000000000010010111100100 6
#253
0-
b00000000000000000010011111011000 6
#254
b00000000000000000000000000000001 *
b00000000000000000000000000001001 +
b00000000000000000000000000000100 ,
1-
b000 /
b0111 2
#255
0-
#256
b00000000000000000000000000000010 *
b00000000000000000000000000001010 +
b00000000000000000000000000000011 ,
1-
b100 /
b00000000000000000010100111001100 6
#257
0-
b00000000000000000010101111000000 6
#258
b00000000000000000000000000000001 *
b00000000000000000000000000001001 +
b00000000000000000000000000000100 ,
1-
b000 /
b1111 2
#259
0-
#260
b00000000000000000000000000000010 *
b00000000000000000000000000001010 +
b00000000000000000000000000000011 ,
1-
b100 /
b00000000000000000010110110110100 6
#261
0-
b00000000000000000010111110101000 6
#262
b00000000000000000000000000000001 *
b00000000000000000000000000001001 +
b00000000000000000000000000000100 ,
1-
b000 /
#263
0-
#264
b00000000000000000000000000000011 *
b00000000000000000000000000001010 +
1-
b1000 0
b1000 3
b00000000000000000000000000000010 5
b00000000000000000010011001001000 7
#265
0-
b00000000000000000010101000110000 7
#266
b00000000000000000000000000000010 *
b00000000000000000000000000001001 +
b00000000000000000000000000000011 ,
1-
b0000 0
b0000 3
b00000000000000000000000000000001 5
#267
0-
#268
b00000000000000000000000000000001 *
b00000000000000000000000000001000 +
b00000000000000000000000000000100 ,
1-
b0111 2
#269
0-
#270
b00000000000000000000000000000111 +
1-
#271
0-
#272
b00000000000000000000000000000010 *
b00000000000000000000000000001010 +
b00000000000000000000000000000011 ,
1-
b100 /
b00000000000000000011000110011100 6
#273
0-
b00000000000000000011001110010000 6
#274
b00000000000000000000000000000001 *
b00000000000000000000000000001001 +
b00000000000000000000000000000100 ,
1-
b000 /
b1111 2
#275
0-
#276
b00000000000000000000000000000011 *
b00000000000000000000000000001010 +
1-
b1000 0
b1000 3
b00000000000000000000000000000010 5
b00000000000000000010111000011000 7
#277
0-
b00000000000000000011001000000000 7
#278
b00000000000000000000000000000010 *
b00000000000000000000000000001001 +
b00000000000000000000000000000011 ,
1-
b0000 0
b0000 3
b00000000000000000000000000000001 5
#279
0-
#280
b00000000000000000000000000000001 *
b00000000000000000000000000001000 +
b00000000000000000000000000000100 ,
1-
b0001 2
#281
0-
