lab1/vending_machine/vending_machine_def.v
// Title         : vending_machine_def.v
// Author      : Jae-Eon Jo (Jojaeeon@postech.ac.kr) 
//					Dongup Kwon (nankdu7@postech.ac.kr)

// Macro constants (prefix k & CamelCase)
`define kTotalBits 32
  
`define kItemBits 8
`define kNumItems 4

`define kCoinBits 8
`define kNumCoins 3

`define kWaitTime 10

`define S0_init 32'h00
`define S1_wait 32'h01
`define S2_select 32'h02
`define S3_return 32'h03

lab1/vending_machine/change_state.v
`include "vending_machine_def.v"


module change_state(clk,reset_n,current_total_nxt,current_total);

	input clk;
	input reset_n;
	input [`kTotalBits-1:0] current_total_nxt;
	output reg [`kTotalBits-1:0] current_total;
	
	// Sequential circuit to reset or update the states
	always @(posedge clk ) begin
		if (!reset_n) begin
			// TODO: reset all states.

			//reset current_total(0)
			current_total <= `kTotalBits'b0;
		end
		else begin
			// TODO: update all states.
			
			// update current_total to current_total_nxt
			current_total <= current_total_nxt;
		end
	end
endmodule

lab1/vending_machine/calculate_current_state.v

`include "vending_machine_def.v"
	

module calculate_current_state(i_input_coin,i_select_item,item_price,coin_value,current_total,
input_total, output_total, return_total,current_total_nxt,wait_time,o_return_coin,o_available_item,o_output_item);


	
	input [`kNumCoins-1:0] i_input_coin,o_return_coin;
	input [`kNumItems-1:0]	i_select_item;			
	input [31:0] item_price [`kNumItems-1:0];
	input [31:0] coin_value [`kNumCoins-1:0];	
	input [`kTotalBits-1:0] current_total;
	input [31:0] wait_time;
	output reg [`kNumItems-1:0] o_available_item,o_output_item;
	output reg  [`kTotalBits-1:0] input_total, output_total, return_total;
	output reg  [`kTotalBits-1:0] current_total_nxt;
	integer i;	

	reg  [`kTotalBits-1:0] INPUT_tot;

	initial begin
		input_total = 0;
		output_total = 0;

		INPUT_tot = 0;

		return_total = input_total - output_total;
		//need to revise
		if (wait_time == 0 && o_return_coin > 0)
			return_total = 0;
	end

	// Combinational logic for the next states
	always @(*) begin
		// TODO: current_total_nxt
		// You don't have to worry about concurrent activations in each input vector (or array).
		// Calculate the next current_total state.
		
		case (current_total)
			`S0_init:
				current_total_nxt = `S1_wait;
			`S1_wait:
				if(i_input_coin > 0) 
					current_total_nxt = `S2_coin;
				else if(i_select_item > 0) 
					current_total_nxt = `S3_select;
			`S2_coin:
				current_total_nxt = `S1_wait;
			`S3_select:
				if (o_available_item > 0) 
					current_total_nxt = `S1_wait;
				else if (input_total > output_total)
					current_total_nxt = `S1_wait;
				else
					current_total_nxt = `S0_init;
			default: begin current_total_nxt = `S0_init; end
		endcase
		
	end

	
	// Combinational logic for the outputs
	always @(*) begin
		// TODO: o_available_item
		// TODO: o_output_item
		//$monitor("state: %h, coin: %h", current_total, input_total);
		case (current_total)
			`S0_init: begin
				input_total = 0;
				INPUT_tot = 0;
				output_total = 0;
				return_total = 0;
				o_available_item = 0;
			end
			`S1_wait: begin
				for (i = 0; i < `kNumItems; i = i+1) begin
					if (input_total - output_total >= item_price[i])
						o_available_item[i] = 1;
					else
						o_available_item[i] = 0;
				end
			end
			`S2_coin: begin
				for (i = 0; i < `kNumCoins; i = i+1) begin
					if (i_input_coin[i]) begin
						input_total = input_total + coin_value[i] / 2;
						
					end
				end
				INPUT_tot = INPUT_tot + coin_value[0];
			end
			`S3_select: begin
				for (i = 0; i < `kNumItems; i = i+1) begin
					if (i_select_item[i] && o_available_item[i]) begin
						o_output_item[i] = 1;
						output_total = output_total + item_price[i] / 2;
					end
					else begin
						o_output_item[i] = 0;
					end
				end
			end
			default: return_total = input_total - output_total;
		endcase

	end
 
	


endmodule

lab1/vending_machine/check_time_and_coin.v
`include "vending_machine_def.v"

	

module check_time_and_coin(i_input_coin,i_select_item,clk,reset_n,wait_time,o_return_coin);
	input clk;
	input reset_n;
	input [`kNumCoins-1:0] i_input_coin;
	input [`kNumItems-1:0]	i_select_item;
	output reg  [`kNumCoins-1:0] o_return_coin;
	output reg [31:0] wait_time;

	// initiate values
	initial begin
		// TODO: initiate values

		// initiate o_return_coin(0000), wait_time(100) //
	end


	// update coin return time
	always @(i_input_coin, i_select_item) begin
		// TODO: update coin return time

		// wait_time will be initialized to original
	end

	always @(*) begin
		// TODO: o_return_coin

		// NOT SURE if select item and avail, subtract price of item from the o_return_coin
	end

	always @(posedge clk ) begin
		if (!reset_n) begin
		// TODO: reset all states.

		// reset all output value //
		end
		else begin
		// TODO: update all states.

		// update output value - wait_time decresing //
		end
	end
endmodule

lab1/vending_machine/vending_machine.v
// Title         : vending_machine.v
// Author      : Jae-Eon Jo (Jojaeeon@postech.ac.kr) 
//			     Dongup Kwon (nankdu7@postech.ac.kr) (2015.03.30)
//			     Jaehun Ryu (jaehunryu@postech.ac.kr) (2021.03.07)

`include "vending_machine_def.v"


module vending_machine (
	clk,							// Clock signal
	reset_n,						// Reset signal (active-low)

	i_input_coin,				// coin is inserted.
	i_select_item,				// item is selected.
	i_trigger_return,			// change-return is triggered 

	o_available_item,			// Sign of the item availability
	o_output_item,			// Sign of the item withdrawal
	o_return_coin				// Sign of the coin return
);

	// Ports Declaration
	// Do not modify the module interface
	input clk;
	input reset_n;
	
	input [`kNumCoins-1:0] i_input_coin;
	input [`kNumItems-1:0] i_select_item;
	input i_trigger_return;
		
	output [`kNumItems-1:0] o_available_item;
	output [`kNumItems-1:0] o_output_item;
	output [`kNumCoins-1:0] o_return_coin;


	

	// Do not modify the values.
	wire [31:0] item_price [`kNumItems-1:0];	// Price of each item
	wire [31:0] coin_value [`kNumCoins-1:0];	// Value of each coin
	assign item_price[0] = 400;
	assign item_price[1] = 500;
	assign item_price[2] = 1000;
	assign item_price[3] = 2000;
	assign coin_value[0] = 100;
	assign coin_value[1] = 500;
	assign coin_value[2] = 1000;

	// Internal states. You may add your own net variables.
	wire [`kTotalBits-1:0] current_total;
	
	// Next internal states. You may add your own net variables.
	wire [`kTotalBits-1:0] current_total_nxt;

	
	// Variables. You may add more your own net variables.
	wire [`kTotalBits-1:0] input_total, output_total, return_total;
	wire [31:0] wait_time;


	// This module interface, structure, and given a number of modules are not mandatory but recommended.
	// However, Implementations that use modules are mandatory.
	wire ret;
	wire [31:0] rett;
	assign ret = i_trigger_return;
	assign rett = input_total;
	assign rett = output_total;
	assign rett = return_total;
	assign rett = rett;
	assign ret = ret;
	
  	check_time_and_coin check_time_and_coin_module(.i_input_coin(i_input_coin),
  									.i_select_item(i_select_item),
									.clk(clk),
									.reset_n(reset_n),
									.wait_time(wait_time),
									.o_return_coin(o_return_coin));

	calculate_current_state calculate_current_state_module(.i_input_coin(i_input_coin),
										.i_select_item(i_select_item),
										.item_price(item_price),
										.coin_value(coin_value),
										.current_total(current_total),
										.input_total(input_total),
										.output_total(output_total),
										.return_total(return_total),
										.current_total_nxt(current_total_nxt),
										.wait_time(wait_time),
										.o_return_coin(o_return_coin),
										.o_available_item(o_available_item),
										.o_output_item(o_output_item));
	
  	change_state change_state_module(
						.clk(clk),
						.reset_n(reset_n),
						.current_total_nxt(current_total_nxt),
						.current_total(current_total));


endmodule

lab1/vending_machine/waveform.vcd
$version Generated by VerilatedVcd $end
$timescale 1ps $end
 $scope module TOP $end
  $var wire 1 . clk $end
  $var wire 1 / reset_n $end
  $var wire 3 0 i_input_coin [2:0] $end
  $var wire 4 1 i_select_item [3:0] $end
  $var wire 1 2 i_trigger_return $end
  $var wire 4 3 o_available_item [3:0] $end
  $var wire 4 4 o_output_item [3:0] $end
  $var wire 3 5 o_return_coin [2:0] $end
  $scope module vending_machine $end
   $var wire 1 . clk $end
   $var wire 1 / reset_n $end
   $var wire 3 0 i_input_coin [2:0] $end
   $var wire 4 1 i_select_item [3:0] $end
   $var wire 1 2 i_trigger_return $end
   $var wire 4 3 o_available_item [3:0] $end
   $var wire 4 4 o_output_item [3:0] $end
   $var wire 3 5 o_return_coin [2:0] $end
   $var wire 32 # item_price[0] [31:0] $end
   $var wire 32 $ item_price[1] [31:0] $end
   $var wire 32 % item_price[2] [31:0] $end
   $var wire 32 & item_price[3] [31:0] $end
   $var wire 32 ' coin_value[0] [31:0] $end
   $var wire 32 ( coin_value[1] [31:0] $end
   $var wire 32 ) coin_value[2] [31:0] $end
   $var wire 32 * current_total [31:0] $end
   $var wire 32 6 current_total_nxt [31:0] $end
   $var wire 32 7 input_total [31:0] $end
   $var wire 32 8 output_total [31:0] $end
   $var wire 32 9 return_total [31:0] $end
   $var wire 32 + wait_time [31:0] $end
   $var wire 1 2 ret $end
   $var wire 32 7 rett [31:0] $end
   $scope module calculate_current_state_module $end
    $var wire 3 0 i_input_coin [2:0] $end
    $var wire 3 5 o_return_coin [2:0] $end
    $var wire 4 1 i_select_item [3:0] $end
    $var wire 32 # item_price[0] [31:0] $end
    $var wire 32 $ item_price[1] [31:0] $end
    $var wire 32 % item_price[2] [31:0] $end
    $var wire 32 & item_price[3] [31:0] $end
    $var wire 32 ' coin_value[0] [31:0] $end
    $var wire 32 ( coin_value[1] [31:0] $end
    $var wire 32 ) coin_value[2] [31:0] $end
    $var wire 32 * current_total [31:0] $end
    $var wire 32 + wait_time [31:0] $end
    $var wire 4 3 o_available_item [3:0] $end
    $var wire 4 4 o_output_item [3:0] $end
    $var wire 32 7 input_total [31:0] $end
    $var wire 32 8 output_total [31:0] $end
    $var wire 32 9 return_total [31:0] $end
    $var wire 32 6 current_total_nxt [31:0] $end
    $var wire 32 , i [31:0] $end
    $var wire 32 - INPUT_tot [31:0] $end
   $upscope $end
   $scope module change_state_module $end
    $var wire 1 . clk $end
    $var wire 1 / reset_n $end
    $var wire 32 6 current_total_nxt [31:0] $end
    $var wire 32 * current_total [31:0] $end
   $upscope $end
   $scope module check_time_and_coin_module $end
    $var wire 1 . clk $end
    $var wire 1 / reset_n $end
    $var wire 3 0 i_input_coin [2:0] $end
    $var wire 4 1 i_select_item [3:0] $end
    $var wire 3 5 o_return_coin [2:0] $end
    $var wire 32 + wait_time [31:0] $end
   $upscope $end
  $upscope $end
 $upscope $end
$enddefinitions $end


#0
b00000000000000000000000110010000 #
b00000000000000000000000111110100 $
b00000000000000000000001111101000 %
b00000000000000000000011111010000 &
b00000000000000000000000001100100 '
b00000000000000000000000111110100 (
b00000000000000000000001111101000 )
b01110011010110000001011000110101 *
b00000000000000000000000000001010 +
b11000110011011010100110101011000 ,
b00000000000000000000000000000000 -
1.
1/
b000 0
b0000 1
02
b1100 3
b0110 4
b000 5
b00000000000000000000000000000000 6
b00000000000000000000000000000000 7
b00000000000000000000000000000000 8
b00000000000000000000000000000000 9
#1
0.
#2
b00000000000000000000000000000000 *
b00000000000000000000000000001001 +
1.
0/
b0000 3
b001 5
b00000000000000000000000000000001 6
#3
0.
#4
b00000000000000000000000000001000 +
1.
#5
0.
#6
b00000000000000000000000000000001 *
b00000000000000000000000000000111 +
b00000000000000000000000000000100 ,
1.
1/
#7
0.
#8
b00000000000000000000000000000010 *
b00000000000000000000000000001010 +
b00000000000000000000000000000011 ,
b00000000000000000000000001100100 -
1.
b001 0
b00000000000000000000000000110010 7
#9
0.
b00000000000000000000000001100100 7
#10
b00000000000000000000000000000001 *
b00000000000000000000000000001001 +
b00000000000000000000000000000100 ,
1.
b000 0
#11
0.
#12
b00000000000000000000000000000010 *
b00000000000000000000000000001010 +
b00000000000000000000000000000011 ,
b00000000000000000000000011001000 -
1.
b001 0
b00000000000000000000000010010110 7
#13
0.
b00000000000000000000000011001000 7
#14
b00000000000000000000000000000001 *
b00000000000000000000000000001001 +
b00000000000000000000000000000100 ,
1.
b000 0
#15
0.
#16
b00000000000000000000000000000010 *
b00000000000000000000000000001010 +
b00000000000000000000000000000011 ,
b00000000000000000000000100101100 -
1.
b001 0
b00000000000000000000000011111010 7
#17
0.
b00000000000000000000000100101100 7
#18
b00000000000000000000000000000001 *
b00000000000000000000000000001001 +
b00000000000000000000000000000100 ,
1.
b000 0
#19
0.
#20
b00000000000000000000000000000010 *
b00000000000000000000000000001010 +
b00000000000000000000000000000011 ,
b00000000000000000000000110010000 -
1.
b001 0
b00000000000000000000000101011110 7
#21
0.
b00000000000000000000000110010000 7
#22
b00000000000000000000000000000001 *
b00000000000000000000000000001001 +
b00000000000000000000000000000100 ,
1.
b000 0
b0001 3
#23
0.
#24
b00000000000000000000000000000010 *
b00000000000000000000000000001010 +
b00000000000000000000000000000011 ,
b00000000000000000000000111110100 -
1.
b001 0
b00000000000000000000000111000010 7
#25
0.
b00000000000000000000000111110100 7
#26
b00000000000000000000000000000001 *
b00000000000000000000000000001001 +
b00000000000000000000000000000100 ,
1.
b000 0
b0011 3
#27
0.
#28
b00000000000000000000000000001000 +
1.
#29
0.
#30
b00000000000000000000000000000000 *
b00000000000000000000000000000111 +
b00000000000000000000000000000000 -
1.
0/
b0000 3
b00000000000000000000000000000000 7
#31
0.
#32
b00000000000000000000000000000110 +
1.
#33
0.
#34
b00000000000000000000000000000001 *
b00000000000000000000000000000101 +
1.
1/
#35
0.
#36
b00000000000000000000000000000010 *
b00000000000000000000000000001010 +
b00000000000000000000000000000011 ,
b00000000000000000000000001100100 -
1.
b010 0
b00000000000000000000000011111010 7
#37
0.
b00000000000000000000000111110100 7
#38
b00000000000000000000000000000001 *
b00000000000000000000000000001001 +
b00000000000000000000000000000100 ,
1.
b000 0
b0011 3
#39
0.
#40
b00000000000000000000000000000010 *
b00000000000000000000000000001010 +
b00000000000000000000000000000011 ,
b00000000000000000000000011001000 -
1.
b010 0
b00000000000000000000001011101110 7
#41
0.
b00000000000000000000001111101000 7
#42
b00000000000000000000000000000001 *
b00000000000000000000000000001001 +
b00000000000000000000000000000100 ,
1.
b000 0
b0111 3
#43
0.
#44
b00000000000000000000000000000010 *
b00000000000000000000000000001010 +
b00000000000000000000000000000011 ,
b00000000000000000000000100101100 -
1.
b010 0
b00000000000000000000010011100010 7
#45
0.
b00000000000000000000010111011100 7
#46
b00000000000000000000000000000001 *
b00000000000000000000000000001001 +
b00000000000000000000000000000100 ,
1.
b000 0
#47
0.
#48
b00000000000000000000000000000010 *
b00000000000000000000000000001010 +
b00000000000000000000000000000011 ,
b00000000000000000000000110010000 -
1.
b010 0
b00000000000000000000011011010110 7
#49
0.
b00000000000000000000011111010000 7
#50
b00000000000000000000000000000001 *
b00000000000000000000000000001001 +
b00000000000000000000000000000100 ,
1.
b000 0
b1111 3
#51
0.
#52
b00000000000000000000000000001000 +
1.
#53
0.
#54
b00000000000000000000000000000000 *
b00000000000000000000000000000111 +
b00000000000000000000000000000000 -
1.
0/
b0000 3
b00000000000000000000000000000000 7
#55
0.
#56
b00000000000000000000000000000110 +
1.
#57
0.
#58
b00000000000000000000000000000001 *
b00000000000000000000000000000101 +
1.
1/
#59
0.
#60
b00000000000000000000000000000010 *
b00000000000000000000000000001010 +
b00000000000000000000000000000011 ,
b00000000000000000000000001100100 -
1.
b100 0
b00000000000000000000000111110100 7
#61
0.
b00000000000000000000001111101000 7
#62
b00000000000000000000000000000001 *
b00000000000000000000000000001001 +
b00000000000000000000000000000100 ,
1.
b000 0
b0111 3
#63
0.
#64
b00000000000000000000000000000010 *
b00000000000000000000000000001010 +
b00000000000000000000000000000011 ,
b00000000000000000000000011001000 -
1.
b100 0
b00000000000000000000010111011100 7
#65
0.
b00000000000000000000011111010000 7
#66
b00000000000000000000000000000001 *
b00000000000000000000000000001001 +
b00000000000000000000000000000100 ,
1.
b000 0
b1111 3
#67
0.
#68
b00000000000000000000000000001000 +
1.
#69
0.
#70
b00000000000000000000000000000000 *
b00000000000000000000000000000111 +
b00000000000000000000000000000000 -
1.
0/
b0000 3
b00000000000000000000000000000000 7
#71
0.
#72
b00000000000000000000000000000110 +
1.
#73
0.
#74
b00000000000000000000000000000001 *
b00000000000000000000000000000101 +
1.
1/
#75
0.
#76
b00000000000000000000000000000010 *
b00000000000000000000000000001010 +
b00000000000000000000000000000011 ,
b00000000000000000000000001100100 -
1.
b100 0
b00000000000000000000000111110100 7
#77
0.
b00000000000000000000001111101000 7
#78
b00000000000000000000000000000001 *
b00000000000000000000000000001001 +
b00000000000000000000000000000100 ,
1.
b000 0
b0111 3
#79
0.
#80
b00000000000000000000000000000010 *
b00000000000000000000000000001010 +
b00000000000000000000000000000011 ,
b00000000000000000000000011001000 -
1.
b100 0
b00000000000000000000010111011100 7
#81
0.
b00000000000000000000011111010000 7
#82
b00000000000000000000000000000001 *
b00000000000000000000000000001001 +
b00000000000000000000000000000100 ,
1.
b000 0
b1111 3
#83
0.
#84
b00000000000000000000000000000010 *
b00000000000000000000000000001010 +
b00000000000000000000000000000011 ,
b00000000000000000000000100101100 -
1.
b100 0
b00000000000000000000100111000100 7
#85
0.
b00000000000000000000101110111000 7
#86
b00000000000000000000000000000001 *
b00000000000000000000000000001001 +
b00000000000000000000000000000100 ,
1.
b000 0
#87
0.
#88
b00000000000000000000000000000011 *
b00000000000000000000000000001010 +
1.
b0001 1
b0001 4
b00000000000000000000000011001000 8
#89
0.
b00000000000000000000000110010000 8
#90
b00000000000000000000000000000001 *
b00000000000000000000000000001001 +
1.
b0000 1
b0000 4
#91
0.
#92
b00000000000000000000000000001000 +
1.
#93
0.
#94
b00000000000000000000000000000111 +
1.
#95
0.
#96
b00000000000000000000000000000011 *
b00000000000000000000000000001010 +
1.
b0001 1
b0001 4
b00000000000000000000001001011000 8
#97
0.
b00000000000000000000001100100000 8
#98
b00000000000000000000000000000001 *
b00000000000000000000000000001001 +
1.
b0000 1
b0000 4
#99
0.
#100
b00000000000000000000000000001000 +
1.
#101
0.
#102
b00000000000000000000000000000111 +
1.
#103
0.
#104
b00000000000000000000000000000011 *
b00000000000000000000000000001010 +
1.
b0001 1
b0001 4
b00000000000000000000001111101000 8
#105
0.
b00000000000000000000010010110000 8
#106
b00000000000000000000000000000001 *
b00000000000000000000000000001001 +
1.
b0000 1
b0111 3
b0000 4
#107
0.
#108
b00000000000000000000000000001000 +
1.
#109
0.
#110
b00000000000000000000000000000111 +
1.
#111
0.
#112
b00000000000000000000000000000011 *
b00000000000000000000000000001010 +
1.
b0001 1
b0001 4
b00000000000000000000010101111000 8
#113
0.
b00000000000000000000011001000000 8
#114
b00000000000000000000000000000001 *
b00000000000000000000000000001001 +
1.
b0000 1
b0000 4
#115
0.
#116
b00000000000000000000000000001000 +
1.
#117
0.
#118
b00000000000000000000000000000111 +
1.
#119
0.
#120
b00000000000000000000000000000011 *
b00000000000000000000000000001010 +
1.
b0001 1
b0001 4
b00000000000000000000011100001000 8
#121
0.
b00000000000000000000011111010000 8
#122
b00000000000000000000000000000001 *
b00000000000000000000000000001001 +
1.
b0000 1
b0000 4
#123
0.
#124
b00000000000000000000000000001000 +
1.
#125
0.
#126
b00000000000000000000000000000111 +
1.
#127
0.
#128
b00000000000000000000000000000011 *
b00000000000000000000000000001010 +
1.
b0001 1
b0001 4
b00000000000000000000100010011000 8
#129
0.
b00000000000000000000100101100000 8
#130
b00000000000000000000000000000001 *
b00000000000000000000000000001001 +
1.
b0000 1
b0011 3
b0000 4
#131
0.
#132
b00000000000000000000000000001000 +
1.
#133
0.
#134
b00000000000000000000000000000111 +
1.
#135
0.
#136
b00000000000000000000000000000011 *
b00000000000000000000000000001010 +
1.
b0001 1
b0001 4
b00000000000000000000101000101000 8
#137
0.
b00000000000000000000101011110000 8
#138
b00000000000000000000000000000001 *
b00000000000000000000000000001001 +
1.
b0000 1
b0000 3
b0000 4
#139
0.
#140
b00000000000000000000000000001000 +
1.
#141
0.
#142
b00000000000000000000000000000111 +
1.
#143
0.
#144
b00000000000000000000000000000110 +
1.
#145
0.
#146
b00000000000000000000000000000101 +
1.
#147
0.
#148
b00000000000000000000000000000010 *
b00000000000000000000000000001010 +
b00000000000000000000000000000011 ,
b00000000000000000000000110010000 -
1.
b100 0
b00000000000000000000110110101100 7
#149
0.
b00000000000000000000111110100000 7
#150
b00000000000000000000000000000001 *
b00000000000000000000000000001001 +
b00000000000000000000000000000100 ,
1.
b000 0
b0111 3
#151
0.
#152
b00000000000000000000000000000010 *
b00000000000000000000000000001010 +
b00000000000000000000000000000011 ,
b00000000000000000000000111110100 -
1.
b100 0
b00000000000000000001000110010100 7
#153
0.
b00000000000000000001001110001000 7
#154
b00000000000000000000000000000001 *
b00000000000000000000000000001001 +
b00000000000000000000000000000100 ,
1.
b000 0
b1111 3
#155
0.
#156
b00000000000000000000000000000010 *
b00000000000000000000000000001010 +
b00000000000000000000000000000011 ,
b00000000000000000000001001011000 -
1.
b100 0
b00000000000000000001010101111100 7
#157
0.
b00000000000000000001011101110000 7
#158
b00000000000000000000000000000001 *
b00000000000000000000000000001001 +
b00000000000000000000000000000100 ,
1.
b000 0
#159
0.
#160
b00000000000000000000000000000011 *
b00000000000000000000000000001010 +
1.
b0010 1
b0010 4
b00000000000000000000101111101010 8
#161
0.
b00000000000000000000110011100100 8
#162
b00000000000000000000000000000001 *
b00000000000000000000000000001001 +
1.
b0000 1
b0000 4
#163
0.
#164
b00000000000000000000000000001000 +
1.
#165
0.
#166
b00000000000000000000000000000111 +
1.
#167
0.
#168
b00000000000000000000000000000011 *
b00000000000000000000000000001010 +
1.
b0010 1
b0010 4
b00000000000000000000110111011110 8
#169
0.
b00000000000000000000111011011000 8
#170
b00000000000000000000000000000001 *
b00000000000000000000000000001001 +
1.
b0000 1
b0000 4
#171
0.
#172
b00000000000000000000000000001000 +
1.
#173
0.
#174
b00000000000000000000000000000111 +
1.
#175
0.
#176
b00000000000000000000000000000011 *
b00000000000000000000000000001010 +
1.
b0010 1
b0010 4
b00000000000000000000111111010010 8
#177
0.
b00000000000000000001000011001100 8
#178
b00000000000000000000000000000001 *
b00000000000000000000000000001001 +
1.
b0000 1
b0111 3
b0000 4
#179
0.
#180
b00000000000000000000000000001000 +
1.
#181
0.
#182
b00000000000000000000000000000111 +
1.
#183
0.
#184
b00000000000000000000000000000011 *
b00000000000000000000000000001010 +
1.
b0010 1
b0010 4
b00000000000000000001000111000110 8
#185
0.
b00000000000000000001001011000000 8
#186
b00000000000000000000000000000001 *
b00000000000000000000000000001001 +
1.
b0000 1
b0000 4
#187
0.
#188
b00000000000000000000000000001000 +
1.
#189
0.
#190
b00000000000000000000000000000111 +
1.
#191
0.
#192
b00000000000000000000000000000011 *
b00000000000000000000000000001010 +
1.
b0010 1
b0010 4
b00000000000000000001001110111010 8
#193
0.
b00000000000000000001010010110100 8
#194
b00000000000000000000000000000001 *
b00000000000000000000000000001001 +
1.
b0000 1
b0011 3
b0000 4
#195
0.
#196
b00000000000000000000000000001000 +
1.
#197
0.
#198
b00000000000000000000000000000111 +
1.
#199
0.
#200
b00000000000000000000000000000011 *
b00000000000000000000000000001010 +
1.
b0010 1
b0010 4
b00000000000000000001010110101110 8
#201
0.
b00000000000000000001011010101000 8
#202
b00000000000000000000000000000001 *
b00000000000000000000000000001001 +
1.
b0000 1
b0000 3
b0000 4
#203
0.
#204
b00000000000000000000000000001000 +
1.
#205
0.
#206
b00000000000000000000000000000111 +
1.
#207
0.
#208
b00000000000000000000000000000010 *
b00000000000000000000000000001010 +
b00000000000000000000000000000011 ,
b00000000000000000000001010111100 -
1.
b001 0
b00000000000000000001011110100010 7
#209
0.
b00000000000000000001011111010100 7
#210
b00000000000000000000000000000001 *
b00000000000000000000000000001001 +
b00000000000000000000000000000100 ,
1.
b000 0
#211
0.
#212
b00000000000000000000000000000010 *
b00000000000000000000000000001010 +
b00000000000000000000000000000011 ,
b00000000000000000000001100100000 -
1.
b001 0
b00000000000000000001100000000110 7
#213
0.
b00000000000000000001100000111000 7
#214
b00000000000000000000000000000001 *
b00000000000000000000000000001001 +
b00000000000000000000000000000100 ,
1.
b000 0
b0001 3
#215
0.
#216
b00000000000000000000000000000010 *
b00000000000000000000000000001010 +
b00000000000000000000000000000011 ,
b00000000000000000000001110000100 -
1.
b100 0
b00000000000000000001101000101100 7
#217
0.
b00000000000000000001110000100000 7
#218
b00000000000000000000000000000001 *
b00000000000000000000000000001001 +
b00000000000000000000000000000100 ,
1.
b000 0
b0111 3
#219
0.
#220
b00000000000000000000000000000010 *
b00000000000000000000000000001010 +
b00000000000000000000000000000011 ,
b00000000000000000000001111101000 -
1.
b100 0
b00000000000000000001111000010100 7
#221
0.
b00000000000000000010000000001000 7
#222
b00000000000000000000000000000001 *
b00000000000000000000000000001001 +
b00000000000000000000000000000100 ,
1.
b000 0
b1111 3
#223
0.
#224
b00000000000000000000000000000010 *
b00000000000000000000000000001010 +
b00000000000000000000000000000011 ,
b00000000000000000000010001001100 -
1.
b100 0
b00000000000000000010000111111100 7
#225
0.
b00000000000000000010001111110000 7
#226
b00000000000000000000000000000001 *
b00000000000000000000000000001001 +
b00000000000000000000000000000100 ,
1.
b000 0
#227
0.
#228
b00000000000000000000000000000011 *
b00000000000000000000000000001010 +
1.
b0100 1
b0100 4
b00000000000000000001100010011100 8
#229
0.
b00000000000000000001101010010000 8
#230
b00000000000000000000000000000001 *
b00000000000000000000000000001001 +
1.
b0000 1
b0000 4
#231
0.
#232
b00000000000000000000000000001000 +
1.
#233
0.
#234
b00000000000000000000000000000111 +
1.
#235
0.
#236
b00000000000000000000000000000011 *
b00000000000000000000000000001010 +
1.
b0100 1
b0100 4
b00000000000000000001110010000100 8
#237
0.
b00000000000000000001111001111000 8
#238
b00000000000000000000000000000001 *
b00000000000000000000000000001001 +
1.
b0000 1
b0111 3
b0000 4
#239
0.
#240
b00000000000000000000000000001000 +
1.
#241
0.
#242
b00000000000000000000000000000111 +
1.
#243
0.
#244
b00000000000000000000000000000011 *
b00000000000000000000000000001010 +
1.
b0100 1
b0100 4
b00000000000000000010000001101100 8
#245
0.
b00000000000000000010001001100000 8
#246
b00000000000000000000000000000001 *
b00000000000000000000000000001001 +
1.
b0000 1
b0001 3
b0000 4
#247
0.
#248
b00000000000000000000000000001000 +
1.
#249
0.
#250
b00000000000000000000000000000111 +
1.
#251
0.
#252
b00000000000000000000000000000010 *
b00000000000000000000000000001010 +
b00000000000000000000000000000011 ,
b00000000000000000000010010110000 -
1.
b100 0
b00000000000000000010010111100100 7
#253
0.
b00000000000000000010011111011000 7
#254
b00000000000000000000000000000001 *
b00000000000000000000000000001001 +
b00000000000000000000000000000100 ,
1.
b000 0
b0111 3
#255
0.
#256
b00000000000000000000000000000010 *
b00000000000000000000000000001010 +
b00000000000000000000000000000011 ,
b00000000000000000000010100010100 -
1.
b100 0
b00000000000000000010100111001100 7
#257
0.
b00000000000000000010101111000000 7
#258
b00000000000000000000000000000001 *
b00000000000000000000000000001001 +
b00000000000000000000000000000100 ,
1.
b000 0
b1111 3
#259
0.
#260
b00000000000000000000000000000010 *
b00000000000000000000000000001010 +
b00000000000000000000000000000011 ,
b00000000000000000000010101111000 -
1.
b100 0
b00000000000000000010110110110100 7
#261
0.
b00000000000000000010111110101000 7
#262
b00000000000000000000000000000001 *
b00000000000000000000000000001001 +
b00000000000000000000000000000100 ,
1.
b000 0
#263
0.
#264
b00000000000000000000000000000011 *
b00000000000000000000000000001010 +
1.
b1000 1
b1000 4
b00000000000000000010011001001000 8
#265
0.
b00000000000000000010101000110000 8
#266
b00000000000000000000000000000001 *
b00000000000000000000000000001001 +
1.
b0000 1
b0111 3
b0000 4
#267
0.
#268
b00000000000000000000000000001000 +
1.
#269
0.
#270
b00000000000000000000000000000111 +
1.
#271
0.
#272
b00000000000000000000000000000010 *
b00000000000000000000000000001010 +
b00000000000000000000000000000011 ,
b00000000000000000000010111011100 -
1.
b100 0
b00000000000000000011000110011100 7
#273
0.
b00000000000000000011001110010000 7
#274
b00000000000000000000000000000001 *
b00000000000000000000000000001001 +
b00000000000000000000000000000100 ,
1.
b000 0
b1111 3
#275
0.
#276
b00000000000000000000000000000011 *
b00000000000000000000000000001010 +
1.
b1000 1
b1000 4
b00000000000000000010111000011000 8
#277
0.
b00000000000000000011001000000000 8
#278
b00000000000000000000000000000001 *
b00000000000000000000000000001001 +
1.
b0000 1
b0001 3
b0000 4
#279
0.
#280
b00000000000000000000000000001000 +
1.
#281
0.
#282
b00000000000000000000000000000111 +
1.
#283
0.
#284
b00000000000000000000000000000010 *
b00000000000000000000000000001010 +
b00000000000000000000000000000011 ,
b00000000000000000000011001000000 -
1.
b001 0
b00000000000000000011001111000010 7
#285
0.
b00000000000000000011001111110100 7
#286
b00000000000000000000000000000001 *
b00000000000000000000000000001001 +
b00000000000000000000000000000100 ,
1.
b000 0
b0011 3
#287
0.
#288
b00000000000000000000000000000010 *
b00000000000000000000000000001010 +
b00000000000000000000000000000011 ,
b00000000000000000000011010100100 -
1.
b001 0
b00000000000000000011010000100110 7
#289
0.
b00000000000000000011010001011000 7
#290
b00000000000000000000000000000001 *
b00000000000000000000000000001001 +
b00000000000000000000000000000100 ,
1.
b000 0
#291
0.
#292
b00000000000000000000000000000010 *
b00000000000000000000000000001010 +
b00000000000000000000000000000011 ,
b00000000000000000000011100001000 -
1.
b001 0
b00000000000000000011010010001010 7
#293
0.
b00000000000000000011010010111100 7
#294
b00000000000000000000000000000001 *
b00000000000000000000000000001001 +
b00000000000000000000000000000100 ,
1.
b000 0
#295
0.
#296
b00000000000000000000000000000010 *
b00000000000000000000000000001010 +
b00000000000000000000000000000011 ,
b00000000000000000000011101101100 -
1.
b001 0
b00000000000000000011010011101110 7
#297
0.
b00000000000000000011010100100000 7
#298
b00000000000000000000000000000001 *
b00000000000000000000000000001001 +
b00000000000000000000000000000100 ,
1.
b000 0
#299
0.
#300
b00000000000000000000000000000010 *
b00000000000000000000000000001010 +
b00000000000000000000000000000011 ,
b00000000000000000000011111010000 -
1.
b010 0
b00000000000000000011011000011010 7
#301
0.
b00000000000000000011011100010100 7
#302
b00000000000000000000000000000001 *
b00000000000000000000000000001001 +
b00000000000000000000000000000100 ,
1.
b000 0
b0111 3
#303
0.
