lab1/vending_machine/vending_machine_def.v
// Title         : vending_machine_def.v
// Author      : Jae-Eon Jo (Jojaeeon@postech.ac.kr) 
//					Dongup Kwon (nankdu7@postech.ac.kr)

// Macro constants (prefix k & CamelCase)
`define kTotalBits 32
  
`define kItemBits 8
`define kNumItems 4

`define kCoinBits 8
`define kNumCoins 3

`define kWaitTime 10

`define S0_init 32'h00
`define S1_wait 32'h01
`define S2_select 32'h02
`define S3_return 32'h03

lab1/vending_machine/change_state.v
`include "vending_machine_def.v"


module change_state(clk,reset_n,current_total_nxt,current_total);

	input clk;
	input reset_n;
	input [`kTotalBits-1:0] current_total_nxt;
	output reg [`kTotalBits-1:0] current_total;
	
	// Sequential circuit to reset or update the states
	always @(posedge clk ) begin
		if (!reset_n) begin
			// TODO: reset all states.

			//reset current_total(0)
			current_total <= `kTotalBits'b0;
		end
		else begin
			// TODO: update all states.
			
			// update current_total to current_total_nxt
			current_total <= current_total_nxt;
		end
	end
endmodule

lab1/vending_machine/calculate_current_state.v

`include "vending_machine_def.v"
	

module calculate_current_state(i_input_coin,i_select_item,i_trigger_return,item_price,coin_value,current_total,
input_total, output_total, return_total,current_total_nxt,wait_time,o_return_coin,o_available_item,o_output_item);

	input i_trigger_return;
	
	input [`kNumCoins-1:0] i_input_coin,o_return_coin;
	input [`kNumItems-1:0]	i_select_item;			
	input [31:0] item_price [`kNumItems-1:0];
	input [31:0] coin_value [`kNumCoins-1:0];	
	input [`kTotalBits-1:0] current_total;
	input [31:0] wait_time;
	output reg [`kNumItems-1:0] o_available_item,o_output_item;
	output reg  [`kTotalBits-1:0] input_total, output_total, return_total;
	output reg  [`kTotalBits-1:0] current_total_nxt;
	integer i;	

	initial begin
		input_total = 0;
		output_total = 0;
		return_total = 0;
	end

	// Combinational logic for the next states
	always @(*) begin
		
		if (wait_time == 0 || i_trigger_return)
			current_total_nxt = `S4_return;
		else if (i_input_coin > 0)
			current_total_nxt = `S2_coin;
		else if (i_select_item > 0)
			current_total_nxt = `S3_select;
		else 
			current_total_nxt = `S1_wait;

		//maybe we can use this logic also.

		// case (current_total)
		// 	`S0_init:
		// 		current_total_nxt = `S1_wait;
		// 	`S1_wait:
		// 		if(i_input_coin > 0) 
		// 			current_total_nxt = `S2_coin;
		// 		else if(i_select_item > 0) 
		// 			current_total_nxt = `S3_select;
		// 		else
		// 			current_total_nxt = current_total;
		// 	`S2_coin:
		// 		current_total_nxt = `S1_wait;
		// 	`S3_select:
		// 		if (o_available_item > 0) 
		// 			current_total_nxt = `S1_wait;
		// 		else if (input_total > output_total)
		// 			current_total_nxt = `S1_wait;
		// 		else
		// 			current_total_nxt = `S0_init;
		// 	default: current_total_nxt = current_total;
		// endcase
		
	end

	
	// Combinational logic for the outputs
	always @(*) begin
		case (current_total)
			`S0_init: begin
				input_total = 0;
				output_total = 0;
				return_total = 0;
			end
			`S1_wait: begin
				for (i = 0; i < `kNumItems; i = i + 1) begin
					if (input_total - output_total >= item_price[i])
						o_available_item[i] = 1;
					else
						o_available_item[i] = 0;
				end
			end
			`S2_coin: begin
				for (i = 0; i < `kNumCoins; i = i + 1) begin
					if (i_input_coin[i]) begin
						input_total = input_total + coin_value[i] / 2; //for result..
					end
				end
			end
			`S3_select: begin
				for (i = 0; i < `kNumItems; i = i+1) begin
					if (i_select_item[i] && o_available_item[i]) begin
						o_output_item[i] = 1;
						output_total = output_total + item_price[i] / 2; //for result..
					end
					else begin
						o_output_item[i] = 0;
					end
				end
			end
			`S4_return: begin
				for (i = 0; i < `kNumCoins; i = i + 1) begin
					if (o_return_coin[i]) begin
						return_total = return_total + coin_value[i];
					end
				end
			end
		endcase

	end
 
	


endmodule

lab1/vending_machine/check_time_and_coin.v
`include "vending_machine_def.v"

	

module check_time_and_coin(i_input_coin,i_select_item,coin_value,input_total,output_total,return_total,i_trigger_return,clk,reset_n,wait_time,o_return_coin);
	input clk;
	input reset_n;
	input i_trigger_return;
	input [31:0] coin_value [`kNumCoins-1:0];
	input [`kNumCoins-1:0] i_input_coin;
	input [`kNumItems-1:0]	i_select_item;
	input [`kTotalBits-1:0] input_total, output_total, return_total;
	output reg  [`kNumCoins-1:0] o_return_coin;
	output reg [31:0] wait_time;

	reg [`kTotalBits-1:0] relative_money;
	reg [`kTotalBits-1:0] temp;

	integer i;

	// initiate values
	initial begin
		// TODO: initiate values

		o_return_coin = `kNumCoins'b000;
		wait_time = `kWaitTime;

		relative_money = input_total - output_total - return_total;
		temp = 0;
	end


	// update coin return time
	always @(i_input_coin, i_select_item) begin
		// TODO: update coin return time
		
		// wait_time will be initialized to original
	end

	always @(*) begin
		// TODO: o_return_coin
	
	end

	always @(posedge clk ) begin
		relative_money <= input_total - output_total - return_total;

		if (wait_time == 0 || i_trigger_return) begin
			for (i = `kNumCoins - 1; i >= 0; i = i-1) begin
				if (relative_money - temp >= coin_value[i]) begin
					o_return_coin[i] <= 1;
					temp <= temp + coin_value[i];
				end
				else
					o_return_coin[i] <= 0;
			end
		end

		if (!reset_n) begin
			wait_time <= `kWaitTime;
		end
		else if (i_input_coin > 0 || i_select_item > 0)
			wait_time <= `kWaitTime;
		else begin
			if (wait_time > 0)
				wait_time <= wait_time - 1;
			else
				wait_time <= 0;
		end
	end
endmodule

lab1/vending_machine/vending_machine.v
// Title         : vending_machine.v
// Author      : Jae-Eon Jo (Jojaeeon@postech.ac.kr) 
//			     Dongup Kwon (nankdu7@postech.ac.kr) (2015.03.30)
//			     Jaehun Ryu (jaehunryu@postech.ac.kr) (2021.03.07)

`include "vending_machine_def.v"


module vending_machine (
	clk,							// Clock signal
	reset_n,						// Reset signal (active-low)

	i_input_coin,				// coin is inserted.
	i_select_item,				// item is selected.
	i_trigger_return,			// change-return is triggered 

	o_available_item,			// Sign of the item availability
	o_output_item,			// Sign of the item withdrawal
	o_return_coin				// Sign of the coin return
);

	// Ports Declaration
	// Do not modify the module interface
	input clk;
	input reset_n;
	
	input [`kNumCoins-1:0] i_input_coin;
	input [`kNumItems-1:0] i_select_item;
	input i_trigger_return;
		
	output [`kNumItems-1:0] o_available_item;
	output [`kNumItems-1:0] o_output_item;
	output [`kNumCoins-1:0] o_return_coin;


	

	// Do not modify the values.
	wire [31:0] item_price [`kNumItems-1:0];	// Price of each item
	wire [31:0] coin_value [`kNumCoins-1:0];	// Value of each coin
	assign item_price[0] = 400;
	assign item_price[1] = 500;
	assign item_price[2] = 1000;
	assign item_price[3] = 2000;
	assign coin_value[0] = 100;
	assign coin_value[1] = 500;
	assign coin_value[2] = 1000;

	// Internal states. You may add your own net variables.
	wire [`kTotalBits-1:0] current_total;
	
	// Next internal states. You may add your own net variables.
	wire [`kTotalBits-1:0] current_total_nxt;

	
	// Variables. You may add more your own net variables.
	wire [`kTotalBits-1:0] input_total, output_total, return_total;
	wire [31:0] wait_time;


	// This module interface, structure, and given a number of modules are not mandatory but recommended.
	// However, Implementations that use modules are mandatory.
	
  	check_time_and_coin check_time_and_coin_module(.i_input_coin(i_input_coin),
  									.i_select_item(i_select_item),
									.coin_value(coin_value),
									.input_total(input_total),
									.output_total(output_total),
									.return_total(return_total),
									.i_trigger_return(i_trigger_return),
									.clk(clk),
									.reset_n(reset_n),
									.wait_time(wait_time),
									.o_return_coin(o_return_coin));

	calculate_current_state calculate_current_state_module(.i_input_coin(i_input_coin),
										.i_select_item(i_select_item),
										.i_trigger_return(i_trigger_return),
										.item_price(item_price),
										.coin_value(coin_value),
										.current_total(current_total),
										.input_total(input_total),
										.output_total(output_total),
										.return_total(return_total),
										.current_total_nxt(current_total_nxt),
										.wait_time(wait_time),
										.o_return_coin(o_return_coin),
										.o_available_item(o_available_item),
										.o_output_item(o_output_item));
	
  	change_state change_state_module(
						.clk(clk),
						.reset_n(reset_n),
						.current_total_nxt(current_total_nxt),
						.current_total(current_total));


endmodule

lab1/vending_machine/waveform.vcd
$version Generated by VerilatedVcd $end
$timescale 1ps $end
 $scope module TOP $end
  $var wire 1 1 clk $end
  $var wire 1 2 reset_n $end
  $var wire 3 3 i_input_coin [2:0] $end
  $var wire 4 4 i_select_item [3:0] $end
  $var wire 1 5 i_trigger_return $end
  $var wire 4 6 o_available_item [3:0] $end
  $var wire 4 7 o_output_item [3:0] $end
  $var wire 3 8 o_return_coin [2:0] $end
  $scope module vending_machine $end
   $var wire 1 1 clk $end
   $var wire 1 2 reset_n $end
   $var wire 3 3 i_input_coin [2:0] $end
   $var wire 4 4 i_select_item [3:0] $end
   $var wire 1 5 i_trigger_return $end
   $var wire 4 6 o_available_item [3:0] $end
   $var wire 4 7 o_output_item [3:0] $end
   $var wire 3 8 o_return_coin [2:0] $end
   $var wire 32 # item_price[0] [31:0] $end
   $var wire 32 $ item_price[1] [31:0] $end
   $var wire 32 % item_price[2] [31:0] $end
   $var wire 32 & item_price[3] [31:0] $end
   $var wire 32 ' coin_value[0] [31:0] $end
   $var wire 32 ( coin_value[1] [31:0] $end
   $var wire 32 ) coin_value[2] [31:0] $end
   $var wire 32 * current_total [31:0] $end
   $var wire 32 9 current_total_nxt [31:0] $end
   $var wire 32 : input_total [31:0] $end
   $var wire 32 ; output_total [31:0] $end
   $var wire 32 + return_total [31:0] $end
   $var wire 32 , wait_time [31:0] $end
   $scope module calculate_current_state_module $end
    $var wire 1 5 i_trigger_return $end
    $var wire 3 3 i_input_coin [2:0] $end
    $var wire 3 8 o_return_coin [2:0] $end
    $var wire 4 4 i_select_item [3:0] $end
    $var wire 32 # item_price[0] [31:0] $end
    $var wire 32 $ item_price[1] [31:0] $end
    $var wire 32 % item_price[2] [31:0] $end
    $var wire 32 & item_price[3] [31:0] $end
    $var wire 32 ' coin_value[0] [31:0] $end
    $var wire 32 ( coin_value[1] [31:0] $end
    $var wire 32 ) coin_value[2] [31:0] $end
    $var wire 32 * current_total [31:0] $end
    $var wire 32 , wait_time [31:0] $end
    $var wire 4 6 o_available_item [3:0] $end
    $var wire 4 7 o_output_item [3:0] $end
    $var wire 32 : input_total [31:0] $end
    $var wire 32 ; output_total [31:0] $end
    $var wire 32 + return_total [31:0] $end
    $var wire 32 9 current_total_nxt [31:0] $end
    $var wire 32 - i [31:0] $end
   $upscope $end
   $scope module change_state_module $end
    $var wire 1 1 clk $end
    $var wire 1 2 reset_n $end
    $var wire 32 9 current_total_nxt [31:0] $end
    $var wire 32 * current_total [31:0] $end
   $upscope $end
   $scope module check_time_and_coin_module $end
    $var wire 1 1 clk $end
    $var wire 1 2 reset_n $end
    $var wire 1 5 i_trigger_return $end
    $var wire 32 ' coin_value[0] [31:0] $end
    $var wire 32 ( coin_value[1] [31:0] $end
    $var wire 32 ) coin_value[2] [31:0] $end
    $var wire 3 3 i_input_coin [2:0] $end
    $var wire 4 4 i_select_item [3:0] $end
    $var wire 32 : input_total [31:0] $end
    $var wire 32 ; output_total [31:0] $end
    $var wire 32 + return_total [31:0] $end
    $var wire 3 8 o_return_coin [2:0] $end
    $var wire 32 , wait_time [31:0] $end
    $var wire 32 . relative_money [31:0] $end
    $var wire 32 / temp [31:0] $end
    $var wire 32 0 i [31:0] $end
   $upscope $end
  $upscope $end
 $upscope $end
$enddefinitions $end


#0
b00000000000000000000000110010000 #
b00000000000000000000000111110100 $
b00000000000000000000001111101000 %
b00000000000000000000011111010000 &
b00000000000000000000000001100100 '
b00000000000000000000000111110100 (
b00000000000000000000001111101000 )
b01110011010110000001011000110101 *
b00000000000000000000000000000000 +
b00000000000000000000000000001010 ,
b01010110110100010000100001011100 -
b10010110110011111110000110111111 .
b00000000000000000000000000000000 /
b11101001110011110000010010110010 0
11
12
b000 3
b0000 4
05
b1100 6
b0110 7
b000 8
b00000000000000000000000000000001 9
b00000000000000000000000000000000 :
b00000000000000000000000000000000 ;
#1
01
#2
b00000000000000000000000000000000 *
b00000000000000000000000000000000 .
11
02
#3
01
#4
11
#5
01
#6
b00000000000000000000000000000001 *
b00000000000000000000000000001001 ,
b00000000000000000000000000000100 -
11
12
b0000 6
#7
01
#8
b00000000000000000000000000000010 *
b00000000000000000000000000001010 ,
b00000000000000000000000000000011 -
11
b001 3
b00000000000000000000000000000010 9
b00000000000000000000000000110010 :
#9
01
b00000000000000000000000001100100 :
#10
b00000000000000000000000000000001 *
b00000000000000000000000000001001 ,
b00000000000000000000000000000100 -
b00000000000000000000000001100100 .
11
b000 3
b00000000000000000000000000000001 9
#11
01
#12
b00000000000000000000000000000010 *
b00000000000000000000000000001010 ,
b00000000000000000000000000000011 -
11
b001 3
b00000000000000000000000000000010 9
b00000000000000000000000010010110 :
#13
01
b00000000000000000000000011001000 :
#14
b00000000000000000000000000000001 *
b00000000000000000000000000001001 ,
b00000000000000000000000000000100 -
b00000000000000000000000011001000 .
11
b000 3
b00000000000000000000000000000001 9
#15
01
#16
b00000000000000000000000000000010 *
b00000000000000000000000000001010 ,
b00000000000000000000000000000011 -
11
b001 3
b00000000000000000000000000000010 9
b00000000000000000000000011111010 :
#17
01
b00000000000000000000000100101100 :
#18
b00000000000000000000000000000001 *
b00000000000000000000000000001001 ,
b00000000000000000000000000000100 -
b00000000000000000000000100101100 .
11
b000 3
b00000000000000000000000000000001 9
#19
01
#20
b00000000000000000000000000000010 *
b00000000000000000000000000001010 ,
b00000000000000000000000000000011 -
11
b001 3
b00000000000000000000000000000010 9
b00000000000000000000000101011110 :
#21
01
b00000000000000000000000110010000 :
#22
b00000000000000000000000000000001 *
b00000000000000000000000000001001 ,
b00000000000000000000000000000100 -
b00000000000000000000000110010000 .
11
b000 3
b0001 6
b00000000000000000000000000000001 9
#23
01
#24
b00000000000000000000000000000010 *
b00000000000000000000000000001010 ,
b00000000000000000000000000000011 -
11
b001 3
b00000000000000000000000000000010 9
b00000000000000000000000111000010 :
#25
01
b00000000000000000000000111110100 :
#26
b00000000000000000000000000000001 *
b00000000000000000000000000001001 ,
b00000000000000000000000000000100 -
b00000000000000000000000111110100 .
11
b000 3
b0011 6
b00000000000000000000000000000001 9
#27
01
#28
b00000000000000000000000000001000 ,
11
#29
01
#30
b00000000000000000000000000000000 *
b00000000000000000000000000001010 ,
11
02
b00000000000000000000000000000000 :
#31
01
#32
b00000000000000000000000000000000 .
11
#33
01
#34
b00000000000000000000000000000001 *
b00000000000000000000000000001001 ,
11
12
b0000 6
#35
01
#36
b00000000000000000000000000000010 *
b00000000000000000000000000001010 ,
b00000000000000000000000000000011 -
11
b010 3
b00000000000000000000000000000010 9
b00000000000000000000000011111010 :
#37
01
b00000000000000000000000111110100 :
#38
b00000000000000000000000000000001 *
b00000000000000000000000000001001 ,
b00000000000000000000000000000100 -
b00000000000000000000000111110100 .
11
b000 3
b0011 6
b00000000000000000000000000000001 9
#39
01
#40
b00000000000000000000000000000010 *
b00000000000000000000000000001010 ,
b00000000000000000000000000000011 -
11
b010 3
b00000000000000000000000000000010 9
b00000000000000000000001011101110 :
#41
01
b00000000000000000000001111101000 :
#42
b00000000000000000000000000000001 *
b00000000000000000000000000001001 ,
b00000000000000000000000000000100 -
b00000000000000000000001111101000 .
11
b000 3
b0111 6
b00000000000000000000000000000001 9
#43
01
#44
b00000000000000000000000000000010 *
b00000000000000000000000000001010 ,
b00000000000000000000000000000011 -
11
b010 3
b00000000000000000000000000000010 9
b00000000000000000000010011100010 :
#45
01
b00000000000000000000010111011100 :
#46
b00000000000000000000000000000001 *
b00000000000000000000000000001001 ,
b00000000000000000000000000000100 -
b00000000000000000000010111011100 .
11
b000 3
b00000000000000000000000000000001 9
#47
01
#48
b00000000000000000000000000000010 *
b00000000000000000000000000001010 ,
b00000000000000000000000000000011 -
11
b010 3
b00000000000000000000000000000010 9
b00000000000000000000011011010110 :
#49
01
b00000000000000000000011111010000 :
#50
b00000000000000000000000000000001 *
b00000000000000000000000000001001 ,
b00000000000000000000000000000100 -
b00000000000000000000011111010000 .
11
b000 3
b1111 6
b00000000000000000000000000000001 9
#51
01
#52
b00000000000000000000000000001000 ,
11
#53
01
#54
b00000000000000000000000000000000 *
b00000000000000000000000000001010 ,
11
02
b00000000000000000000000000000000 :
#55
01
#56
b00000000000000000000000000000000 .
11
#57
01
#58
b00000000000000000000000000000001 *
b00000000000000000000000000001001 ,
11
12
b0000 6
#59
01
#60
b00000000000000000000000000000010 *
b00000000000000000000000000001010 ,
b00000000000000000000000000000011 -
11
b100 3
b00000000000000000000000000000010 9
b00000000000000000000000111110100 :
#61
01
b00000000000000000000001111101000 :
#62
b00000000000000000000000000000001 *
b00000000000000000000000000001001 ,
b00000000000000000000000000000100 -
b00000000000000000000001111101000 .
11
b000 3
b0111 6
b00000000000000000000000000000001 9
#63
01
#64
b00000000000000000000000000000010 *
b00000000000000000000000000001010 ,
b00000000000000000000000000000011 -
11
b100 3
b00000000000000000000000000000010 9
b00000000000000000000010111011100 :
#65
01
b00000000000000000000011111010000 :
#66
b00000000000000000000000000000001 *
b00000000000000000000000000001001 ,
b00000000000000000000000000000100 -
b00000000000000000000011111010000 .
11
b000 3
b1111 6
b00000000000000000000000000000001 9
#67
01
#68
b00000000000000000000000000001000 ,
11
#69
01
#70
b00000000000000000000000000000000 *
b00000000000000000000000000001010 ,
11
02
b00000000000000000000000000000000 :
#71
01
#72
b00000000000000000000000000000000 .
11
#73
01
#74
b00000000000000000000000000000001 *
b00000000000000000000000000001001 ,
11
12
b0000 6
#75
01
#76
b00000000000000000000000000000010 *
b00000000000000000000000000001010 ,
b00000000000000000000000000000011 -
11
b100 3
b00000000000000000000000000000010 9
b00000000000000000000000111110100 :
#77
01
b00000000000000000000001111101000 :
#78
b00000000000000000000000000000001 *
b00000000000000000000000000001001 ,
b00000000000000000000000000000100 -
b00000000000000000000001111101000 .
11
b000 3
b0111 6
b00000000000000000000000000000001 9
#79
01
#80
b00000000000000000000000000000010 *
b00000000000000000000000000001010 ,
b00000000000000000000000000000011 -
11
b100 3
b00000000000000000000000000000010 9
b00000000000000000000010111011100 :
#81
01
b00000000000000000000011111010000 :
#82
b00000000000000000000000000000001 *
b00000000000000000000000000001001 ,
b00000000000000000000000000000100 -
b00000000000000000000011111010000 .
11
b000 3
b1111 6
b00000000000000000000000000000001 9
#83
01
#84
b00000000000000000000000000000010 *
b00000000000000000000000000001010 ,
b00000000000000000000000000000011 -
11
b100 3
b00000000000000000000000000000010 9
b00000000000000000000100111000100 :
#85
01
b00000000000000000000101110111000 :
#86
b00000000000000000000000000000001 *
b00000000000000000000000000001001 ,
b00000000000000000000000000000100 -
b00000000000000000000101110111000 .
11
b000 3
b00000000000000000000000000000001 9
#87
01
#88
b00000000000000000000000000000011 *
b00000000000000000000000000001010 ,
11
b0001 4
b0001 7
b00000000000000000000000000000011 9
b00000000000000000000000011001000 ;
#89
01
b00000000000000000000000110010000 ;
#90
b00000000000000000000000000000001 *
b00000000000000000000000000001001 ,
b00000000000000000000101000101000 .
11
b0000 4
b0000 7
b00000000000000000000000000000001 9
#91
01
#92
b00000000000000000000000000001000 ,
11
#93
01
#94
b00000000000000000000000000000111 ,
11
#95
01
#96
b00000000000000000000000000000011 *
b00000000000000000000000000001010 ,
11
b0001 4
b0001 7
b00000000000000000000000000000011 9
b00000000000000000000001001011000 ;
#97
01
b00000000000000000000001100100000 ;
#98
b00000000000000000000000000000001 *
b00000000000000000000000000001001 ,
b00000000000000000000100010011000 .
11
b0000 4
b0000 7
b00000000000000000000000000000001 9
#99
01
#100
b00000000000000000000000000001000 ,
11
#101
01
#102
b00000000000000000000000000000111 ,
11
#103
01
#104
b00000000000000000000000000000011 *
b00000000000000000000000000001010 ,
11
b0001 4
b0001 7
b00000000000000000000000000000011 9
b00000000000000000000001111101000 ;
#105
01
b00000000000000000000010010110000 ;
#106
b00000000000000000000000000000001 *
b00000000000000000000000000001001 ,
b00000000000000000000011100001000 .
11
b0000 4
b0111 6
b0000 7
b00000000000000000000000000000001 9
#107
01
#108
b00000000000000000000000000001000 ,
11
#109
01
#110
b00000000000000000000000000000111 ,
11
#111
01
#112
b00000000000000000000000000000011 *
b00000000000000000000000000001010 ,
11
b0001 4
b0001 7
b00000000000000000000000000000011 9
b00000000000000000000010101111000 ;
#113
01
b00000000000000000000011001000000 ;
#114
b00000000000000000000000000000001 *
b00000000000000000000000000001001 ,
b00000000000000000000010101111000 .
11
b0000 4
b0000 7
b00000000000000000000000000000001 9
#115
01
#116
b00000000000000000000000000001000 ,
11
#117
01
#118
b00000000000000000000000000000111 ,
11
#119
01
#120
b00000000000000000000000000000011 *
b00000000000000000000000000001010 ,
11
b0001 4
b0001 7
b00000000000000000000000000000011 9
b00000000000000000000011100001000 ;
#121
01
b00000000000000000000011111010000 ;
#122
b00000000000000000000000000000001 *
b00000000000000000000000000001001 ,
b00000000000000000000001111101000 .
11
b0000 4
b0000 7
b00000000000000000000000000000001 9
#123
01
#124
b00000000000000000000000000001000 ,
11
#125
01
#126
b00000000000000000000000000000111 ,
11
#127
01
#128
b00000000000000000000000000000011 *
b00000000000000000000000000001010 ,
11
b0001 4
b0001 7
b00000000000000000000000000000011 9
b00000000000000000000100010011000 ;
#129
01
b00000000000000000000100101100000 ;
#130
b00000000000000000000000000000001 *
b00000000000000000000000000001001 ,
b00000000000000000000001001011000 .
11
b0000 4
b0011 6
b0000 7
b00000000000000000000000000000001 9
#131
01
#132
b00000000000000000000000000001000 ,
11
#133
01
#134
b00000000000000000000000000000111 ,
11
#135
01
#136
b00000000000000000000000000000011 *
b00000000000000000000000000001010 ,
11
b0001 4
b0001 7
b00000000000000000000000000000011 9
b00000000000000000000101000101000 ;
#137
01
b00000000000000000000101011110000 ;
#138
b00000000000000000000000000000001 *
b00000000000000000000000000001001 ,
b00000000000000000000000011001000 .
11
b0000 4
b0000 6
b0000 7
b00000000000000000000000000000001 9
#139
01
#140
b00000000000000000000000000001000 ,
11
#141
01
#142
b00000000000000000000000000000111 ,
11
#143
01
#144
b00000000000000000000000000000110 ,
11
#145
01
#146
b00000000000000000000000000000101 ,
11
#147
01
#148
b00000000000000000000000000000010 *
b00000000000000000000000000001010 ,
b00000000000000000000000000000011 -
11
b100 3
b00000000000000000000000000000010 9
b00000000000000000000110110101100 :
#149
01
b00000000000000000000111110100000 :
#150
b00000000000000000000000000000001 *
b00000000000000000000000000001001 ,
b00000000000000000000000000000100 -
b00000000000000000000010010110000 .
11
b000 3
b0111 6
b00000000000000000000000000000001 9
#151
01
#152
b00000000000000000000000000000010 *
b00000000000000000000000000001010 ,
b00000000000000000000000000000011 -
11
b100 3
b00000000000000000000000000000010 9
b00000000000000000001000110010100 :
#153
01
b00000000000000000001001110001000 :
#154
b00000000000000000000000000000001 *
b00000000000000000000000000001001 ,
b00000000000000000000000000000100 -
b00000000000000000000100010011000 .
11
b000 3
b1111 6
b00000000000000000000000000000001 9
#155
01
#156
b00000000000000000000000000000010 *
b00000000000000000000000000001010 ,
b00000000000000000000000000000011 -
11
b100 3
b00000000000000000000000000000010 9
b00000000000000000001010101111100 :
#157
01
b00000000000000000001011101110000 :
#158
b00000000000000000000000000000001 *
b00000000000000000000000000001001 ,
b00000000000000000000000000000100 -
b00000000000000000000110010000000 .
11
b000 3
b00000000000000000000000000000001 9
#159
01
#160
b00000000000000000000000000000011 *
b00000000000000000000000000001010 ,
11
b0010 4
b0010 7
b00000000000000000000000000000011 9
b00000000000000000000101111101010 ;
#161
01
b00000000000000000000110011100100 ;
#162
b00000000000000000000000000000001 *
b00000000000000000000000000001001 ,
b00000000000000000000101010001100 .
11
b0000 4
b0000 7
b00000000000000000000000000000001 9
#163
01
#164
b00000000000000000000000000001000 ,
11
#165
01
#166
b00000000000000000000000000000111 ,
11
#167
01
#168
b00000000000000000000000000000011 *
b00000000000000000000000000001010 ,
11
b0010 4
b0010 7
b00000000000000000000000000000011 9
b00000000000000000000110111011110 ;
#169
01
b00000000000000000000111011011000 ;
#170
b00000000000000000000000000000001 *
b00000000000000000000000000001001 ,
b00000000000000000000100010011000 .
11
b0000 4
b0000 7
b00000000000000000000000000000001 9
#171
01
#172
b00000000000000000000000000001000 ,
11
#173
01
#174
b00000000000000000000000000000111 ,
11
#175
01
#176
b00000000000000000000000000000011 *
b00000000000000000000000000001010 ,
11
b0010 4
b0010 7
b00000000000000000000000000000011 9
b00000000000000000000111111010010 ;
#177
01
b00000000000000000001000011001100 ;
#178
b00000000000000000000000000000001 *
b00000000000000000000000000001001 ,
b00000000000000000000011010100100 .
11
b0000 4
b0111 6
b0000 7
b00000000000000000000000000000001 9
#179
01
#180
b00000000000000000000000000001000 ,
11
#181
01
#182
b00000000000000000000000000000111 ,
11
#183
01
#184
b00000000000000000000000000000011 *
b00000000000000000000000000001010 ,
11
b0010 4
b0010 7
b00000000000000000000000000000011 9
b00000000000000000001000111000110 ;
#185
01
b00000000000000000001001011000000 ;
#186
b00000000000000000000000000000001 *
b00000000000000000000000000001001 ,
b00000000000000000000010010110000 .
11
b0000 4
b0000 7
b00000000000000000000000000000001 9
#187
01
#188
b00000000000000000000000000001000 ,
11
#189
01
#190
b00000000000000000000000000000111 ,
11
#191
01
#192
b00000000000000000000000000000011 *
b00000000000000000000000000001010 ,
11
b0010 4
b0010 7
b00000000000000000000000000000011 9
b00000000000000000001001110111010 ;
#193
01
b00000000000000000001010010110100 ;
#194
b00000000000000000000000000000001 *
b00000000000000000000000000001001 ,
b00000000000000000000001010111100 .
11
b0000 4
b0011 6
b0000 7
b00000000000000000000000000000001 9
#195
01
#196
b00000000000000000000000000001000 ,
11
#197
01
#198
b00000000000000000000000000000111 ,
11
#199
01
#200
b00000000000000000000000000000011 *
b00000000000000000000000000001010 ,
11
b0010 4
b0010 7
b00000000000000000000000000000011 9
b00000000000000000001010110101110 ;
#201
01
b00000000000000000001011010101000 ;
#202
b00000000000000000000000000000001 *
b00000000000000000000000000001001 ,
b00000000000000000000000011001000 .
11
b0000 4
b0000 6
b0000 7
b00000000000000000000000000000001 9
#203
01
#204
b00000000000000000000000000001000 ,
11
#205
01
#206
b00000000000000000000000000000111 ,
11
#207
01
#208
b00000000000000000000000000000010 *
b00000000000000000000000000001010 ,
b00000000000000000000000000000011 -
11
b001 3
b00000000000000000000000000000010 9
b00000000000000000001011110100010 :
#209
01
b00000000000000000001011111010100 :
#210
b00000000000000000000000000000001 *
b00000000000000000000000000001001 ,
b00000000000000000000000000000100 -
b00000000000000000000000100101100 .
11
b000 3
b00000000000000000000000000000001 9
#211
01
#212
b00000000000000000000000000000010 *
b00000000000000000000000000001010 ,
b00000000000000000000000000000011 -
11
b001 3
b00000000000000000000000000000010 9
b00000000000000000001100000000110 :
#213
01
b00000000000000000001100000111000 :
#214
b00000000000000000000000000000001 *
b00000000000000000000000000001001 ,
b00000000000000000000000000000100 -
b00000000000000000000000110010000 .
11
b000 3
b0001 6
b00000000000000000000000000000001 9
#215
01
#216
b00000000000000000000000000000010 *
b00000000000000000000000000001010 ,
b00000000000000000000000000000011 -
11
b100 3
b00000000000000000000000000000010 9
b00000000000000000001101000101100 :
#217
01
b00000000000000000001110000100000 :
#218
b00000000000000000000000000000001 *
b00000000000000000000000000001001 ,
b00000000000000000000000000000100 -
b00000000000000000000010101111000 .
11
b000 3
b0111 6
b00000000000000000000000000000001 9
#219
01
#220
b00000000000000000000000000000010 *
b00000000000000000000000000001010 ,
b00000000000000000000000000000011 -
11
b100 3
b00000000000000000000000000000010 9
b00000000000000000001111000010100 :
#221
01
b00000000000000000010000000001000 :
#222
b00000000000000000000000000000001 *
b00000000000000000000000000001001 ,
b00000000000000000000000000000100 -
b00000000000000000000100101100000 .
11
b000 3
b1111 6
b00000000000000000000000000000001 9
#223
01
#224
b00000000000000000000000000000010 *
b00000000000000000000000000001010 ,
b00000000000000000000000000000011 -
11
b100 3
b00000000000000000000000000000010 9
b00000000000000000010000111111100 :
#225
01
b00000000000000000010001111110000 :
#226
b00000000000000000000000000000001 *
b00000000000000000000000000001001 ,
b00000000000000000000000000000100 -
b00000000000000000000110101001000 .
11
b000 3
b00000000000000000000000000000001 9
#227
01
#228
b00000000000000000000000000000011 *
b00000000000000000000000000001010 ,
11
b0100 4
b0100 7
b00000000000000000000000000000011 9
b00000000000000000001100010011100 ;
#229
01
b00000000000000000001101010010000 ;
#230
b00000000000000000000000000000001 *
b00000000000000000000000000001001 ,
b00000000000000000000100101100000 .
11
b0000 4
b0000 7
b00000000000000000000000000000001 9
#231
01
#232
b00000000000000000000000000001000 ,
11
#233
01
#234
b00000000000000000000000000000111 ,
11
#235
01
#236
b00000000000000000000000000000011 *
b00000000000000000000000000001010 ,
11
b0100 4
b0100 7
b00000000000000000000000000000011 9
b00000000000000000001110010000100 ;
#237
01
b00000000000000000001111001111000 ;
#238
b00000000000000000000000000000001 *
b00000000000000000000000000001001 ,
b00000000000000000000010101111000 .
11
b0000 4
b0111 6
b0000 7
b00000000000000000000000000000001 9
#239
01
#240
b00000000000000000000000000001000 ,
11
#241
01
#242
b00000000000000000000000000000111 ,
11
#243
01
#244
b00000000000000000000000000000011 *
b00000000000000000000000000001010 ,
11
b0100 4
b0100 7
b00000000000000000000000000000011 9
b00000000000000000010000001101100 ;
#245
01
b00000000000000000010001001100000 ;
#246
b00000000000000000000000000000001 *
b00000000000000000000000000001001 ,
b00000000000000000000000110010000 .
11
b0000 4
b0001 6
b0000 7
b00000000000000000000000000000001 9
#247
01
#248
b00000000000000000000000000001000 ,
11
#249
01
#250
b00000000000000000000000000000111 ,
11
#251
01
#252
b00000000000000000000000000000010 *
b00000000000000000000000000001010 ,
b00000000000000000000000000000011 -
11
b100 3
b00000000000000000000000000000010 9
b00000000000000000010010111100100 :
#253
01
b00000000000000000010011111011000 :
#254
b00000000000000000000000000000001 *
b00000000000000000000000000001001 ,
b00000000000000000000000000000100 -
b00000000000000000000010101111000 .
11
b000 3
b0111 6
b00000000000000000000000000000001 9
#255
01
