lab1/vending_machine/vending_machine_def.v
// Title         : vending_machine_def.v
// Author      : Jae-Eon Jo (Jojaeeon@postech.ac.kr) 
//					Dongup Kwon (nankdu7@postech.ac.kr)

// Macro constants (prefix k & CamelCase)
`define kTotalBits 32
  
`define kItemBits 8
`define kNumItems 4

`define kCoinBits 8
`define kNumCoins 3

`define kWaitTime 10

`define S0_init 32'h00
`define S1_wait 32'h01
`define S2_select 32'h02
`define S3_return 32'h03

lab1/vending_machine/change_state.v
`include "vending_machine_def.v"


module change_state(clk,reset_n,current_total_nxt,current_total);

	input clk;
	input reset_n;
	input [`kTotalBits-1:0] current_total_nxt;
	output reg [`kTotalBits-1:0] current_total;
	
	// Sequential circuit to reset or update the states
	always @(posedge clk ) begin
		if (!reset_n) begin
			// TODO: reset all states.

			//reset current_total(0)
			current_total <= `kTotalBits'b0;
		end
		else begin
			// TODO: update all states.
			
			// update current_total to current_total_nxt
			current_total <= current_total_nxt;
		end
	end
endmodule

lab1/vending_machine/calculate_current_state.v

`include "vending_machine_def.v"
	

module calculate_current_state(i_input_coin,i_select_item,item_price,coin_value,current_total,
input_total, output_total, return_total,current_total_nxt,wait_time,o_return_coin,o_available_item,o_output_item);


	
	input [`kNumCoins-1:0] i_input_coin,o_return_coin;
	input [`kNumItems-1:0]	i_select_item;			
	input [31:0] item_price [`kNumItems-1:0];
	input [31:0] coin_value [`kNumCoins-1:0];	
	input [`kTotalBits-1:0] current_total;
	input [31:0] wait_time;
	output reg [`kNumItems-1:0] o_available_item,o_output_item;
	output reg  [`kTotalBits-1:0] input_total, output_total, return_total;
	output reg  [`kTotalBits-1:0] current_total_nxt;
	integer i;	

	initial begin
		input_total = 0;
		output_total = 0;
		return_total = input_total - output_total;
	end

	// Combinational logic for the next states
	always @(*) begin
		// TODO: current_total_nxt
		// You don't have to worry about concurrent activations in each input vector (or array).
		// Calculate the next current_total state.
		
		case (current_total)
			`S0_init:
				if(i_input_coin > 0) 
					current_total_nxt = `S1_wait;
			`S1_wait:
				if(i_select_item > 0) 
					current_total_nxt = `S2_select;
				else if(wait_time == 0) 
					current_total_nxt = `S3_return;
				// else
				// 	current_total_nxt = `S1_wait;
			`S2_select:
				if (o_available_item > 0) 
					current_total_nxt = `S1_wait;
				else if (wait_time == 0)
					current_total_nxt = `S3_return;
				else if (input_total > output_total)
					current_total_nxt = `S1_wait;
				else
					current_total_nxt = `S0_init;
			`S3_return: begin
				if (o_return_coin == 0)
					current_total_nxt = `S0_init;
				else
					current_total_nxt = `S3_return;
			end
			default: begin current_total_nxt = `S0_init; end
		endcase
		
	end

	
	
	// Combinational logic for the outputs
	always @(*) begin
		// TODO: o_available_item
		// TODO: o_output_item

		case (current_total)
			`S0_init: begin
				input_total = 0;
				output_total = 0;
				return_total = 0;
				o_available_item = 0;
			end
			`S1_wait: begin
				for (i = 0; i < `kNumCoins; i = i+1) begin
					if (i_input_coin[i])
						input_total = input_total + coin_value[i];
				end
				for (i = 0; i < `kNumItems; i = i+1) begin
					if (input_total - output_total >= item_price[i])
						o_available_item[i] = 1;
					else
						o_available_item[i] = 0;
				end
			end
			`S2_select: begin
				for (i = 0; i < `kNumItems; i = i+1) begin
					if (i_select_item[i] && o_available_item[i]) begin
						o_output_item[i] = 1;
						output_total = output_total + item_price[i];
					end
				end
			end
			`S3_return: return_total = input_total - output_total;
			default: return_total = input_total - output_total;
		endcase

	end
 
	


endmodule

lab1/vending_machine/check_time_and_coin.v
`include "vending_machine_def.v"

	

module check_time_and_coin(i_input_coin,i_select_item,clk,reset_n,wait_time,o_return_coin);
	input clk;
	input reset_n;
	input [`kNumCoins-1:0] i_input_coin;
	input [`kNumItems-1:0]	i_select_item;
	output reg  [`kNumCoins-1:0] o_return_coin;
	output reg [31:0] wait_time;

	// initiate values
	initial begin
		// TODO: initiate values

		// initiate o_return_coin(0000), wait_time(100) //
		o_return_coin = `kNumCoins'b0;
		wait_time = `kWaitTime;
	end


	// update coin return time
	always @(i_input_coin, i_select_item) begin
		// TODO: update coin return time

		// wait_time will be initialized to original
	end

	always @(*) begin
		// TODO: o_return_coin

		// NOT SURE if select item and avail, subtract price of item from the o_return_coin
	end

	always @(posedge clk ) begin
		if (!reset_n) begin
		// TODO: reset all states.

		// reset all output value //
		o_return_coin <= `kNumCoins'b001; //여기 나중에 바꿔야함!!//
		wait_time <= `kWaitTime;
		end
		else if (i_input_coin > 0 || i_select_item > 0)
			wait_time <= `kWaitTime;
		else begin
		// TODO: update all states.

		// update output value - wait_time decresing //
		wait_time <= wait_time - 1;
		end
	end
endmodule

lab1/vending_machine/vending_machine.v
// Title         : vending_machine.v
// Author      : Jae-Eon Jo (Jojaeeon@postech.ac.kr) 
//			     Dongup Kwon (nankdu7@postech.ac.kr) (2015.03.30)
//			     Jaehun Ryu (jaehunryu@postech.ac.kr) (2021.03.07)

`include "vending_machine_def.v"


module vending_machine (
	clk,							// Clock signal
	reset_n,						// Reset signal (active-low)

	i_input_coin,				// coin is inserted.
	i_select_item,				// item is selected.
	i_trigger_return,			// change-return is triggered 

	o_available_item,			// Sign of the item availability
	o_output_item,			// Sign of the item withdrawal
	o_return_coin				// Sign of the coin return
);

	// Ports Declaration
	// Do not modify the module interface
	input clk;
	input reset_n;
	
	input [`kNumCoins-1:0] i_input_coin;
	input [`kNumItems-1:0] i_select_item;
	input i_trigger_return;
		
	output [`kNumItems-1:0] o_available_item;
	output [`kNumItems-1:0] o_output_item;
	output [`kNumCoins-1:0] o_return_coin;


	

	// Do not modify the values.
	wire [31:0] item_price [`kNumItems-1:0];	// Price of each item
	wire [31:0] coin_value [`kNumCoins-1:0];	// Value of each coin
	assign item_price[0] = 400;
	assign item_price[1] = 500;
	assign item_price[2] = 1000;
	assign item_price[3] = 2000;
	assign coin_value[0] = 100;
	assign coin_value[1] = 500;
	assign coin_value[2] = 1000;

	// Internal states. You may add your own net variables.
	wire [`kTotalBits-1:0] current_total;
	
	// Next internal states. You may add your own net variables.
	wire [`kTotalBits-1:0] current_total_nxt;

	
	// Variables. You may add more your own net variables.
	wire [`kTotalBits-1:0] input_total, output_total, return_total;
	wire [31:0] wait_time;


	// This module interface, structure, and given a number of modules are not mandatory but recommended.
	// However, Implementations that use modules are mandatory.
	wire ret;
	wire [31:0] rett;
	assign ret = i_trigger_return;
	assign rett = input_total;
	assign rett = output_total;
	assign rett = return_total;
	assign rett = rett;
	assign ret = ret;
	
  	check_time_and_coin check_time_and_coin_module(.i_input_coin(i_input_coin),
  									.i_select_item(i_select_item),
									.clk(clk),
									.reset_n(reset_n),
									.wait_time(wait_time),
									.o_return_coin(o_return_coin));

	calculate_current_state calculate_current_state_module(.i_input_coin(i_input_coin),
										.i_select_item(i_select_item),
										.item_price(item_price),
										.coin_value(coin_value),
										.current_total(current_total),
										.input_total(input_total),
										.output_total(output_total),
										.return_total(return_total),
										.current_total_nxt(current_total_nxt),
										.wait_time(wait_time),
										.o_return_coin(o_return_coin),
										.o_available_item(o_available_item),
										.o_output_item(o_output_item));
	
  	change_state change_state_module(
						.clk(clk),
						.reset_n(reset_n),
						.current_total_nxt(current_total_nxt),
						.current_total(current_total));


endmodule

lab1/vending_machine/waveform.vcd
$version Generated by VerilatedVcd $end
$timescale 1ps $end
 $scope module TOP $end
  $var wire 1 - clk $end
  $var wire 1 . reset_n $end
  $var wire 3 / i_input_coin [2:0] $end
  $var wire 4 0 i_select_item [3:0] $end
  $var wire 1 1 i_trigger_return $end
  $var wire 4 2 o_available_item [3:0] $end
  $var wire 4 3 o_output_item [3:0] $end
  $var wire 3 4 o_return_coin [2:0] $end
  $scope module vending_machine $end
   $var wire 1 - clk $end
   $var wire 1 . reset_n $end
   $var wire 3 / i_input_coin [2:0] $end
   $var wire 4 0 i_select_item [3:0] $end
   $var wire 1 1 i_trigger_return $end
   $var wire 4 2 o_available_item [3:0] $end
   $var wire 4 3 o_output_item [3:0] $end
   $var wire 3 4 o_return_coin [2:0] $end
   $var wire 32 # item_price[0] [31:0] $end
   $var wire 32 $ item_price[1] [31:0] $end
   $var wire 32 % item_price[2] [31:0] $end
   $var wire 32 & item_price[3] [31:0] $end
   $var wire 32 ' coin_value[0] [31:0] $end
   $var wire 32 ( coin_value[1] [31:0] $end
   $var wire 32 ) coin_value[2] [31:0] $end
   $var wire 32 * current_total [31:0] $end
   $var wire 32 5 current_total_nxt [31:0] $end
   $var wire 32 6 input_total [31:0] $end
   $var wire 32 7 output_total [31:0] $end
   $var wire 32 8 return_total [31:0] $end
   $var wire 32 + wait_time [31:0] $end
   $var wire 1 1 ret $end
   $var wire 32 6 rett [31:0] $end
   $scope module calculate_current_state_module $end
    $var wire 3 / i_input_coin [2:0] $end
    $var wire 3 4 o_return_coin [2:0] $end
    $var wire 4 0 i_select_item [3:0] $end
    $var wire 32 # item_price[0] [31:0] $end
    $var wire 32 $ item_price[1] [31:0] $end
    $var wire 32 % item_price[2] [31:0] $end
    $var wire 32 & item_price[3] [31:0] $end
    $var wire 32 ' coin_value[0] [31:0] $end
    $var wire 32 ( coin_value[1] [31:0] $end
    $var wire 32 ) coin_value[2] [31:0] $end
    $var wire 32 * current_total [31:0] $end
    $var wire 32 + wait_time [31:0] $end
    $var wire 4 2 o_available_item [3:0] $end
    $var wire 4 3 o_output_item [3:0] $end
    $var wire 32 6 input_total [31:0] $end
    $var wire 32 7 output_total [31:0] $end
    $var wire 32 8 return_total [31:0] $end
    $var wire 32 5 current_total_nxt [31:0] $end
    $var wire 32 , i [31:0] $end
   $upscope $end
   $scope module change_state_module $end
    $var wire 1 - clk $end
    $var wire 1 . reset_n $end
    $var wire 32 5 current_total_nxt [31:0] $end
    $var wire 32 * current_total [31:0] $end
   $upscope $end
   $scope module check_time_and_coin_module $end
    $var wire 1 - clk $end
    $var wire 1 . reset_n $end
    $var wire 3 / i_input_coin [2:0] $end
    $var wire 4 0 i_select_item [3:0] $end
    $var wire 3 4 o_return_coin [2:0] $end
    $var wire 32 + wait_time [31:0] $end
   $upscope $end
  $upscope $end
 $upscope $end
$enddefinitions $end


#0
b00000000000000000000000110010000 #
b00000000000000000000000111110100 $
b00000000000000000000001111101000 %
b00000000000000000000011111010000 &
b00000000000000000000000001100100 '
b00000000000000000000000111110100 (
b00000000000000000000001111101000 )
b01110011010110000001011000110101 *
b00000000000000000000000000001010 +
b11000110011011010100110101011000 ,
1-
1.
b000 /
b0000 0
01
b1100 2
b0110 3
b000 4
b00000000000000000000000000000000 5
b00000000000000000000000000000000 6
b00000000000000000000000000000000 7
b00000000000000000000000000000000 8
#1
0-
#2
b00000000000000000000000000000000 *
1-
0.
b0000 2
b001 4
#3
0-
#4
1-
#5
0-
#6
b00000000000000000000000000001001 +
1-
1.
#7
0-
#8
b00000000000000000000000000000001 *
b00000000000000000000000000001010 +
b00000000000000000000000000000100 ,
1-
b001 /
b00000000000000000000000000000001 5
b00000000000000000000000001100100 6
#9
0-
b00000000000000000000000011001000 6
#10
b00000000000000000000000000001001 +
1-
b000 /
#11
0-
#12
b00000000000000000000000000001010 +
1-
b001 /
b0001 2
b00000000000000000000000110010000 6
#13
0-
b0011 2
b00000000000000000000000111110100 6
#14
b00000000000000000000000000001001 +
1-
b000 /
#15
0-
#16
b00000000000000000000000000001010 +
1-
b001 /
b00000000000000000000001010111100 6
#17
0-
b00000000000000000000001100100000 6
#18
b00000000000000000000000000001001 +
1-
b000 /
#19
0-
#20
b00000000000000000000000000001010 +
1-
b001 /
b0111 2
b00000000000000000000001111101000 6
#21
0-
b00000000000000000000010001001100 6
#22
b00000000000000000000000000001001 +
1-
b000 /
#23
0-
#24
b00000000000000000000000000001010 +
1-
b001 /
b00000000000000000000010100010100 6
#25
0-
b00000000000000000000010101111000 6
#26
b00000000000000000000000000001001 +
1-
b000 /
#27
0-
#28
b00000000000000000000000000001000 +
1-
#29
0-
#30
b00000000000000000000000000000000 *
b00000000000000000000000000001010 +
1-
0.
b0000 2
b00000000000000000000000000000000 6
#31
0-
#32
1-
#33
0-
#34
b00000000000000000000000000000001 *
b00000000000000000000000000001001 +
1-
1.
#35
0-
#36
b00000000000000000000000000001010 +
1-
b010 /
b0111 2
b00000000000000000000001111101000 6
#37
0-
b00000000000000000000010111011100 6
#38
b00000000000000000000000000001001 +
1-
b000 /
#39
0-
#40
b00000000000000000000000000001010 +
1-
b010 /
b1111 2
b00000000000000000000100111000100 6
#41
0-
b00000000000000000000101110111000 6
#42
b00000000000000000000000000001001 +
1-
b000 /
#43
0-
#44
b00000000000000000000000000001010 +
1-
b010 /
b00000000000000000000111110100000 6
#45
0-
b00000000000000000001000110010100 6
#46
b00000000000000000000000000001001 +
1-
b000 /
#47
0-
#48
b00000000000000000000000000001010 +
1-
b010 /
b00000000000000000001010101111100 6
#49
0-
b00000000000000000001011101110000 6
#50
b00000000000000000000000000001001 +
1-
b000 /
#51
0-
#52
b00000000000000000000000000001000 +
1-
#53
0-
#54
b00000000000000000000000000000000 *
b00000000000000000000000000001010 +
1-
0.
b0000 2
b00000000000000000000000000000000 6
#55
0-
#56
1-
#57
0-
#58
b00000000000000000000000000000001 *
b00000000000000000000000000001001 +
1-
1.
#59
0-
#60
b00000000000000000000000000001010 +
1-
b100 /
b1111 2
b00000000000000000000011111010000 6
#61
0-
b00000000000000000000101110111000 6
#62
b00000000000000000000000000001001 +
1-
b000 /
#63
0-
#64
b00000000000000000000000000001010 +
1-
b100 /
b00000000000000000001001110001000 6
#65
0-
b00000000000000000001011101110000 6
#66
b00000000000000000000000000001001 +
1-
b000 /
#67
0-
#68
b00000000000000000000000000001000 +
1-
#69
0-
#70
b00000000000000000000000000000000 *
b00000000000000000000000000001010 +
1-
0.
b0000 2
b00000000000000000000000000000000 6
#71
0-
#72
1-
#73
0-
#74
b00000000000000000000000000000001 *
b00000000000000000000000000001001 +
1-
1.
#75
0-
#76
b00000000000000000000000000001010 +
1-
b100 /
b1111 2
b00000000000000000000011111010000 6
#77
0-
b00000000000000000000101110111000 6
#78
b00000000000000000000000000001001 +
1-
b000 /
#79
0-
#80
b00000000000000000000000000001010 +
1-
b100 /
b00000000000000000001001110001000 6
#81
0-
b00000000000000000001011101110000 6
#82
b00000000000000000000000000001001 +
1-
b000 /
#83
0-
#84
b00000000000000000000000000001010 +
1-
b100 /
b00000000000000000001111101000000 6
#85
0-
b00000000000000000010001100101000 6
#86
b00000000000000000000000000001001 +
1-
b000 /
#87
0-
#88
b00000000000000000000000000000010 *
b00000000000000000000000000001010 +
1-
b0001 0
b0111 3
b00000000000000000000000110010000 7
#89
0-
b00000000000000000000001100100000 7
#90
b00000000000000000000000000000001 *
b00000000000000000000000000001001 +
1-
b0000 0
#91
0-
#92
b00000000000000000000000000001000 +
1-
#93
0-
#94
b00000000000000000000000000000111 +
1-
#95
0-
#96
b00000000000000000000000000000010 *
b00000000000000000000000000001010 +
1-
b0001 0
b00000000000000000000010010110000 7
#97
0-
b00000000000000000000011001000000 7
#98
b00000000000000000000000000000001 *
b00000000000000000000000000001001 +
1-
b0000 0
#99
0-
#100
b00000000000000000000000000001000 +
1-
#101
0-
#102
b00000000000000000000000000000111 +
1-
#103
0-
#104
b00000000000000000000000000000010 *
b00000000000000000000000000001010 +
1-
b0001 0
b00000000000000000000011111010000 7
#105
0-
b00000000000000000000100101100000 7
#106
b00000000000000000000000000000001 *
b00000000000000000000000000001001 +
1-
b0000 0
#107
0-
#108
b00000000000000000000000000001000 +
1-
#109
0-
#110
b00000000000000000000000000000111 +
1-
#111
0-
#112
b00000000000000000000000000000010 *
b00000000000000000000000000001010 +
1-
b0001 0
b00000000000000000000101011110000 7
#113
0-
b00000000000000000000110010000000 7
#114
b00000000000000000000000000000001 *
b00000000000000000000000000001001 +
1-
b0000 0
#115
0-
#116
b00000000000000000000000000001000 +
1-
#117
0-
#118
b00000000000000000000000000000111 +
1-
#119
0-
#120
b00000000000000000000000000000010 *
b00000000000000000000000000001010 +
1-
b0001 0
b00000000000000000000111000010000 7
#121
0-
b00000000000000000000111110100000 7
#122
b00000000000000000000000000000001 *
b00000000000000000000000000001001 +
1-
b0000 0
#123
0-
#124
b00000000000000000000000000001000 +
1-
#125
0-
#126
b00000000000000000000000000000111 +
1-
#127
0-
#128
b00000000000000000000000000000010 *
b00000000000000000000000000001010 +
1-
b0001 0
b00000000000000000001000100110000 7
#129
0-
b00000000000000000001001011000000 7
#130
b00000000000000000000000000000001 *
b00000000000000000000000000001001 +
1-
b0000 0
#131
0-
#132
b00000000000000000000000000001000 +
1-
#133
0-
#134
b00000000000000000000000000000111 +
1-
#135
0-
#136
b00000000000000000000000000000010 *
b00000000000000000000000000001010 +
1-
b0001 0
b00000000000000000001010001010000 7
#137
0-
b00000000000000000001010111100000 7
#138
b00000000000000000000000000000001 *
b00000000000000000000000000001001 +
1-
b0000 0
#139
0-
#140
b00000000000000000000000000001000 +
1-
#141
0-
#142
b00000000000000000000000000000111 +
1-
#143
0-
#144
b00000000000000000000000000000110 +
1-
#145
0-
#146
b00000000000000000000000000000101 +
1-
#147
0-
#148
b00000000000000000000000000001010 +
1-
b100 /
b00000000000000000010101011111000 6
#149
0-
b00000000000000000010111011100000 6
#150
b00000000000000000000000000001001 +
1-
b000 /
#151
0-
#152
b00000000000000000000000000001010 +
1-
b100 /
b00000000000000000011011010110000 6
#153
0-
b00000000000000000011101010011000 6
#154
b00000000000000000000000000001001 +
1-
b000 /
#155
0-
#156
b00000000000000000000000000001010 +
1-
b100 /
b00000000000000000100001001101000 6
#157
0-
b00000000000000000100011001010000 6
#158
b00000000000000000000000000001001 +
1-
b000 /
#159
0-
#160
b00000000000000000000000000000010 *
b00000000000000000000000000001010 +
1-
b0010 0
b00000000000000000001011111010100 7
#161
0-
b00000000000000000001100111001000 7
#162
b00000000000000000000000000000001 *
b00000000000000000000000000001001 +
1-
b0000 0
#163
0-
#164
b00000000000000000000000000001000 +
1-
#165
0-
#166
b00000000000000000000000000000111 +
1-
#167
0-
#168
b00000000000000000000000000000010 *
b00000000000000000000000000001010 +
1-
b0010 0
b00000000000000000001101110111100 7
#169
0-
b00000000000000000001110110110000 7
#170
b00000000000000000000000000000001 *
b00000000000000000000000000001001 +
1-
b0000 0
#171
0-
#172
b00000000000000000000000000001000 +
1-
#173
0-
#174
b00000000000000000000000000000111 +
1-
#175
0-
#176
b00000000000000000000000000000010 *
b00000000000000000000000000001010 +
1-
b0010 0
b00000000000000000001111110100100 7
#177
0-
b00000000000000000010000110011000 7
#178
b00000000000000000000000000000001 *
b00000000000000000000000000001001 +
1-
b0000 0
#179
0-
#180
b00000000000000000000000000001000 +
1-
#181
0-
#182
b00000000000000000000000000000111 +
1-
#183
0-
#184
b00000000000000000000000000000010 *
b00000000000000000000000000001010 +
1-
b0010 0
b00000000000000000010001110001100 7
#185
0-
b00000000000000000010010110000000 7
#186
b00000000000000000000000000000001 *
b00000000000000000000000000001001 +
1-
b0000 0
#187
0-
#188
b00000000000000000000000000001000 +
1-
#189
0-
#190
b00000000000000000000000000000111 +
1-
#191
0-
#192
b00000000000000000000000000000010 *
b00000000000000000000000000001010 +
1-
b0010 0
b00000000000000000010011101110100 7
#193
0-
b00000000000000000010100101101000 7
#194
b00000000000000000000000000000001 *
b00000000000000000000000000001001 +
1-
b0000 0
#195
0-
#196
b00000000000000000000000000001000 +
1-
#197
0-
#198
b00000000000000000000000000000111 +
1-
#199
0-
#200
b00000000000000000000000000000010 *
b00000000000000000000000000001010 +
1-
b0010 0
b00000000000000000010101101011100 7
#201
0-
b00000000000000000010110101010000 7
#202
b00000000000000000000000000000001 *
b00000000000000000000000000001001 +
1-
b0000 0
#203
0-
#204
b00000000000000000000000000001000 +
1-
#205
0-
#206
b00000000000000000000000000000111 +
1-
#207
0-
#208
b00000000000000000000000000001010 +
1-
b001 /
b00000000000000000100011100011000 6
#209
0-
b00000000000000000100011101111100 6
#210
b00000000000000000000000000001001 +
1-
b000 /
#211
0-
#212
b00000000000000000000000000001010 +
1-
b001 /
b00000000000000000100100001000100 6
#213
0-
b00000000000000000100100010101000 6
#214
b00000000000000000000000000001001 +
1-
b000 /
#215
0-
#216
b00000000000000000000000000001010 +
1-
b100 /
b00000000000000000101000001111000 6
#217
0-
b00000000000000000101010001100000 6
#218
b00000000000000000000000000001001 +
1-
b000 /
#219
0-
#220
b00000000000000000000000000001010 +
1-
b100 /
b00000000000000000101110000110000 6
#221
0-
b00000000000000000110000000011000 6
#222
b00000000000000000000000000001001 +
1-
b000 /
#223
0-
#224
b00000000000000000000000000001010 +
1-
b100 /
b00000000000000000110011111101000 6
#225
0-
b00000000000000000110101111010000 6
#226
b00000000000000000000000000001001 +
1-
b000 /
#227
0-
#228
b00000000000000000000000000000010 *
b00000000000000000000000000001010 +
1-
b0100 0
b00000000000000000011000100111000 7
#229
0-
b00000000000000000011010100100000 7
#230
b00000000000000000000000000000001 *
b00000000000000000000000000001001 +
1-
b0000 0
#231
0-
#232
b00000000000000000000000000001000 +
1-
#233
0-
#234
b00000000000000000000000000000111 +
1-
#235
0-
#236
b00000000000000000000000000000010 *
b00000000000000000000000000001010 +
1-
b0100 0
b00000000000000000011100100001000 7
#237
0-
b00000000000000000011110011110000 7
#238
b00000000000000000000000000000001 *
b00000000000000000000000000001001 +
1-
b0000 0
#239
0-
#240
b00000000000000000000000000001000 +
1-
#241
0-
#242
b00000000000000000000000000000111 +
1-
#243
0-
#244
b00000000000000000000000000000010 *
b00000000000000000000000000001010 +
1-
b0100 0
b00000000000000000100000011011000 7
#245
0-
b00000000000000000100010011000000 7
#246
b00000000000000000000000000000001 *
b00000000000000000000000000001001 +
1-
b0000 0
#247
0-
#248
b00000000000000000000000000001000 +
1-
#249
0-
#250
b00000000000000000000000000000111 +
1-
#251
0-
#252
b00000000000000000000000000001010 +
1-
b100 /
b00000000000000000111001110100000 6
#253
0-
b00000000000000000111011110001000 6
#254
b00000000000000000000000000001001 +
1-
b000 /
#255
0-
#256
b00000000000000000000000000001010 +
1-
b100 /
b00000000000000000111111101011000 6
#257
0-
b00000000000000001000001101000000 6
#258
b00000000000000000000000000001001 +
1-
b000 /
#259
0-
#260
b00000000000000000000000000001010 +
1-
b100 /
b00000000000000001000101100010000 6
#261
0-
b00000000000000001000111011111000 6
#262
b00000000000000000000000000001001 +
1-
b000 /
#263
0-
#264
b00000000000000000000000000000010 *
b00000000000000000000000000001010 +
1-
b1000 0
b1111 3
b00000000000000000100110010010000 7
#265
0-
b00000000000000000101010001100000 7
#266
b00000000000000000000000000000001 *
b00000000000000000000000000001001 +
1-
b0000 0
#267
0-
#268
b00000000000000000000000000001000 +
1-
#269
0-
#270
b00000000000000000000000000000111 +
1-
#271
0-
#272
b00000000000000000000000000001010 +
1-
b100 /
b00000000000000001001011011001000 6
#273
0-
b00000000000000001001101010110000 6
#274
b00000000000000000000000000001001 +
1-
b000 /
#275
0-
#276
b00000000000000000000000000000010 *
b00000000000000000000000000001010 +
1-
b1000 0
b00000000000000000101110000110000 7
#277
0-
b00000000000000000110010000000000 7
#278
b00000000000000000000000000000001 *
b00000000000000000000000000001001 +
1-
b0000 0
#279
0-
#280
b00000000000000000000000000001000 +
1-
#281
0-
#282
b00000000000000000000000000000111 +
1-
#283
0-
#284
b00000000000000000000000000001010 +
1-
b001 /
b00000000000000001001101101111000 6
#285
0-
b00000000000000001001101111011100 6
#286
b00000000000000000000000000001001 +
1-
b000 /
#287
0-
#288
b00000000000000000000000000001010 +
1-
b001 /
b00000000000000001001110010100100 6
#289
0-
b00000000000000001001110100001000 6
#290
b00000000000000000000000000001001 +
1-
b000 /
#291
0-
#292
b00000000000000000000000000001010 +
1-
b001 /
b00000000000000001001110111010000 6
#293
0-
b00000000000000001001111000110100 6
#294
b00000000000000000000000000001001 +
1-
b000 /
#295
0-
#296
b00000000000000000000000000001010 +
1-
b001 /
b00000000000000001001111011111100 6
#297
0-
b00000000000000001001111101100000 6
#298
b00000000000000000000000000001001 +
1-
b000 /
#299
0-
#300
b00000000000000000000000000001010 +
1-
b010 /
b00000000000000001010001101001000 6
#301
0-
b00000000000000001010010100111100 6
#302
b00000000000000000000000000001001 +
1-
b000 /
#303
0-
#304
b00000000000000000000000000001010 +
1-
b010 /
b00000000000000001010100100100100 6
#305
0-
b00000000000000001010101100011000 6
#306
b00000000000000000000000000001001 +
1-
b000 /
#307
0-
#308
b00000000000000000000000000001010 +
1-
b100 /
b00000000000000001011001011101000 6
#309
0-
b00000000000000001011011011010000 6
#310
b00000000000000000000000000001001 +
1-
b000 /
#311
0-
#312
b00000000000000000000000000001000 +
1-
#313
0-
#314
b00000000000000000000000000000111 +
1-
#315
0-
#316
b00000000000000000000000000000110 +
1-
#317
0-
#318
b00000000000000000000000000000101 +
1-
#319
0-
#320
b00000000000000000000000000000100 +
1-
#321
0-
#322
b00000000000000000000000000000011 +
1-
#323
0-
#324
b00000000000000000000000000000010 +
1-
#325
0-
#326
b00000000000000000000000000000001 +
1-
#327
0-
#328
b00000000000000000000000000000000 +
1-
b00000000000000000000000000000011 5
#329
0-
#330
b00000000000000000000000000000011 *
b11111111111111111111111111111111 +
1-
b00000000000000000101001011010000 8
#331
0-
#332
b11111111111111111111111111111110 +
1-
#333
0-
#334
b11111111111111111111111111111101 +
1-
#335
0-
#336
b11111111111111111111111111111100 +
1-
#337
0-
#338
b11111111111111111111111111111011 +
1-
#339
0-
#340
b11111111111111111111111111111010 +
1-
#341
0-
#342
b11111111111111111111111111111001 +
1-
#343
0-
#344
b11111111111111111111111111111000 +
1-
#345
0-
#346
b11111111111111111111111111110111 +
1-
#347
0-
#348
b11111111111111111111111111110110 +
1-
#349
0-
#350
b11111111111111111111111111110101 +
1-
#351
0-
#352
b11111111111111111111111111110100 +
1-
#353
0-
#354
b11111111111111111111111111110011 +
1-
#355
0-
#356
b11111111111111111111111111110010 +
1-
#357
0-
#358
b11111111111111111111111111110001 +
1-
#359
0-
#360
b11111111111111111111111111110000 +
1-
#361
0-
#362
b11111111111111111111111111101111 +
1-
#363
0-
#364
b11111111111111111111111111101110 +
1-
#365
0-
#366
b11111111111111111111111111101101 +
1-
#367
0-
#368
b11111111111111111111111111101100 +
1-
#369
0-
#370
b11111111111111111111111111101011 +
1-
#371
0-
#372
b11111111111111111111111111101010 +
1-
#373
0-
#374
b11111111111111111111111111101001 +
1-
#375
0-
#376
b11111111111111111111111111101000 +
1-
#377
0-
#378
b11111111111111111111111111100111 +
1-
#379
0-
#380
b11111111111111111111111111100110 +
1-
#381
0-
#382
b11111111111111111111111111100101 +
1-
#383
0-
#384
b11111111111111111111111111100100 +
1-
#385
0-
#386
b11111111111111111111111111100011 +
1-
#387
0-
#388
b00000000000000000000000000001010 +
1-
b001 /
#389
0-
#390
b00000000000000000000000000001001 +
1-
b000 /
#391
0-
#392
b00000000000000000000000000001010 +
1-
b001 /
#393
0-
#394
b00000000000000000000000000001001 +
1-
b000 /
#395
0-
#396
b00000000000000000000000000001010 +
1-
b001 /
#397
0-
#398
b00000000000000000000000000001001 +
1-
b000 /
#399
0-
#400
b00000000000000000000000000001010 +
1-
b010 /
#401
0-
#402
b00000000000000000000000000001001 +
1-
b000 /
#403
0-
#404
b00000000000000000000000000001010 +
1-
b010 /
#405
0-
#406
b00000000000000000000000000001001 +
1-
b000 /
#407
0-
#408
b00000000000000000000000000001010 +
1-
b010 /
#409
0-
#410
b00000000000000000000000000001001 +
1-
b000 /
#411
0-
#412
b00000000000000000000000000001010 +
1-
b100 /
#413
0-
#414
b00000000000000000000000000001001 +
1-
b000 /
#415
0-
#416
b00000000000000000000000000001010 +
1-
b100 /
#417
0-
#418
b00000000000000000000000000001001 +
1-
b000 /
#419
0-
#420
b00000000000000000000000000001010 +
1-
b100 /
#421
0-
#422
b00000000000000000000000000001001 +
1-
b000 /
#423
0-
#424
b00000000000000000000000000001000 +
1-
#425
0-
#426
b00000000000000000000000000000111 +
1-
11
#427
0-
#428
b00000000000000000000000000000110 +
1-
#429
0-
#430
b00000000000000000000000000000101 +
1-
#431
0-
#432
b00000000000000000000000000000100 +
1-
#433
0-
#434
b00000000000000000000000000000011 +
1-
#435
0-
#436
b00000000000000000000000000000010 +
1-
#437
0-
#438
b00000000000000000000000000000001 +
1-
#439
0-
#440
b00000000000000000000000000000000 +
1-
#441
0-
#442
b11111111111111111111111111111111 +
1-
#443
0-
#444
b11111111111111111111111111111110 +
1-
#445
0-
#446
b11111111111111111111111111111101 +
1-
#447
0-
#448
b11111111111111111111111111111100 +
1-
#449
0-
#450
b11111111111111111111111111111011 +
1-
#451
0-
#452
b11111111111111111111111111111010 +
1-
#453
0-
#454
b11111111111111111111111111111001 +
1-
#455
0-
#456
b11111111111111111111111111111000 +
1-
#457
0-
#458
b11111111111111111111111111110111 +
1-
#459
0-
#460
b11111111111111111111111111110110 +
1-
#461
0-
#462
b11111111111111111111111111110101 +
1-
#463
0-
#464
b11111111111111111111111111110100 +
1-
#465
0-
#466
b11111111111111111111111111110011 +
1-
#467
0-
#468
b11111111111111111111111111110010 +
1-
#469
0-
#470
b11111111111111111111111111110001 +
1-
#471
0-
#472
b11111111111111111111111111110000 +
1-
#473
0-
#474
b11111111111111111111111111101111 +
1-
#475
0-
#476
b11111111111111111111111111101110 +
1-
#477
0-
#478
b11111111111111111111111111101101 +
1-
#479
0-
#480
b11111111111111111111111111101100 +
1-
#481
0-
#482
b11111111111111111111111111101011 +
1-
#483
0-
#484
b11111111111111111111111111101010 +
1-
#485
0-
#486
b11111111111111111111111111101001 +
1-
#487
0-
#488
b11111111111111111111111111101000 +
1-
#489
0-
#490
b11111111111111111111111111100111 +
1-
#491
0-
#492
b11111111111111111111111111100110 +
1-
#493
0-
#494
b11111111111111111111111111100101 +
1-
#495
0-
#496
b11111111111111111111111111100100 +
1-
