lab1/vending_machine/vending_machine_def.v
// Title         : vending_machine_def.v
// Author      : Jae-Eon Jo (Jojaeeon@postech.ac.kr) 
//					Dongup Kwon (nankdu7@postech.ac.kr)

// Macro constants (prefix k & CamelCase)
`define kTotalBits 32
  
`define kItemBits 8
`define kNumItems 4

`define kCoinBits 8
`define kNumCoins 3

`define kWaitTime 10

`define S0_init 32'h00
`define S1_wait 32'h01
`define S2_select 32'h02
`define S3_return 32'h03

lab1/vending_machine/change_state.v
`include "vending_machine_def.v"


module change_state(clk,reset_n,current_total_nxt,current_total);

	input clk;
	input reset_n;
	input [`kTotalBits-1:0] current_total_nxt;
	output reg [`kTotalBits-1:0] current_total;
	
	// Sequential circuit to reset or update the states
	always @(posedge clk ) begin
		if (!reset_n) begin
			// TODO: reset all states.

			//reset current_total(0)
			current_total <= `kTotalBits'b0;
		end
		else begin
			// TODO: update all states.
			
			// update current_total to current_total_nxt
			current_total <= current_total_nxt;
		end
	end
endmodule

lab1/vending_machine/calculate_current_state.v

`include "vending_machine_def.v"
	

module calculate_current_state(i_input_coin,i_select_item,item_price,coin_value,current_total,
/*input_total, output_total, return_total,*/current_total_nxt,wait_time,o_return_coin,o_available_item,o_output_item);


	
	input [`kNumCoins-1:0] i_input_coin,o_return_coin;
	input [`kNumItems-1:0]	i_select_item;			
	input [31:0] item_price [`kNumItems-1:0];
	input [31:0] coin_value [`kNumCoins-1:0];	
	input [`kTotalBits-1:0] current_total;
	input [31:0] wait_time;
	output reg [`kNumItems-1:0] o_available_item,o_output_item;
	//output reg  [`kTotalBits-1:0] input_total, output_total, return_total;
	output reg  [`kTotalBits-1:0] current_total_nxt;
	integer i;	


	
	// Combinational logic for the next states
	always @(*) begin
		// TODO: current_total_nxt
		// You don't have to worry about concurrent activations in each input vector (or array).
		// Calculate the next current_total state.

		// if input coin --> update input_total //
		if (o_return_coin == 0 && wait_time == 0)
			o_available_item[0] = 0;
		else	
			o_available_item[0] = 0;
		// current_total_nxt update
		for (i = 0; i < `kNumCoins; i = i+1) begin
			if (i_input_coin[i]) begin
				current_total_nxt = current_total + coin_value[i];
				o_available_item[0] = 1; //---//
			end
			else begin
				current_total_nxt = current_total;
				o_available_item[0] = 0;  //---//
			end
		end
		
		// select_item && avail --> current_total_nxt - price
		for (i = 0; i < `kItemBits; i = i+1) begin
			if (i_select_item[i] && o_available_item[i])
				current_total_nxt = current_total + item_price[i];
			else
				current_total_nxt = current_total; 
		end
		
	end

	
	
	// Combinational logic for the outputs
	always @(*) begin
		// TODO: o_available_item
		// TODO: o_output_item

		// if current_total enough --> update o_available_item
		for (i = 0; i < `kItemBits; i = i+1) begin
			if (current_total >= item_price[0])
				o_available_item[i] = 1;
			else
				o_available_item[i] = 0;
		end

		// if i_select_item && avail --> o_output_item
		
		for (i = 0; i < `kItemBits; i = i+1) begin
			if (i_select_item[i] && o_available_item[i])
				o_output_item[i] = 1;
			else
				o_output_item[i] = 0;
		end

	end
 
	


endmodule

lab1/vending_machine/check_time_and_coin.v
`include "vending_machine_def.v"

	

module check_time_and_coin(i_input_coin,i_select_item,clk,reset_n,wait_time,o_return_coin);
	input clk;
	input reset_n;
	input [`kNumCoins-1:0] i_input_coin;
	input [`kNumItems-1:0]	i_select_item;
	output reg  [`kNumCoins-1:0] o_return_coin;
	output reg [31:0] wait_time;

	// initiate values
	initial begin
		// TODO: initiate values

		// initiate o_return_coin(0000), wait_time(100) //
		o_return_coin = `kNumCoins'b0;
		wait_time = 100;
	end


	// update coin return time
	always @(i_input_coin, i_select_item) begin
		// TODO: update coin return time

		// wait_time will be initialized to original
	end

	always @(*) begin
		// TODO: o_return_coin

		// NOT SURE if select item and avail, subtract price of item from the o_return_coin
	end

	always @(posedge clk ) begin
		if (!reset_n) begin
		// TODO: reset all states.

		// reset all output value //
		o_return_coin <= `kNumCoins'b001; //여기 나중에 바꿔야함!!//
		wait_time <= 100;
		end
		else begin
		// TODO: update all states.

		// update output value - wait_time decresing //
		wait_time <= wait_time - 1;
		end
	end
endmodule

lab1/vending_machine/vending_machine.v
// Title         : vending_machine.v
// Author      : Jae-Eon Jo (Jojaeeon@postech.ac.kr) 
//			     Dongup Kwon (nankdu7@postech.ac.kr) (2015.03.30)
//			     Jaehun Ryu (jaehunryu@postech.ac.kr) (2021.03.07)

`include "vending_machine_def.v"


module vending_machine (
	clk,							// Clock signal
	reset_n,						// Reset signal (active-low)

	i_input_coin,				// coin is inserted.
	i_select_item,				// item is selected.
	i_trigger_return,			// change-return is triggered 

	o_available_item,			// Sign of the item availability
	o_output_item,			// Sign of the item withdrawal
	o_return_coin				// Sign of the coin return
);

	// Ports Declaration
	// Do not modify the module interface
	input clk;
	input reset_n;
	
	input [`kNumCoins-1:0] i_input_coin;
	input [`kNumItems-1:0] i_select_item;
	input i_trigger_return;
		
	output [`kNumItems-1:0] o_available_item;
	output [`kNumItems-1:0] o_output_item;
	output [`kNumCoins-1:0] o_return_coin;


	

	// Do not modify the values.
	wire [31:0] item_price [`kNumItems-1:0];	// Price of each item
	wire [31:0] coin_value [`kNumCoins-1:0];	// Value of each coin
	assign item_price[0] = 400;
	assign item_price[1] = 500;
	assign item_price[2] = 1000;
	assign item_price[3] = 2000;
	assign coin_value[0] = 100;
	assign coin_value[1] = 500;
	assign coin_value[2] = 1000;

	// Internal states. You may add your own net variables.
	wire [`kTotalBits-1:0] current_total;
	
	// Next internal states. You may add your own net variables.
	wire [`kTotalBits-1:0] current_total_nxt;

	
	// Variables. You may add more your own net variables.
	//wire [`kTotalBits-1:0] input_total, output_total, return_total;
	wire [31:0] wait_time;


	// This module interface, structure, and given a number of modules are not mandatory but recommended.
	// However, Implementations that use modules are mandatory.
	wire ret;
	assign ret = i_trigger_return;
	assign ret = ret;
  	check_time_and_coin check_time_and_coin_module(.i_input_coin(i_input_coin),
  									.i_select_item(i_select_item),
									.clk(clk),
									.reset_n(reset_n),
									.wait_time(wait_time),
									.o_return_coin(o_return_coin));

	calculate_current_state calculate_current_state_module(.i_input_coin(i_input_coin),
										.i_select_item(i_select_item),
										.item_price(item_price),
										.coin_value(coin_value),
										.current_total(current_total),
										/*.input_total(input_total),
										.output_total(output_total),
										.return_total(return_total),*/
										.current_total_nxt(current_total_nxt),
										.wait_time(wait_time),
										.o_return_coin(o_return_coin),
										.o_available_item(o_available_item),
										.o_output_item(o_output_item));
	
  	change_state change_state_module(
						.clk(clk),
						.reset_n(reset_n),
						.current_total_nxt(current_total_nxt),
						.current_total(current_total));


endmodule

lab1/vending_machine/waveform.vcd
$version Generated by VerilatedVcd $end
$timescale 1ps $end
 $scope module TOP $end
  $var wire 1 + clk $end
  $var wire 1 , reset_n $end
  $var wire 3 - i_input_coin [2:0] $end
  $var wire 4 . i_select_item [3:0] $end
  $var wire 1 / i_trigger_return $end
  $var wire 4 0 o_available_item [3:0] $end
  $var wire 4 1 o_output_item [3:0] $end
  $var wire 3 2 o_return_coin [2:0] $end
  $scope module vending_machine $end
   $var wire 1 + clk $end
   $var wire 1 , reset_n $end
   $var wire 3 - i_input_coin [2:0] $end
   $var wire 4 . i_select_item [3:0] $end
   $var wire 1 / i_trigger_return $end
   $var wire 4 0 o_available_item [3:0] $end
   $var wire 4 1 o_output_item [3:0] $end
   $var wire 3 2 o_return_coin [2:0] $end
   $var wire 32 # item_price[0] [31:0] $end
   $var wire 32 $ item_price[1] [31:0] $end
   $var wire 32 % item_price[2] [31:0] $end
   $var wire 32 & item_price[3] [31:0] $end
   $var wire 32 ' coin_value[0] [31:0] $end
   $var wire 32 ( coin_value[1] [31:0] $end
   $var wire 32 ) coin_value[2] [31:0] $end
   $var wire 32 3 current_total [31:0] $end
   $var wire 32 4 current_total_nxt [31:0] $end
   $var wire 32 5 wait_time [31:0] $end
   $var wire 1 / ret $end
   $scope module calculate_current_state_module $end
    $var wire 3 - i_input_coin [2:0] $end
    $var wire 3 2 o_return_coin [2:0] $end
    $var wire 4 . i_select_item [3:0] $end
    $var wire 32 # item_price[0] [31:0] $end
    $var wire 32 $ item_price[1] [31:0] $end
    $var wire 32 % item_price[2] [31:0] $end
    $var wire 32 & item_price[3] [31:0] $end
    $var wire 32 ' coin_value[0] [31:0] $end
    $var wire 32 ( coin_value[1] [31:0] $end
    $var wire 32 ) coin_value[2] [31:0] $end
    $var wire 32 3 current_total [31:0] $end
    $var wire 32 5 wait_time [31:0] $end
    $var wire 4 0 o_available_item [3:0] $end
    $var wire 4 1 o_output_item [3:0] $end
    $var wire 32 4 current_total_nxt [31:0] $end
    $var wire 32 * i [31:0] $end
   $upscope $end
   $scope module change_state_module $end
    $var wire 1 + clk $end
    $var wire 1 , reset_n $end
    $var wire 32 4 current_total_nxt [31:0] $end
    $var wire 32 3 current_total [31:0] $end
   $upscope $end
   $scope module check_time_and_coin_module $end
    $var wire 1 + clk $end
    $var wire 1 , reset_n $end
    $var wire 3 - i_input_coin [2:0] $end
    $var wire 4 . i_select_item [3:0] $end
    $var wire 3 2 o_return_coin [2:0] $end
    $var wire 32 5 wait_time [31:0] $end
   $upscope $end
  $upscope $end
 $upscope $end
$enddefinitions $end


#0
b00000000000000000000000110010000 #
b00000000000000000000000111110100 $
b00000000000000000000001111101000 %
b00000000000000000000011111010000 &
b00000000000000000000000001100100 '
b00000000000000000000000111110100 (
b00000000000000000000001111101000 )
b00000000000000000000000000001000 *
1+
1,
b000 -
b0000 .
0/
b1110 0
b0000 1
b000 2
b01110011010110000001011000110101 3
b01110011010110000001011000110101 4
b00000000000000000000000001100100 5
#1
0+
#2
1+
0,
b0000 0
b001 2
b00000000000000000000000000000000 3
b00000000000000000000000000000000 4
#3
0+
#4
1+
#5
0+
#6
1+
1,
b00000000000000000000000001100011 5
#7
0+
#8
1+
b001 -
b00000000000000000000000001100010 5
#9
0+
#10
1+
b000 -
b00000000000000000000000001100001 5
#11
0+
#12
1+
b001 -
b00000000000000000000000001100000 5
#13
0+
#14
1+
b000 -
b00000000000000000000000001011111 5
#15
0+
#16
1+
b001 -
b00000000000000000000000001011110 5
#17
0+
#18
1+
b000 -
b00000000000000000000000001011101 5
#19
0+
#20
1+
b001 -
b00000000000000000000000001011100 5
#21
0+
#22
1+
b000 -
b00000000000000000000000001011011 5
#23
0+
#24
1+
b001 -
b00000000000000000000000001011010 5
#25
0+
#26
1+
b000 -
b00000000000000000000000001011001 5
#27
0+
#28
1+
b00000000000000000000000001011000 5
#29
0+
#30
1+
0,
b00000000000000000000000001100100 5
#31
0+
#32
1+
#33
0+
#34
1+
1,
b00000000000000000000000001100011 5
#35
0+
#36
1+
b010 -
b00000000000000000000000001100010 5
#37
0+
#38
1+
b000 -
b00000000000000000000000001100001 5
#39
0+
#40
1+
b010 -
b00000000000000000000000001100000 5
#41
0+
#42
1+
b000 -
b00000000000000000000000001011111 5
#43
0+
#44
1+
b010 -
b00000000000000000000000001011110 5
#45
0+
#46
1+
b000 -
b00000000000000000000000001011101 5
#47
0+
#48
1+
b010 -
b00000000000000000000000001011100 5
#49
0+
#50
1+
b000 -
b00000000000000000000000001011011 5
#51
0+
#52
1+
b00000000000000000000000001011010 5
#53
0+
#54
1+
0,
b00000000000000000000000001100100 5
#55
0+
#56
1+
#57
0+
#58
1+
1,
b00000000000000000000000001100011 5
#59
0+
#60
1+
b100 -
b0001 0
b00000000000000000000000001100010 5
#61
0+
#62
1+
b000 -
b0000 0
b00000000000000000000000001100001 5
#63
0+
#64
1+
b100 -
b0001 0
b00000000000000000000000001100000 5
#65
0+
#66
1+
b000 -
b0000 0
b00000000000000000000000001011111 5
#67
0+
#68
1+
b00000000000000000000000001011110 5
#69
0+
#70
1+
0,
b00000000000000000000000001100100 5
#71
0+
#72
1+
#73
0+
#74
1+
1,
b00000000000000000000000001100011 5
#75
0+
#76
1+
b100 -
b0001 0
b00000000000000000000000001100010 5
#77
0+
#78
1+
b000 -
b0000 0
b00000000000000000000000001100001 5
#79
0+
#80
1+
b100 -
b0001 0
b00000000000000000000000001100000 5
#81
0+
#82
1+
b000 -
b0000 0
b00000000000000000000000001011111 5
#83
0+
#84
1+
b100 -
b0001 0
b00000000000000000000000001011110 5
#85
0+
#86
1+
b000 -
b0000 0
b00000000000000000000000001011101 5
#87
0+
#88
1+
b0001 .
b00000000000000000000000001011100 5
#89
0+
#90
1+
b0000 .
b00000000000000000000000001011011 5
#91
0+
#92
1+
b00000000000000000000000001011010 5
#93
0+
#94
1+
b00000000000000000000000001011001 5
#95
0+
#96
1+
b0001 .
b00000000000000000000000001011000 5
#97
0+
#98
1+
b0000 .
b00000000000000000000000001010111 5
#99
0+
#100
1+
b00000000000000000000000001010110 5
#101
0+
#102
1+
b00000000000000000000000001010101 5
#103
0+
#104
1+
b0001 .
b00000000000000000000000001010100 5
#105
0+
#106
1+
b0000 .
b00000000000000000000000001010011 5
#107
0+
#108
1+
b00000000000000000000000001010010 5
#109
0+
#110
1+
b00000000000000000000000001010001 5
#111
0+
#112
1+
b0001 .
b00000000000000000000000001010000 5
#113
0+
#114
1+
b0000 .
b00000000000000000000000001001111 5
#115
0+
#116
1+
b00000000000000000000000001001110 5
#117
0+
#118
1+
b00000000000000000000000001001101 5
#119
0+
#120
1+
b0001 .
b00000000000000000000000001001100 5
#121
0+
#122
1+
b0000 .
b00000000000000000000000001001011 5
#123
0+
#124
1+
b00000000000000000000000001001010 5
#125
0+
#126
1+
b00000000000000000000000001001001 5
#127
0+
#128
1+
b0001 .
b00000000000000000000000001001000 5
#129
0+
#130
1+
b0000 .
b00000000000000000000000001000111 5
#131
0+
#132
1+
b00000000000000000000000001000110 5
#133
0+
#134
1+
b00000000000000000000000001000101 5
#135
0+
#136
1+
b0001 .
b00000000000000000000000001000100 5
#137
0+
#138
1+
b0000 .
b00000000000000000000000001000011 5
#139
0+
#140
1+
b00000000000000000000000001000010 5
#141
0+
#142
1+
b00000000000000000000000001000001 5
#143
0+
#144
1+
b00000000000000000000000001000000 5
#145
0+
#146
1+
b00000000000000000000000000111111 5
#147
0+
#148
1+
b100 -
b0001 0
b00000000000000000000000000111110 5
#149
0+
#150
1+
b000 -
b0000 0
b00000000000000000000000000111101 5
#151
0+
#152
1+
b100 -
b0001 0
b00000000000000000000000000111100 5
#153
0+
#154
1+
b000 -
b0000 0
b00000000000000000000000000111011 5
#155
0+
#156
1+
b100 -
b0001 0
b00000000000000000000000000111010 5
#157
0+
#158
1+
b000 -
b0000 0
b00000000000000000000000000111001 5
#159
0+
#160
1+
b0010 .
b00000000000000000000000000111000 5
#161
0+
#162
1+
b0000 .
b00000000000000000000000000110111 5
#163
0+
#164
1+
b00000000000000000000000000110110 5
#165
0+
#166
1+
b00000000000000000000000000110101 5
#167
0+
#168
1+
b0010 .
b00000000000000000000000000110100 5
#169
0+
#170
1+
b0000 .
b00000000000000000000000000110011 5
#171
0+
#172
1+
b00000000000000000000000000110010 5
#173
0+
#174
1+
b00000000000000000000000000110001 5
#175
0+
#176
1+
b0010 .
b00000000000000000000000000110000 5
#177
0+
#178
1+
b0000 .
b00000000000000000000000000101111 5
#179
0+
#180
1+
b00000000000000000000000000101110 5
#181
0+
#182
1+
b00000000000000000000000000101101 5
#183
0+
#184
1+
b0010 .
b00000000000000000000000000101100 5
#185
0+
#186
1+
b0000 .
b00000000000000000000000000101011 5
#187
0+
#188
1+
b00000000000000000000000000101010 5
#189
0+
#190
1+
b00000000000000000000000000101001 5
#191
0+
#192
1+
b0010 .
b00000000000000000000000000101000 5
#193
0+
#194
1+
b0000 .
b00000000000000000000000000100111 5
#195
0+
#196
1+
b00000000000000000000000000100110 5
#197
0+
#198
1+
b00000000000000000000000000100101 5
#199
0+
#200
1+
b0010 .
b00000000000000000000000000100100 5
#201
0+
#202
1+
b0000 .
b00000000000000000000000000100011 5
#203
0+
#204
1+
b00000000000000000000000000100010 5
#205
0+
#206
1+
b00000000000000000000000000100001 5
#207
0+
#208
1+
b001 -
b00000000000000000000000000100000 5
#209
0+
#210
1+
b000 -
b00000000000000000000000000011111 5
#211
0+
#212
1+
b001 -
b00000000000000000000000000011110 5
#213
0+
#214
1+
b000 -
b00000000000000000000000000011101 5
#215
0+
#216
1+
b100 -
b0001 0
b00000000000000000000000000011100 5
#217
0+
#218
1+
b000 -
b0000 0
b00000000000000000000000000011011 5
#219
0+
#220
1+
b100 -
b0001 0
b00000000000000000000000000011010 5
#221
0+
#222
1+
b000 -
b0000 0
b00000000000000000000000000011001 5
#223
0+
#224
1+
b100 -
b0001 0
b00000000000000000000000000011000 5
#225
0+
#226
1+
b000 -
b0000 0
b00000000000000000000000000010111 5
#227
0+
#228
1+
b0100 .
b00000000000000000000000000010110 5
#229
0+
#230
1+
b0000 .
b00000000000000000000000000010101 5
#231
0+
#232
1+
b00000000000000000000000000010100 5
#233
0+
#234
1+
b00000000000000000000000000010011 5
#235
0+
#236
1+
b0100 .
b00000000000000000000000000010010 5
#237
0+
#238
1+
b0000 .
b00000000000000000000000000010001 5
#239
0+
#240
1+
b00000000000000000000000000010000 5
#241
0+
#242
1+
b00000000000000000000000000001111 5
#243
0+
#244
1+
b0100 .
b00000000000000000000000000001110 5
#245
0+
#246
1+
b0000 .
b00000000000000000000000000001101 5
#247
0+
#248
1+
b00000000000000000000000000001100 5
#249
0+
#250
1+
b00000000000000000000000000001011 5
#251
0+
#252
1+
b100 -
b0001 0
b00000000000000000000000000001010 5
#253
0+
#254
1+
b000 -
b0000 0
b00000000000000000000000000001001 5
#255
0+
#256
1+
b100 -
b0001 0
b00000000000000000000000000001000 5
#257
0+
#258
1+
b000 -
b0000 0
b00000000000000000000000000000111 5
#259
0+
#260
1+
b100 -
b0001 0
b00000000000000000000000000000110 5
#261
0+
#262
1+
b000 -
b0000 0
b00000000000000000000000000000101 5
#263
0+
#264
1+
b1000 .
b00000000000000000000000000000100 5
#265
0+
#266
1+
b0000 .
b00000000000000000000000000000011 5
#267
0+
#268
1+
b00000000000000000000000000000010 5
#269
0+
#270
1+
b00000000000000000000000000000001 5
#271
0+
#272
1+
b100 -
b0001 0
b00000000000000000000000000000000 5
#273
0+
#274
1+
b000 -
b0000 0
b11111111111111111111111111111111 5
#275
0+
#276
1+
b1000 .
b11111111111111111111111111111110 5
#277
0+
#278
1+
b0000 .
b11111111111111111111111111111101 5
#279
0+
#280
1+
b11111111111111111111111111111100 5
#281
0+
#282
1+
b11111111111111111111111111111011 5
#283
0+
#284
1+
b001 -
b11111111111111111111111111111010 5
#285
0+
#286
1+
b000 -
b11111111111111111111111111111001 5
#287
0+
#288
1+
b001 -
b11111111111111111111111111111000 5
#289
0+
#290
1+
b000 -
b11111111111111111111111111110111 5
#291
0+
#292
1+
b001 -
b11111111111111111111111111110110 5
#293
0+
#294
1+
b000 -
b11111111111111111111111111110101 5
#295
0+
#296
1+
b001 -
b11111111111111111111111111110100 5
#297
0+
#298
1+
b000 -
b11111111111111111111111111110011 5
#299
0+
#300
1+
b010 -
b11111111111111111111111111110010 5
#301
0+
#302
1+
b000 -
b11111111111111111111111111110001 5
#303
0+
#304
1+
b010 -
b11111111111111111111111111110000 5
#305
0+
#306
1+
b000 -
b11111111111111111111111111101111 5
#307
0+
#308
1+
b100 -
b0001 0
b11111111111111111111111111101110 5
#309
0+
#310
1+
b000 -
b0000 0
b11111111111111111111111111101101 5
#311
0+
#312
1+
b11111111111111111111111111101100 5
#313
0+
#314
1+
b11111111111111111111111111101011 5
#315
0+
#316
1+
b11111111111111111111111111101010 5
#317
0+
#318
1+
b11111111111111111111111111101001 5
#319
0+
#320
1+
b11111111111111111111111111101000 5
#321
0+
#322
1+
b11111111111111111111111111100111 5
#323
0+
#324
1+
b11111111111111111111111111100110 5
#325
0+
#326
1+
b11111111111111111111111111100101 5
#327
0+
#328
1+
b11111111111111111111111111100100 5
#329
0+
#330
1+
b11111111111111111111111111100011 5
#331
0+
#332
1+
b11111111111111111111111111100010 5
#333
0+
#334
1+
b11111111111111111111111111100001 5
#335
0+
#336
1+
b11111111111111111111111111100000 5
#337
0+
#338
1+
b11111111111111111111111111011111 5
#339
0+
#340
1+
b11111111111111111111111111011110 5
#341
0+
#342
1+
b11111111111111111111111111011101 5
#343
0+
#344
1+
b11111111111111111111111111011100 5
#345
0+
#346
1+
b11111111111111111111111111011011 5
#347
0+
#348
1+
b11111111111111111111111111011010 5
#349
0+
#350
1+
b11111111111111111111111111011001 5
#351
0+
#352
1+
b11111111111111111111111111011000 5
#353
0+
#354
1+
b11111111111111111111111111010111 5
#355
0+
#356
1+
b11111111111111111111111111010110 5
#357
0+
#358
1+
b11111111111111111111111111010101 5
#359
0+
#360
1+
b11111111111111111111111111010100 5
#361
0+
#362
1+
b11111111111111111111111111010011 5
#363
0+
#364
1+
b11111111111111111111111111010010 5
#365
0+
#366
1+
b11111111111111111111111111010001 5
#367
0+
#368
1+
b11111111111111111111111111010000 5
#369
0+
#370
1+
b11111111111111111111111111001111 5
#371
0+
#372
1+
b11111111111111111111111111001110 5
#373
0+
#374
1+
b11111111111111111111111111001101 5
#375
0+
#376
1+
b11111111111111111111111111001100 5
#377
0+
#378
1+
b11111111111111111111111111001011 5
#379
0+
#380
1+
b11111111111111111111111111001010 5
#381
0+
#382
1+
b11111111111111111111111111001001 5
#383
0+
#384
1+
b11111111111111111111111111001000 5
#385
0+
#386
1+
b11111111111111111111111111000111 5
#387
0+
#388
1+
b001 -
b11111111111111111111111111000110 5
#389
0+
#390
1+
b000 -
b11111111111111111111111111000101 5
#391
0+
#392
1+
b001 -
b11111111111111111111111111000100 5
#393
0+
#394
1+
b000 -
b11111111111111111111111111000011 5
#395
0+
#396
1+
b001 -
b11111111111111111111111111000010 5
#397
0+
#398
1+
b000 -
b11111111111111111111111111000001 5
#399
0+
#400
1+
b010 -
b11111111111111111111111111000000 5
#401
0+
#402
1+
b000 -
b11111111111111111111111110111111 5
#403
0+
#404
1+
b010 -
b11111111111111111111111110111110 5
#405
0+
#406
1+
b000 -
b11111111111111111111111110111101 5
#407
0+
#408
1+
b010 -
b11111111111111111111111110111100 5
#409
0+
#410
1+
b000 -
b11111111111111111111111110111011 5
#411
0+
#412
1+
b100 -
b0001 0
b11111111111111111111111110111010 5
#413
0+
#414
1+
b000 -
b0000 0
b11111111111111111111111110111001 5
#415
0+
#416
1+
b100 -
b0001 0
b11111111111111111111111110111000 5
#417
0+
#418
1+
b000 -
b0000 0
b11111111111111111111111110110111 5
#419
0+
#420
1+
b100 -
b0001 0
b11111111111111111111111110110110 5
#421
0+
#422
1+
b000 -
b0000 0
b11111111111111111111111110110101 5
#423
0+
#424
1+
b11111111111111111111111110110100 5
#425
0+
#426
1+
1/
b11111111111111111111111110110011 5
#427
0+
#428
1+
b11111111111111111111111110110010 5
#429
0+
#430
1+
b11111111111111111111111110110001 5
#431
0+
#432
1+
b11111111111111111111111110110000 5
#433
0+
#434
1+
b11111111111111111111111110101111 5
#435
0+
#436
1+
b11111111111111111111111110101110 5
#437
0+
#438
1+
b11111111111111111111111110101101 5
#439
0+
#440
1+
b11111111111111111111111110101100 5
#441
0+
#442
1+
b11111111111111111111111110101011 5
#443
0+
#444
1+
b11111111111111111111111110101010 5
#445
0+
#446
1+
b11111111111111111111111110101001 5
#447
0+
#448
1+
b11111111111111111111111110101000 5
#449
0+
#450
1+
b11111111111111111111111110100111 5
#451
0+
#452
1+
b11111111111111111111111110100110 5
#453
0+
#454
1+
b11111111111111111111111110100101 5
#455
0+
#456
1+
b11111111111111111111111110100100 5
#457
0+
#458
1+
b11111111111111111111111110100011 5
#459
0+
#460
1+
b11111111111111111111111110100010 5
#461
0+
#462
1+
b11111111111111111111111110100001 5
#463
0+
#464
1+
b11111111111111111111111110100000 5
#465
0+
#466
1+
b11111111111111111111111110011111 5
#467
0+
#468
1+
b11111111111111111111111110011110 5
#469
0+
#470
1+
b11111111111111111111111110011101 5
#471
0+
#472
1+
b11111111111111111111111110011100 5
#473
0+
#474
1+
b11111111111111111111111110011011 5
#475
0+
#476
1+
b11111111111111111111111110011010 5
#477
0+
#478
1+
b11111111111111111111111110011001 5
#479
0+
#480
1+
b11111111111111111111111110011000 5
#481
0+
#482
1+
b11111111111111111111111110010111 5
#483
0+
#484
1+
b11111111111111111111111110010110 5
#485
0+
#486
1+
b11111111111111111111111110010101 5
#487
0+
#488
1+
b11111111111111111111111110010100 5
#489
0+
#490
1+
b11111111111111111111111110010011 5
#491
0+
#492
1+
b11111111111111111111111110010010 5
#493
0+
#494
1+
b11111111111111111111111110010001 5
#495
0+
#496
1+
b11111111111111111111111110010000 5
#497
0+
#498
1+
b11111111111111111111111110001111 5
#499
0+
#500
1+
b11111111111111111111111110001110 5
#501
0+
#502
1+
b11111111111111111111111110001101 5
#503
0+
#504
1+
b11111111111111111111111110001100 5
#505
0+
#506
1+
b11111111111111111111111110001011 5
#507
0+
#508
1+
b11111111111111111111111110001010 5
#509
0+
#510
1+
b11111111111111111111111110001001 5
#511
0+
#512
1+
b11111111111111111111111110001000 5
#513
0+
#514
1+
b11111111111111111111111110000111 5
#515
0+
#516
1+
b11111111111111111111111110000110 5
#517
0+
#518
1+
b11111111111111111111111110000101 5
#519
0+
#520
1+
b11111111111111111111111110000100 5
#521
0+
#522
1+
b11111111111111111111111110000011 5
#523
0+
#524
1+
b11111111111111111111111110000010 5
#525
0+
#526
1+
b11111111111111111111111110000001 5
