lab1/vending_machine/vending_machine_def.v
// Title         : vending_machine_def.v
// Author      : Jae-Eon Jo (Jojaeeon@postech.ac.kr) 
//					Dongup Kwon (nankdu7@postech.ac.kr)

// Macro constants (prefix k & CamelCase)
`define kTotalBits 32
  
`define kItemBits 8
`define kNumItems 4

`define kCoinBits 8
`define kNumCoins 3

`define kWaitTime 10

`define S0_init 32'h00
`define S1_wait 32'h01
`define S2_select 32'h02
`define S3_return 32'h03

lab1/vending_machine/change_state.v
`include "vending_machine_def.v"


module change_state(clk,reset_n,current_total_nxt,current_total);

	input clk;
	input reset_n;
	input [`kTotalBits-1:0] current_total_nxt;
	output reg [`kTotalBits-1:0] current_total;
	
	// Sequential circuit to reset or update the states
	always @(posedge clk ) begin
		if (!reset_n) begin
			// TODO: reset all states.

			//reset current_total(0)
			current_total <= `kTotalBits'b0;
		end
		else begin
			// TODO: update all states.
			
			// update current_total to current_total_nxt
			current_total <= current_total_nxt;
		end
	end
endmodule

lab1/vending_machine/calculate_current_state.v

`include "vending_machine_def.v"
	

module calculate_current_state(i_input_coin,i_select_item,i_trigger_return,item_price,coin_value,current_total,
relative_money,current_total_nxt,wait_time,o_return_coin,o_available_item,o_output_item);

	input i_trigger_return;
	
	input [`kNumCoins-1:0] i_input_coin,o_return_coin;
	input [`kNumItems-1:0]	i_select_item;			
	input [31:0] item_price [`kNumItems-1:0];
	input [31:0] coin_value [`kNumCoins-1:0];	
	input [`kTotalBits-1:0] current_total;
	input [31:0] wait_time;
	output reg [`kNumItems-1:0] o_available_item,o_output_item;
	output [`kTotalBits-1:0] relative_money;
	output reg  [`kTotalBits-1:0] current_total_nxt;
	integer i;	

	reg  [`kTotalBits-1:0] input_total, output_total, return_total;
	reg turn;

	assign relative_money = input_total - output_total - return_total;

	// Combinational logic for the next states
	always @(*) begin
		
		// if (current_total == `S4_return && relative_money == 0)
		// 	current_total_nxt = `S0_init;
		// else if (i_input_coin > 0)
		// 	current_total_nxt = `S2_coin;
		// else if (wait_time == 0 || i_trigger_return)
		// 	current_total_nxt = `S4_return;
		// else if (i_select_item > 0)
		// 	current_total_nxt = `S3_select;
		// else 
		// 	current_total_nxt = `S1_wait;

		//maybe we can use this logic also.

		case (current_total)
			`S0_init:
				if (i_input_coin > 0) 
					current_total_nxt = `S2_coin;
				else 
					current_total_nxt = `S1_wait;
			`S1_wait:
				if (i_input_coin > 0) 
					current_total_nxt = `S2_coin;
				else if (i_select_item > 0) 
					current_total_nxt = `S3_select;
				else if (wait_time == 0 || i_trigger_return)
					current_total_nxt = `S4_return;
			`S2_coin:
				current_total_nxt = `S1_wait;
			`S3_select:
				current_total_nxt = `S1_wait;
			`S4_return:
				if (relative_money == 0)
					current_total_nxt = `S0_init;
		endcase
		
	end

	
	
	// Combinational logic for the outputs
	always @(*) begin
		case (current_total)
			`S0_init: begin
				input_total = 0;
				output_total = 0;
				return_total = 0;
				turn = 1;
			end
			`S1_wait: begin
				for (i = 0; i < `kNumItems; i = i + 1) begin
					if (input_total - output_total >= item_price[i])
						o_available_item[i] = 1;
					else
						o_available_item[i] = 0;
				end
				turn = 1;
			end
			`S2_coin: begin
				//$monitor("input_total: %d", input_total);
				if (turn) begin
					for (i = 0; i < `kNumCoins; i = i + 1) begin
						if (i_input_coin[i]) begin
							//$display("input_total: %d, coin: %d", input_total, coin_value[i]);
							input_total = input_total + coin_value[i];
						end
					end
					turn = 0;
				end
			end
			`S3_select: begin
				if (turn) begin
					for (i = 0; i < `kNumItems; i = i+1) begin
						if (i_select_item[i] && o_available_item[i]) begin
							o_output_item[i] = 1;
							output_total = output_total + item_price[i];
						end
						else begin
							o_output_item[i] = 0;
						end
					end
					turn = 0;
				end
			end
			`S4_return: begin
				for (i = 0; i < `kNumCoins; i = i + 1) begin
					if (o_return_coin[i]) begin
						return_total = return_total + coin_value[i];
					end
				end
			end
		endcase

	end
 
	


endmodule

lab1/vending_machine/check_time_and_coin.v
`include "vending_machine_def.v"

	

module check_time_and_coin(i_input_coin,i_select_item,coin_value,o_available_item,relative_money,current_total,i_trigger_return,clk,reset_n,wait_time,o_return_coin);
	input clk;
	input reset_n;
	input i_trigger_return;
	input [31:0] coin_value [`kNumCoins-1:0];
	input [`kNumCoins-1:0] i_input_coin;
	input [`kNumItems-1:0]	i_select_item;
	input [`kNumItems-1:0] o_available_item;
	input [`kTotalBits-1:0] relative_money;
	input [`kTotalBits-1:0] current_total;
	output reg  [`kNumCoins-1:0] o_return_coin;
	output reg [31:0] wait_time;

	reg flag;

	// initiate values
	initial begin
		// TODO: initiate values

		
	end


	// update coin return time
	always @(i_input_coin, i_select_item) begin
		// TODO: update coin return time
		
	end

	always @(*) begin
		// TODO: o_return_coin
	
	end

	always @(posedge clk ) begin

		// return coin in descending order of coin value
		if (wait_time == 0) begin
			if (relative_money >= coin_value[2])
				o_return_coin <= `kNumCoins'b100; // 1000
			else if (relative_money >= coin_value[1])
				o_return_coin <= `kNumCoins'b010; // 500
			else if (relative_money >= coin_value[0])
				o_return_coin <= `kNumCoins'b001; // 100
			else
				o_return_coin <= `kNumCoins'b000;
		end
		else	
			o_return_coin <= `kNumCoins'b000;



		if (!reset_n) begin
			wait_time <= `kWaitTime;
			flag <= 0;
			o_return_coin <= `kNumCoins'b000;
		end
		else if (i_trigger_return && !flag) begin // wait 3 cycles before starting return
			wait_time <= 2;
			flag <= 1;
		end
		else if (!i_trigger_return && flag) // initialize flag when return command button canceled
			flag <= 0;
		else if (i_input_coin > 0 || current_total == `S0_init)
			wait_time <= `kWaitTime;
		else if ((i_select_item & o_available_item) > 0) // initialize wait time when purchase
			wait_time <= `kWaitTime;
		else begin // time diminishes per clk
			if (wait_time > 0)
				wait_time <= wait_time - 1;
			else
				wait_time <= 0;
		end
	end
endmodule

lab1/vending_machine/vending_machine.v
// Title         : vending_machine.v
// Author      : Jae-Eon Jo (Jojaeeon@postech.ac.kr) 
//			     Dongup Kwon (nankdu7@postech.ac.kr) (2015.03.30)
//			     Jaehun Ryu (jaehunryu@postech.ac.kr) (2021.03.07)

`include "vending_machine_def.v"


module vending_machine (
	clk,							// Clock signal
	reset_n,						// Reset signal (active-low)

	i_input_coin,				// coin is inserted.
	i_select_item,				// item is selected.
	i_trigger_return,			// change-return is triggered 

	o_available_item,			// Sign of the item availability
	o_output_item,			// Sign of the item withdrawal
	o_return_coin				// Sign of the coin return
);

	// Ports Declaration
	// Do not modify the module interface
	input clk;
	input reset_n;
	
	input [`kNumCoins-1:0] i_input_coin;
	input [`kNumItems-1:0] i_select_item;
	input i_trigger_return;
		
	output [`kNumItems-1:0] o_available_item;
	output [`kNumItems-1:0] o_output_item;
	output [`kNumCoins-1:0] o_return_coin;


	

	// Do not modify the values.
	wire [31:0] item_price [`kNumItems-1:0];	// Price of each item
	wire [31:0] coin_value [`kNumCoins-1:0];	// Value of each coin
	assign item_price[0] = 400;
	assign item_price[1] = 500;
	assign item_price[2] = 1000;
	assign item_price[3] = 2000;
	assign coin_value[0] = 100;
	assign coin_value[1] = 500;
	assign coin_value[2] = 1000;

	// Internal states. You may add your own net variables.
	wire [`kTotalBits-1:0] current_total;
	
	// Next internal states. You may add your own net variables.
	wire [`kTotalBits-1:0] current_total_nxt;

	
	// Variables. You may add more your own net variables.
	wire [`kTotalBits-1:0] relative_money;
	wire [31:0] wait_time;


	// This module interface, structure, and given a number of modules are not mandatory but recommended.
	// However, Implementations that use modules are mandatory.
	
  	check_time_and_coin check_time_and_coin_module(.i_input_coin(i_input_coin),
  									.i_select_item(i_select_item),
									.coin_value(coin_value),
									.o_available_item(o_available_item),
									.relative_money(relative_money),
									.current_total(current_total),
									.i_trigger_return(i_trigger_return),
									.clk(clk),
									.reset_n(reset_n),
									.wait_time(wait_time),
									.o_return_coin(o_return_coin));

	calculate_current_state calculate_current_state_module(.i_input_coin(i_input_coin),
										.i_select_item(i_select_item),
										.i_trigger_return(i_trigger_return),
										.item_price(item_price),
										.coin_value(coin_value),
										.current_total(current_total),
										.relative_money(relative_money),
										.current_total_nxt(current_total_nxt),
										.wait_time(wait_time),
										.o_return_coin(o_return_coin),
										.o_available_item(o_available_item),
										.o_output_item(o_output_item));
	
  	change_state change_state_module(
						.clk(clk),
						.reset_n(reset_n),
						.current_total_nxt(current_total_nxt),
						.current_total(current_total));


endmodule

lab1/vending_machine/waveform.vcd
$version Generated by VerilatedVcd $end
$timescale 1ps $end
 $scope module TOP $end
  $var wire 1 4 clk $end
  $var wire 1 5 reset_n $end
  $var wire 3 6 i_input_coin [2:0] $end
  $var wire 4 7 i_select_item [3:0] $end
  $var wire 1 8 i_trigger_return $end
  $var wire 4 9 o_available_item [3:0] $end
  $var wire 4 : o_output_item [3:0] $end
  $var wire 3 ; o_return_coin [2:0] $end
  $scope module vending_machine $end
   $var wire 1 4 clk $end
   $var wire 1 5 reset_n $end
   $var wire 3 6 i_input_coin [2:0] $end
   $var wire 4 7 i_select_item [3:0] $end
   $var wire 1 8 i_trigger_return $end
   $var wire 4 9 o_available_item [3:0] $end
   $var wire 4 : o_output_item [3:0] $end
   $var wire 3 ; o_return_coin [2:0] $end
   $var wire 32 # item_price[0] [31:0] $end
   $var wire 32 $ item_price[1] [31:0] $end
   $var wire 32 % item_price[2] [31:0] $end
   $var wire 32 & item_price[3] [31:0] $end
   $var wire 32 ' coin_value[0] [31:0] $end
   $var wire 32 ( coin_value[1] [31:0] $end
   $var wire 32 ) coin_value[2] [31:0] $end
   $var wire 32 0 current_total [31:0] $end
   $var wire 32 * current_total_nxt [31:0] $end
   $var wire 32 + relative_money [31:0] $end
   $var wire 32 1 wait_time [31:0] $end
   $scope module calculate_current_state_module $end
    $var wire 1 8 i_trigger_return $end
    $var wire 3 6 i_input_coin [2:0] $end
    $var wire 3 ; o_return_coin [2:0] $end
    $var wire 4 7 i_select_item [3:0] $end
    $var wire 32 # item_price[0] [31:0] $end
    $var wire 32 $ item_price[1] [31:0] $end
    $var wire 32 % item_price[2] [31:0] $end
    $var wire 32 & item_price[3] [31:0] $end
    $var wire 32 ' coin_value[0] [31:0] $end
    $var wire 32 ( coin_value[1] [31:0] $end
    $var wire 32 ) coin_value[2] [31:0] $end
    $var wire 32 0 current_total [31:0] $end
    $var wire 32 1 wait_time [31:0] $end
    $var wire 4 9 o_available_item [3:0] $end
    $var wire 4 : o_output_item [3:0] $end
    $var wire 32 + relative_money [31:0] $end
    $var wire 32 * current_total_nxt [31:0] $end
    $var wire 32 , i [31:0] $end
    $var wire 32 - input_total [31:0] $end
    $var wire 32 . output_total [31:0] $end
    $var wire 32 2 return_total [31:0] $end
    $var wire 1 / turn $end
   $upscope $end
   $scope module change_state_module $end
    $var wire 1 4 clk $end
    $var wire 1 5 reset_n $end
    $var wire 32 * current_total_nxt [31:0] $end
    $var wire 32 0 current_total [31:0] $end
   $upscope $end
   $scope module check_time_and_coin_module $end
    $var wire 1 4 clk $end
    $var wire 1 5 reset_n $end
    $var wire 1 8 i_trigger_return $end
    $var wire 32 ' coin_value[0] [31:0] $end
    $var wire 32 ( coin_value[1] [31:0] $end
    $var wire 32 ) coin_value[2] [31:0] $end
    $var wire 3 6 i_input_coin [2:0] $end
    $var wire 4 7 i_select_item [3:0] $end
    $var wire 4 9 o_available_item [3:0] $end
    $var wire 32 + relative_money [31:0] $end
    $var wire 32 0 current_total [31:0] $end
    $var wire 3 ; o_return_coin [2:0] $end
    $var wire 32 1 wait_time [31:0] $end
    $var wire 1 3 flag $end
   $upscope $end
  $upscope $end
 $upscope $end
$enddefinitions $end


#0
b00000000000000000000000110010000 #
b00000000000000000000000111110100 $
b00000000000000000000001111101000 %
b00000000000000000000011111010000 &
b00000000000000000000000001100100 '
b00000000000000000000000111110100 (
b00000000000000000000001111101000 )
b10101101111110111100100100010010 *
b10000101110011010100000001001010 +
b00000110101011011111010100111011 ,
b11000110011011010100110101011000 -
b11101001110011110000010010110010 .
0/
b01110011010110000001011000110101 0
b10110100001100100011101111111101 1
b01010110110100010000100001011100 2
03
14
15
b000 6
b0000 7
08
b1100 9
b0110 :
b100 ;
#1
04
#2
b00000000000000000000000000000001 *
b00000000000000000000000000000000 +
b00000000000000000000000000000000 -
b00000000000000000000000000000000 .
1/
b00000000000000000000000000000000 0
b00000000000000000000000000001010 1
b00000000000000000000000000000000 2
14
05
b000 ;
#3
04
#4
14
#5
04
#6
b00000000000000000000000000000100 ,
b00000000000000000000000000000001 0
14
15
b0000 9
#7
04
#8
b00000000000000000000000001100100 +
b00000000000000000000000000000011 ,
b00000000000000000000000001100100 -
0/
b00000000000000000000000000000010 0
14
b001 6
#9
04
#10
b00000000000000000000000000000100 ,
1/
b00000000000000000000000000000001 0
b00000000000000000000000000001001 1
14
b000 6
#11
04
#12
b00000000000000000000000011001000 +
b00000000000000000000000000000011 ,
b00000000000000000000000011001000 -
0/
b00000000000000000000000000000010 0
b00000000000000000000000000001010 1
14
b001 6
#13
04
#14
b00000000000000000000000000000100 ,
1/
b00000000000000000000000000000001 0
b00000000000000000000000000001001 1
14
b000 6
#15
04
#16
b00000000000000000000000100101100 +
b00000000000000000000000000000011 ,
b00000000000000000000000100101100 -
0/
b00000000000000000000000000000010 0
b00000000000000000000000000001010 1
14
b001 6
#17
04
#18
b00000000000000000000000000000100 ,
1/
b00000000000000000000000000000001 0
b00000000000000000000000000001001 1
14
b000 6
#19
04
#20
b00000000000000000000000110010000 +
b00000000000000000000000000000011 ,
b00000000000000000000000110010000 -
0/
b00000000000000000000000000000010 0
b00000000000000000000000000001010 1
14
b001 6
#21
04
#22
b00000000000000000000000000000100 ,
1/
b00000000000000000000000000000001 0
b00000000000000000000000000001001 1
14
b000 6
b0001 9
#23
04
#24
b00000000000000000000000111110100 +
b00000000000000000000000000000011 ,
b00000000000000000000000111110100 -
0/
b00000000000000000000000000000010 0
b00000000000000000000000000001010 1
14
b001 6
#25
04
#26
b00000000000000000000000000000100 ,
1/
b00000000000000000000000000000001 0
b00000000000000000000000000001001 1
14
b000 6
b0011 9
#27
04
#28
b00000000000000000000000000001000 1
14
#29
04
#30
b00000000000000000000000000000000 +
b00000000000000000000000000000000 -
b00000000000000000000000000000000 0
b00000000000000000000000000001010 1
14
05
#31
04
#32
14
#33
04
#34
b00000000000000000000000000000001 0
14
15
b0000 9
#35
04
#36
b00000000000000000000000111110100 +
b00000000000000000000000000000011 ,
b00000000000000000000000111110100 -
0/
b00000000000000000000000000000010 0
14
b010 6
#37
04
#38
b00000000000000000000000000000100 ,
1/
b00000000000000000000000000000001 0
b00000000000000000000000000001001 1
14
b000 6
b0011 9
#39
04
#40
b00000000000000000000001111101000 +
b00000000000000000000000000000011 ,
b00000000000000000000001111101000 -
0/
b00000000000000000000000000000010 0
b00000000000000000000000000001010 1
14
b010 6
#41
04
#42
b00000000000000000000000000000100 ,
1/
b00000000000000000000000000000001 0
b00000000000000000000000000001001 1
14
b000 6
b0111 9
#43
04
#44
b00000000000000000000010111011100 +
b00000000000000000000000000000011 ,
b00000000000000000000010111011100 -
0/
b00000000000000000000000000000010 0
b00000000000000000000000000001010 1
14
b010 6
#45
04
#46
b00000000000000000000000000000100 ,
1/
b00000000000000000000000000000001 0
b00000000000000000000000000001001 1
14
b000 6
#47
04
#48
b00000000000000000000011111010000 +
b00000000000000000000000000000011 ,
b00000000000000000000011111010000 -
0/
b00000000000000000000000000000010 0
b00000000000000000000000000001010 1
14
b010 6
#49
04
#50
b00000000000000000000000000000100 ,
1/
b00000000000000000000000000000001 0
b00000000000000000000000000001001 1
14
b000 6
b1111 9
#51
04
#52
b00000000000000000000000000001000 1
14
#53
04
#54
b00000000000000000000000000000000 +
b00000000000000000000000000000000 -
b00000000000000000000000000000000 0
b00000000000000000000000000001010 1
14
05
#55
04
#56
14
#57
04
#58
b00000000000000000000000000000001 0
14
15
b0000 9
#59
04
#60
b00000000000000000000001111101000 +
b00000000000000000000000000000011 ,
b00000000000000000000001111101000 -
0/
b00000000000000000000000000000010 0
14
b100 6
#61
04
#62
b00000000000000000000000000000100 ,
1/
b00000000000000000000000000000001 0
b00000000000000000000000000001001 1
14
b000 6
b0111 9
#63
04
#64
b00000000000000000000011111010000 +
b00000000000000000000000000000011 ,
b00000000000000000000011111010000 -
0/
b00000000000000000000000000000010 0
b00000000000000000000000000001010 1
14
b100 6
#65
04
#66
b00000000000000000000000000000100 ,
1/
b00000000000000000000000000000001 0
b00000000000000000000000000001001 1
14
b000 6
b1111 9
#67
04
#68
b00000000000000000000000000001000 1
14
#69
04
#70
b00000000000000000000000000000000 +
b00000000000000000000000000000000 -
b00000000000000000000000000000000 0
b00000000000000000000000000001010 1
14
05
#71
04
#72
14
#73
04
#74
b00000000000000000000000000000001 0
14
15
b0000 9
#75
04
#76
b00000000000000000000001111101000 +
b00000000000000000000000000000011 ,
b00000000000000000000001111101000 -
0/
b00000000000000000000000000000010 0
14
b100 6
#77
04
#78
b00000000000000000000000000000100 ,
1/
b00000000000000000000000000000001 0
b00000000000000000000000000001001 1
14
b000 6
b0111 9
#79
04
#80
b00000000000000000000011111010000 +
b00000000000000000000000000000011 ,
b00000000000000000000011111010000 -
0/
b00000000000000000000000000000010 0
b00000000000000000000000000001010 1
14
b100 6
#81
04
#82
b00000000000000000000000000000100 ,
1/
b00000000000000000000000000000001 0
b00000000000000000000000000001001 1
14
b000 6
b1111 9
#83
04
#84
b00000000000000000000101110111000 +
b00000000000000000000000000000011 ,
b00000000000000000000101110111000 -
0/
b00000000000000000000000000000010 0
b00000000000000000000000000001010 1
14
b100 6
#85
04
#86
b00000000000000000000000000000100 ,
1/
b00000000000000000000000000000001 0
b00000000000000000000000000001001 1
14
b000 6
#87
04
#88
b00000000000000000000101000101000 +
b00000000000000000000000110010000 .
0/
b00000000000000000000000000000011 0
b00000000000000000000000000001010 1
14
b0001 7
b0001 :
#89
04
#90
1/
b00000000000000000000000000000001 0
b00000000000000000000000000001001 1
14
b0000 7
#91
04
#92
b00000000000000000000000000001000 1
14
#93
04
#94
b00000000000000000000000000000111 1
14
#95
04
#96
b00000000000000000000100010011000 +
b00000000000000000000001100100000 .
0/
b00000000000000000000000000000011 0
b00000000000000000000000000001010 1
14
b0001 7
#97
04
#98
1/
b00000000000000000000000000000001 0
b00000000000000000000000000001001 1
14
b0000 7
#99
04
#100
b00000000000000000000000000001000 1
14
#101
04
#102
b00000000000000000000000000000111 1
14
#103
04
#104
b00000000000000000000011100001000 +
b00000000000000000000010010110000 .
0/
b00000000000000000000000000000011 0
b00000000000000000000000000001010 1
14
b0001 7
#105
04
#106
1/
b00000000000000000000000000000001 0
b00000000000000000000000000001001 1
14
b0000 7
b0111 9
#107
04
#108
b00000000000000000000000000001000 1
14
#109
04
#110
b00000000000000000000000000000111 1
14
#111
04
#112
b00000000000000000000010101111000 +
b00000000000000000000011001000000 .
0/
b00000000000000000000000000000011 0
b00000000000000000000000000001010 1
14
b0001 7
#113
04
#114
1/
b00000000000000000000000000000001 0
b00000000000000000000000000001001 1
14
b0000 7
#115
04
#116
b00000000000000000000000000001000 1
14
#117
04
#118
b00000000000000000000000000000111 1
14
#119
04
#120
b00000000000000000000001111101000 +
b00000000000000000000011111010000 .
0/
b00000000000000000000000000000011 0
b00000000000000000000000000001010 1
14
b0001 7
#121
04
#122
1/
b00000000000000000000000000000001 0
b00000000000000000000000000001001 1
14
b0000 7
#123
04
#124
b00000000000000000000000000001000 1
14
#125
04
#126
b00000000000000000000000000000111 1
14
#127
04
#128
b00000000000000000000001001011000 +
b00000000000000000000100101100000 .
0/
b00000000000000000000000000000011 0
b00000000000000000000000000001010 1
14
b0001 7
#129
04
#130
1/
b00000000000000000000000000000001 0
b00000000000000000000000000001001 1
14
b0000 7
b0011 9
#131
04
#132
b00000000000000000000000000001000 1
14
#133
04
#134
b00000000000000000000000000000111 1
14
#135
04
#136
b00000000000000000000000011001000 +
b00000000000000000000101011110000 .
0/
b00000000000000000000000000000011 0
b00000000000000000000000000001010 1
14
b0001 7
#137
04
#138
1/
b00000000000000000000000000000001 0
b00000000000000000000000000001001 1
14
b0000 7
b0000 9
#139
04
#140
b00000000000000000000000000001000 1
14
#141
04
#142
b00000000000000000000000000000111 1
14
#143
04
#144
b00000000000000000000000000000110 1
14
#145
04
#146
b00000000000000000000000000000101 1
14
#147
04
#148
b00000000000000000000010010110000 +
b00000000000000000000000000000011 ,
b00000000000000000000111110100000 -
0/
b00000000000000000000000000000010 0
b00000000000000000000000000001010 1
14
b100 6
#149
04
#150
b00000000000000000000000000000100 ,
1/
b00000000000000000000000000000001 0
b00000000000000000000000000001001 1
14
b000 6
b0111 9
#151
04
#152
b00000000000000000000100010011000 +
b00000000000000000000000000000011 ,
b00000000000000000001001110001000 -
0/
b00000000000000000000000000000010 0
b00000000000000000000000000001010 1
14
b100 6
#153
04
#154
b00000000000000000000000000000100 ,
1/
b00000000000000000000000000000001 0
b00000000000000000000000000001001 1
14
b000 6
b1111 9
#155
04
#156
b00000000000000000000110010000000 +
b00000000000000000000000000000011 ,
b00000000000000000001011101110000 -
0/
b00000000000000000000000000000010 0
b00000000000000000000000000001010 1
14
b100 6
#157
04
#158
b00000000000000000000000000000100 ,
1/
b00000000000000000000000000000001 0
b00000000000000000000000000001001 1
14
b000 6
#159
04
#160
b00000000000000000000101010001100 +
b00000000000000000000110011100100 .
0/
b00000000000000000000000000000011 0
b00000000000000000000000000001010 1
14
b0010 7
b0010 :
#161
04
#162
1/
b00000000000000000000000000000001 0
b00000000000000000000000000001001 1
14
b0000 7
#163
04
#164
b00000000000000000000000000001000 1
14
#165
04
#166
b00000000000000000000000000000111 1
14
#167
04
#168
b00000000000000000000100010011000 +
b00000000000000000000111011011000 .
0/
b00000000000000000000000000000011 0
b00000000000000000000000000001010 1
14
b0010 7
#169
04
#170
1/
b00000000000000000000000000000001 0
b00000000000000000000000000001001 1
14
b0000 7
#171
04
#172
b00000000000000000000000000001000 1
14
#173
04
#174
b00000000000000000000000000000111 1
14
#175
04
#176
b00000000000000000000011010100100 +
b00000000000000000001000011001100 .
0/
b00000000000000000000000000000011 0
b00000000000000000000000000001010 1
14
b0010 7
#177
04
#178
1/
b00000000000000000000000000000001 0
b00000000000000000000000000001001 1
14
b0000 7
b0111 9
#179
04
#180
b00000000000000000000000000001000 1
14
#181
04
#182
b00000000000000000000000000000111 1
14
#183
04
#184
b00000000000000000000010010110000 +
b00000000000000000001001011000000 .
0/
b00000000000000000000000000000011 0
b00000000000000000000000000001010 1
14
b0010 7
#185
04
#186
1/
b00000000000000000000000000000001 0
b00000000000000000000000000001001 1
14
b0000 7
#187
04
#188
b00000000000000000000000000001000 1
14
#189
04
#190
b00000000000000000000000000000111 1
14
#191
04
#192
b00000000000000000000001010111100 +
b00000000000000000001010010110100 .
0/
b00000000000000000000000000000011 0
b00000000000000000000000000001010 1
14
b0010 7
#193
04
#194
1/
b00000000000000000000000000000001 0
b00000000000000000000000000001001 1
14
b0000 7
b0011 9
#195
04
#196
b00000000000000000000000000001000 1
14
#197
04
#198
b00000000000000000000000000000111 1
14
#199
04
#200
b00000000000000000000000011001000 +
b00000000000000000001011010101000 .
0/
b00000000000000000000000000000011 0
b00000000000000000000000000001010 1
14
b0010 7
#201
04
#202
1/
b00000000000000000000000000000001 0
b00000000000000000000000000001001 1
14
b0000 7
b0000 9
#203
04
#204
b00000000000000000000000000001000 1
14
#205
04
#206
b00000000000000000000000000000111 1
14
#207
04
#208
b00000000000000000000000100101100 +
b00000000000000000000000000000011 ,
b00000000000000000001011111010100 -
0/
b00000000000000000000000000000010 0
b00000000000000000000000000001010 1
14
b001 6
#209
04
#210
b00000000000000000000000000000100 ,
1/
b00000000000000000000000000000001 0
b00000000000000000000000000001001 1
14
b000 6
#211
04
#212
b00000000000000000000000110010000 +
b00000000000000000000000000000011 ,
b00000000000000000001100000111000 -
0/
b00000000000000000000000000000010 0
b00000000000000000000000000001010 1
14
b001 6
#213
04
#214
b00000000000000000000000000000100 ,
1/
b00000000000000000000000000000001 0
b00000000000000000000000000001001 1
14
b000 6
b0001 9
#215
04
#216
b00000000000000000000010101111000 +
b00000000000000000000000000000011 ,
b00000000000000000001110000100000 -
0/
b00000000000000000000000000000010 0
b00000000000000000000000000001010 1
14
b100 6
#217
04
#218
b00000000000000000000000000000100 ,
1/
b00000000000000000000000000000001 0
b00000000000000000000000000001001 1
14
b000 6
b0111 9
#219
04
#220
b00000000000000000000100101100000 +
b00000000000000000000000000000011 ,
b00000000000000000010000000001000 -
0/
b00000000000000000000000000000010 0
b00000000000000000000000000001010 1
14
b100 6
#221
04
#222
b00000000000000000000000000000100 ,
1/
b00000000000000000000000000000001 0
b00000000000000000000000000001001 1
14
b000 6
b1111 9
#223
04
#224
b00000000000000000000110101001000 +
b00000000000000000000000000000011 ,
b00000000000000000010001111110000 -
0/
b00000000000000000000000000000010 0
b00000000000000000000000000001010 1
14
b100 6
#225
04
#226
b00000000000000000000000000000100 ,
1/
b00000000000000000000000000000001 0
b00000000000000000000000000001001 1
14
b000 6
#227
04
#228
b00000000000000000000100101100000 +
b00000000000000000001101010010000 .
0/
b00000000000000000000000000000011 0
b00000000000000000000000000001010 1
14
b0100 7
b0100 :
#229
04
#230
1/
b00000000000000000000000000000001 0
b00000000000000000000000000001001 1
14
b0000 7
#231
04
#232
b00000000000000000000000000001000 1
14
#233
04
#234
b00000000000000000000000000000111 1
14
#235
04
#236
b00000000000000000000010101111000 +
b00000000000000000001111001111000 .
0/
b00000000000000000000000000000011 0
b00000000000000000000000000001010 1
14
b0100 7
#237
04
#238
1/
b00000000000000000000000000000001 0
b00000000000000000000000000001001 1
14
b0000 7
b0111 9
#239
04
#240
b00000000000000000000000000001000 1
14
#241
04
#242
b00000000000000000000000000000111 1
14
#243
04
#244
b00000000000000000000000110010000 +
b00000000000000000010001001100000 .
0/
b00000000000000000000000000000011 0
b00000000000000000000000000001010 1
14
b0100 7
#245
04
#246
1/
b00000000000000000000000000000001 0
b00000000000000000000000000001001 1
14
b0000 7
b0001 9
#247
04
#248
b00000000000000000000000000001000 1
14
#249
04
#250
b00000000000000000000000000000111 1
14
#251
04
#252
b00000000000000000000010101111000 +
b00000000000000000000000000000011 ,
b00000000000000000010011111011000 -
0/
b00000000000000000000000000000010 0
b00000000000000000000000000001010 1
14
b100 6
#253
04
#254
b00000000000000000000000000000100 ,
1/
b00000000000000000000000000000001 0
b00000000000000000000000000001001 1
14
b000 6
b0111 9
#255
04
#256
b00000000000000000000100101100000 +
b00000000000000000000000000000011 ,
b00000000000000000010101111000000 -
0/
b00000000000000000000000000000010 0
b00000000000000000000000000001010 1
14
b100 6
#257
04
#258
b00000000000000000000000000000100 ,
1/
b00000000000000000000000000000001 0
b00000000000000000000000000001001 1
14
b000 6
b1111 9
#259
04
#260
b00000000000000000000110101001000 +
b00000000000000000000000000000011 ,
b00000000000000000010111110101000 -
0/
b00000000000000000000000000000010 0
b00000000000000000000000000001010 1
14
b100 6
#261
04
#262
b00000000000000000000000000000100 ,
1/
b00000000000000000000000000000001 0
b00000000000000000000000000001001 1
14
b000 6
#263
04
#264
b00000000000000000000010101111000 +
b00000000000000000010101000110000 .
0/
b00000000000000000000000000000011 0
b00000000000000000000000000001010 1
14
b1000 7
b1000 :
#265
04
#266
1/
b00000000000000000000000000000001 0
b00000000000000000000000000001001 1
14
b0000 7
b0111 9
#267
04
#268
b00000000000000000000000000001000 1
14
#269
04
#270
b00000000000000000000000000000111 1
14
#271
04
#272
b00000000000000000000100101100000 +
b00000000000000000000000000000011 ,
b00000000000000000011001110010000 -
0/
b00000000000000000000000000000010 0
b00000000000000000000000000001010 1
14
b100 6
#273
04
#274
b00000000000000000000000000000100 ,
1/
b00000000000000000000000000000001 0
b00000000000000000000000000001001 1
14
b000 6
b1111 9
#275
04
#276
b00000000000000000000000110010000 +
b00000000000000000011001000000000 .
0/
b00000000000000000000000000000011 0
b00000000000000000000000000001010 1
14
b1000 7
#277
04
#278
1/
b00000000000000000000000000000001 0
b00000000000000000000000000001001 1
14
b0000 7
b0001 9
#279
04
#280
b00000000000000000000000000001000 1
14
#281
04
#282
b00000000000000000000000000000111 1
14
#283
04
#284
b00000000000000000000000111110100 +
b00000000000000000000000000000011 ,
b00000000000000000011001111110100 -
0/
b00000000000000000000000000000010 0
b00000000000000000000000000001010 1
14
b001 6
#285
04
#286
b00000000000000000000000000000100 ,
1/
b00000000000000000000000000000001 0
b00000000000000000000000000001001 1
14
b000 6
b0011 9
#287
04
#288
b00000000000000000000001001011000 +
b00000000000000000000000000000011 ,
b00000000000000000011010001011000 -
0/
b00000000000000000000000000000010 0
b00000000000000000000000000001010 1
14
b001 6
#289
04
#290
b00000000000000000000000000000100 ,
1/
b00000000000000000000000000000001 0
b00000000000000000000000000001001 1
14
b000 6
#291
04
#292
b00000000000000000000001010111100 +
b00000000000000000000000000000011 ,
b00000000000000000011010010111100 -
0/
b00000000000000000000000000000010 0
b00000000000000000000000000001010 1
14
b001 6
#293
04
#294
b00000000000000000000000000000100 ,
1/
b00000000000000000000000000000001 0
b00000000000000000000000000001001 1
14
b000 6
#295
04
#296
b00000000000000000000001100100000 +
b00000000000000000000000000000011 ,
b00000000000000000011010100100000 -
0/
b00000000000000000000000000000010 0
b00000000000000000000000000001010 1
14
b001 6
#297
04
#298
b00000000000000000000000000000100 ,
1/
b00000000000000000000000000000001 0
b00000000000000000000000000001001 1
14
b000 6
#299
04
#300
b00000000000000000000010100010100 +
b00000000000000000000000000000011 ,
b00000000000000000011011100010100 -
0/
b00000000000000000000000000000010 0
b00000000000000000000000000001010 1
14
b010 6
#301
04
#302
b00000000000000000000000000000100 ,
1/
b00000000000000000000000000000001 0
b00000000000000000000000000001001 1
14
b000 6
b0111 9
#303
04
